Workbook

Sheet Dataset
A1: Project_ID | B1: 프로젝트명 | C1: 투자유형 | D1: 세부유형 | E1: 자본구조1(SAP) | F1: 약정통화 | G1: 최초인출일 | H1: 만기일 | I1: 빈티지 | J1: 종목ID/트렌치ID(대표) | K1: Asset_Class_EN | L1: Asset_Name_EN | M1: Manager_EN | N1: Manager_EN_2 | O1: Region_EN | P1: Strategy | Q1: Sector | R1: 약정금액(원화)_합계 | S1: 실행(누적)_합계 | T1: 상환(누적)_합계 | U1: 장부가액(원화)_합계 | V1: 평가금액(원화)_합계 | W1: 수익률(원화,누적)_대표 | X1: 트렌치수 | Y1: 하위자산수
A2: BS00000004 | B2: =IF($A2="","",IFERROR(VLOOKUP($A2,AI_PF!$A:$D,4,FALSE),"")) -> 서울고속도로 리파이낸싱 | C2: =IF($A2="","",IFERROR(VLOOKUP($A2,AI_PF!$A:$G,7,FALSE),"")) -> BTO | D2: =IF($A2="","",IFERROR(VLOOKUP($A2,AI_PF!$A:$H,8,FALSE),"")) -> 도로 | E2: =IF($A2="","",IFERROR(VLOOKUP($A2,AI_PF!$A:$N,14,FALSE),"")) -> 대출 | F2: =IF($A2="","",IFERROR(VLOOKUP($A2,AI_PF!$A:$R,18,FALSE),"")) -> KRW | G2: =IF($A2="","",IFERROR(VLOOKUP($A2,AI_PF!$A:$T,20,FALSE),"")) -> 40723 | H2: =IF($A2="","",IFERROR(VLOOKUP($A2,AI_PF!$A:$V,22,FALSE),"")) -> 48394 | I2: =IF($A2="","",IFERROR(VLOOKUP($A2,AI_PF!$A:$EU,151,FALSE),"")) -> ~2016 | J2: =IF($A2="","",IFERROR(VLOOKUP($A2,AI_PF!$A:$C,3,FALSE),"")) -> 6000000000138 | K2: =IF($A2="","",IFERROR(VLOOKUP($A2,Data_Raw!$A:$G,2,FALSE),"")) -> Infrastructure | L2: =IF($A2="","",IFERROR(VLOOKUP($A2,Data_Raw!$A:$G,3,FALSE),"")) -> 서울고속도로 리파이낸싱 | M2: =IF($A2="","",IFERROR(VLOOKUP($A2,Data_Raw!$A:$G,4,FALSE),"")) -> 칸서스자산운용 | N2: =IF($A2="","",IFERROR(VLOOKUP($A2,AI_PF!$A:$EU,29,FALSE),"")) -> 해당없음 | O2: =IF($A2="","",IFERROR(VLOOKUP($A2,Data_Raw!$A:$G,5,FALSE),"")) -> KOR | P2: =IF($A2="","",IFERROR(VLOOKUP($A2,Data_Raw!$A:$G,6,FALSE),"")) -> BTO | Q2: =IF($A2="","",IFERROR(VLOOKUP($A2,Data_Raw!$A:$G,7,FALSE),"")) -> Transportation | R2: =IF($A2="","",SUMIFS(AI_PF!$AP:$AP,AI_PF!$A:$A,$A2)) -> 14000000000 | S2: =IF($A2="","",SUMIFS(AI_PF!$AW:$AW,AI_PF!$A:$A,$A2)) -> 14000000000 | T2: =IF($A2="","",SUMIFS(AI_PF!$AZ:$AZ,AI_PF!$A:$A,$A2)) -> 4737712417 | U2: =IF($A2="","",SUMIFS(AI_PF!$CA:$CA,AI_PF!$A:$A,$A2)) -> 9275000000 | V2: =IF($A2="","",SUMIFS(AI_PF!$CE:$CE,AI_PF!$A:$A,$A2)) -> 9262287583 | W2: =IF($A2="","",IFERROR(VLOOKUP($A2,AI_PF!$A:$CO,93,FALSE),"")) -> 7.4321597 | X2: =IF($A2="","",COUNTIF(AI_PF!$A:$A,$A2)) -> 1 | Y2: =IF($A2="","",COUNTIF(LookThrough!$A:$A,J2)) -> 0
A3: BS00000005 | B3: =IF($A3="","",IFERROR(VLOOKUP($A3,AI_PF!$A:$D,4,FALSE),"")) -> 신공항하이웨이 리파이낸싱 (지분) | C3: =IF($A3="","",IFERROR(VLOOKUP($A3,AI_PF!$A:$G,7,FALSE),"")) -> BTO | D3: =IF($A3="","",IFERROR(VLOOKUP($A3,AI_PF!$A:$H,8,FALSE),"")) -> 도로 | E3: =IF($A3="","",IFERROR(VLOOKUP($A3,AI_PF!$A:$N,14,FALSE),"")) -> 출자 | F3: =IF($A3="","",IFERROR(VLOOKUP($A3,AI_PF!$A:$R,18,FALSE),"")) -> KRW | G3: =IF($A3="","",IFERROR(VLOOKUP($A3,AI_PF!$A:$T,20,FALSE),"")) -> 37984 | H3: =IF($A3="","",IFERROR(VLOOKUP($A3,AI_PF!$A:$V,22,FALSE),"")) -> 2958465 | I3: =IF($A3="","",IFERROR(VLOOKUP($A3,AI_PF!$A:$EU,151,FALSE),"")) -> ~2016 | J3: =IF($A3="","",IFERROR(VLOOKUP($A3,AI_PF!$A:$C,3,FALSE),"")) -> 100001946 | K3: =IF($A3="","",IFERROR(VLOOKUP($A3,Data_Raw!$A:$G,2,FALSE),"")) -> Infrastructure | L3: =IF($A3="","",IFERROR(VLOOKUP($A3,Data_Raw!$A:$G,3,FALSE),"")) -> 신공항하이웨이 리파이낸싱 (지분) | M3: =IF($A3="","",IFERROR(VLOOKUP($A3,Data_Raw!$A:$G,4,FALSE),"")) -> 우리은행 | N3: =IF($A3="","",IFERROR(VLOOKUP($A3,AI_PF!$A:$EU,29,FALSE),"")) -> 해당없음 | O3: =IF($A3="","",IFERROR(VLOOKUP($A3,Data_Raw!$A:$G,5,FALSE),"")) -> KOR | P3: =IF($A3="","",IFERROR(VLOOKUP($A3,Data_Raw!$A:$G,6,FALSE),"")) -> BTO | Q3: =IF($A3="","",IFERROR(VLOOKUP($A3,Data_Raw!$A:$G,7,FALSE),"")) -> Transportation | R3: =IF($A3="","",SUMIFS(AI_PF!$AP:$AP,AI_PF!$A:$A,$A3)) -> 8453000000 | S3: =IF($A3="","",SUMIFS(AI_PF!$AW:$AW,AI_PF!$A:$A,$A3)) -> 0 | T3: =IF($A3="","",SUMIFS(AI_PF!$AZ:$AZ,AI_PF!$A:$A,$A3)) -> 5031495000 | U3: =IF($A3="","",SUMIFS(AI_PF!$CA:$CA,AI_PF!$A:$A,$A3)) -> 7992109627 | V3: =IF($A3="","",SUMIFS(AI_PF!$CE:$CE,AI_PF!$A:$A,$A3)) -> 7992109627 | W3: =IF($A3="","",IFERROR(VLOOKUP($A3,AI_PF!$A:$CO,93,FALSE),"")) -> 0 | X3: =IF($A3="","",COUNTIF(AI_PF!$A:$A,$A3)) -> 1 | Y3: =IF($A3="","",COUNTIF(LookThrough!$A:$A,J3)) -> 0
A4: BS00000009 | B4: =IF($A4="","",IFERROR(VLOOKUP($A4,AI_PF!$A:$D,4,FALSE),"")) -> 광주제2순환도로 리파이낸싱 | C4: =IF($A4="","",IFERROR(VLOOKUP($A4,AI_PF!$A:$G,7,FALSE),"")) -> BTO | D4: =IF($A4="","",IFERROR(VLOOKUP($A4,AI_PF!$A:$H,8,FALSE),"")) -> 도로 | E4: =IF($A4="","",IFERROR(VLOOKUP($A4,AI_PF!$A:$N,14,FALSE),"")) -> 대출 | F4: =IF($A4="","",IFERROR(VLOOKUP($A4,AI_PF!$A:$R,18,FALSE),"")) -> KRW | G4: =IF($A4="","",IFERROR(VLOOKUP($A4,AI_PF!$A:$T,20,FALSE),"")) -> 41074 | H4: =IF($A4="","",IFERROR(VLOOKUP($A4,AI_PF!$A:$V,22,FALSE),"")) -> 48196 | I4: =IF($A4="","",IFERROR(VLOOKUP($A4,AI_PF!$A:$EU,151,FALSE),"")) -> ~2016 | J4: =IF($A4="","",IFERROR(VLOOKUP($A4,AI_PF!$A:$C,3,FALSE),"")) -> 6000000000220 | K4: =IF($A4="","",IFERROR(VLOOKUP($A4,Data_Raw!$A:$G,2,FALSE),"")) -> Infrastructure | L4: =IF($A4="","",IFERROR(VLOOKUP($A4,Data_Raw!$A:$G,3,FALSE),"")) -> 광주제2순환도로 리파이낸싱 | M4: =IF($A4="","",IFERROR(VLOOKUP($A4,Data_Raw!$A:$G,4,FALSE),"")) -> 신한자산운용 | N4: =IF($A4="","",IFERROR(VLOOKUP($A4,AI_PF!$A:$EU,29,FALSE),"")) -> 해당없음 | O4: =IF($A4="","",IFERROR(VLOOKUP($A4,Data_Raw!$A:$G,5,FALSE),"")) -> KOR | P4: =IF($A4="","",IFERROR(VLOOKUP($A4,Data_Raw!$A:$G,6,FALSE),"")) -> BTO | Q4: =IF($A4="","",IFERROR(VLOOKUP($A4,Data_Raw!$A:$G,7,FALSE),"")) -> Transportation | R4: =IF($A4="","",SUMIFS(AI_PF!$AP:$AP,AI_PF!$A:$A,$A4)) -> 48820000000 | S4: =IF($A4="","",SUMIFS(AI_PF!$AW:$AW,AI_PF!$A:$A,$A4)) -> 38817500000 | T4: =IF($A4="","",SUMIFS(AI_PF!$AZ:$AZ,AI_PF!$A:$A,$A4)) -> 13037382925 | U4: =IF($A4="","",SUMIFS(AI_PF!$CA:$CA,AI_PF!$A:$A,$A4)) -> 30509431114 | V4: =IF($A4="","",SUMIFS(AI_PF!$CE:$CE,AI_PF!$A:$A,$A4)) -> 41731507289 | W4: =IF($A4="","",IFERROR(VLOOKUP($A4,AI_PF!$A:$CO,93,FALSE),"")) -> 12.543752 | X4: =IF($A4="","",COUNTIF(AI_PF!$A:$A,$A4)) -> 3 | Y4: =IF($A4="","",COUNTIF(LookThrough!$A:$A,J4)) -> 0
A5: BS00000021 | B5: =IF($A5="","",IFERROR(VLOOKUP($A5,AI_PF!$A:$D,4,FALSE),"")) -> 흥국 인프라 사모특별자산투자신탁 2호 (대구동부순환도로 리파이낸싱) | C5: =IF($A5="","",IFERROR(VLOOKUP($A5,AI_PF!$A:$G,7,FALSE),"")) -> BTO | D5: =IF($A5="","",IFERROR(VLOOKUP($A5,AI_PF!$A:$H,8,FALSE),"")) -> 도로 | E5: =IF($A5="","",IFERROR(VLOOKUP($A5,AI_PF!$A:$N,14,FALSE),"")) -> 수익증권 | F5: =IF($A5="","",IFERROR(VLOOKUP($A5,AI_PF!$A:$R,18,FALSE),"")) -> KRW | G5: =IF($A5="","",IFERROR(VLOOKUP($A5,AI_PF!$A:$T,20,FALSE),"")) -> 41085 | H5: =IF($A5="","",IFERROR(VLOOKUP($A5,AI_PF!$A:$V,22,FALSE),"")) -> 46562 | I5: =IF($A5="","",IFERROR(VLOOKUP($A5,AI_PF!$A:$EU,151,FALSE),"")) -> ~2016 | J5: =IF($A5="","",IFERROR(VLOOKUP($A5,AI_PF!$A:$C,3,FALSE),"")) -> 200000318 | K5: =IF($A5="","",IFERROR(VLOOKUP($A5,Data_Raw!$A:$G,2,FALSE),"")) -> Infrastructure | L5: =IF($A5="","",IFERROR(VLOOKUP($A5,Data_Raw!$A:$G,3,FALSE),"")) -> 흥국 인프라 사모특별자산투자신탁 2호 (대구동부순환도로 리파이낸싱) | M5: =IF($A5="","",IFERROR(VLOOKUP($A5,Data_Raw!$A:$G,4,FALSE),"")) -> 흥국자산운용 | N5: =IF($A5="","",IFERROR(VLOOKUP($A5,AI_PF!$A:$EU,29,FALSE),"")) -> 해당없음 | O5: =IF($A5="","",IFERROR(VLOOKUP($A5,Data_Raw!$A:$G,5,FALSE),"")) -> KOR | P5: =IF($A5="","",IFERROR(VLOOKUP($A5,Data_Raw!$A:$G,6,FALSE),"")) -> BTO | Q5: =IF($A5="","",IFERROR(VLOOKUP($A5,Data_Raw!$A:$G,7,FALSE),"")) -> Transportation | R5: =IF($A5="","",SUMIFS(AI_PF!$AP:$AP,AI_PF!$A:$A,$A5)) -> 90000000000 | S5: =IF($A5="","",SUMIFS(AI_PF!$AW:$AW,AI_PF!$A:$A,$A5)) -> 90000000000 | T5: =IF($A5="","",SUMIFS(AI_PF!$AZ:$AZ,AI_PF!$A:$A,$A5)) -> 85685503961 | U5: =IF($A5="","",SUMIFS(AI_PF!$CA:$CA,AI_PF!$A:$A,$A5)) -> 4351144467 | V5: =IF($A5="","",SUMIFS(AI_PF!$CE:$CE,AI_PF!$A:$A,$A5)) -> 4318302029 | W5: =IF($A5="","",IFERROR(VLOOKUP($A5,AI_PF!$A:$CO,93,FALSE),"")) -> 4.6826825 | X5: =IF($A5="","",COUNTIF(AI_PF!$A:$A,$A5)) -> 1 | Y5: =IF($A5="","",COUNTIF(LookThrough!$A:$A,J5)) -> 2
A6: BS00000029 | B6: =IF($A6="","",IFERROR(VLOOKUP($A6,AI_PF!$A:$D,4,FALSE),"")) -> 푸른김해지키미 | C6: =IF($A6="","",IFERROR(VLOOKUP($A6,AI_PF!$A:$G,7,FALSE),"")) -> BTL | D6: =IF($A6="","",IFERROR(VLOOKUP($A6,AI_PF!$A:$H,8,FALSE),"")) -> 하수관거 | E6: =IF($A6="","",IFERROR(VLOOKUP($A6,AI_PF!$A:$N,14,FALSE),"")) -> 대출 | F6: =IF($A6="","",IFERROR(VLOOKUP($A6,AI_PF!$A:$R,18,FALSE),"")) -> KRW | G6: =IF($A6="","",IFERROR(VLOOKUP($A6,AI_PF!$A:$T,20,FALSE),"")) -> 40289 | H6: =IF($A6="","",IFERROR(VLOOKUP($A6,AI_PF!$A:$V,22,FALSE),"")) -> 2958465 | I6: =IF($A6="","",IFERROR(VLOOKUP($A6,AI_PF!$A:$EU,151,FALSE),"")) -> ~2016 | J6: =IF($A6="","",IFERROR(VLOOKUP($A6,AI_PF!$A:$C,3,FALSE),"")) -> 6000000000209 | K6: =IF($A6="","",IFERROR(VLOOKUP($A6,Data_Raw!$A:$G,2,FALSE),"")) -> Infrastructure | L6: =IF($A6="","",IFERROR(VLOOKUP($A6,Data_Raw!$A:$G,3,FALSE),"")) -> 푸른김해지키미 | M6: =IF($A6="","",IFERROR(VLOOKUP($A6,Data_Raw!$A:$G,4,FALSE),"")) -> IBK기업은행 | N6: =IF($A6="","",IFERROR(VLOOKUP($A6,AI_PF!$A:$EU,29,FALSE),"")) -> 해당없음 | O6: =IF($A6="","",IFERROR(VLOOKUP($A6,Data_Raw!$A:$G,5,FALSE),"")) -> KOR | P6: =IF($A6="","",IFERROR(VLOOKUP($A6,Data_Raw!$A:$G,6,FALSE),"")) -> BTL | Q6: =IF($A6="","",IFERROR(VLOOKUP($A6,Data_Raw!$A:$G,7,FALSE),"")) -> Environmental | R6: =IF($A6="","",SUMIFS(AI_PF!$AP:$AP,AI_PF!$A:$A,$A6)) -> 20419035102 | S6: =IF($A6="","",SUMIFS(AI_PF!$AW:$AW,AI_PF!$A:$A,$A6)) -> 16023270000 | T6: =IF($A6="","",SUMIFS(AI_PF!$AZ:$AZ,AI_PF!$A:$A,$A6)) -> 12569126780 | U6: =IF($A6="","",SUMIFS(AI_PF!$CA:$CA,AI_PF!$A:$A,$A6)) -> 4888599289 | V6: =IF($A6="","",SUMIFS(AI_PF!$CE:$CE,AI_PF!$A:$A,$A6)) -> 4865152924 | W6: =IF($A6="","",IFERROR(VLOOKUP($A6,AI_PF!$A:$CO,93,FALSE),"")) -> 3.5150033 | X6: =IF($A6="","",COUNTIF(AI_PF!$A:$A,$A6)) -> 3 | Y6: =IF($A6="","",COUNTIF(LookThrough!$A:$A,J6)) -> 0
A7: BS00000030 | B7: =IF($A7="","",IFERROR(VLOOKUP($A7,AI_PF!$A:$D,4,FALSE),"")) -> 청정상주 | C7: =IF($A7="","",IFERROR(VLOOKUP($A7,AI_PF!$A:$G,7,FALSE),"")) -> BTL | D7: =IF($A7="","",IFERROR(VLOOKUP($A7,AI_PF!$A:$H,8,FALSE),"")) -> 하수관거 | E7: =IF($A7="","",IFERROR(VLOOKUP($A7,AI_PF!$A:$N,14,FALSE),"")) -> 대출 | F7: =IF($A7="","",IFERROR(VLOOKUP($A7,AI_PF!$A:$R,18,FALSE),"")) -> KRW | G7: =IF($A7="","",IFERROR(VLOOKUP($A7,AI_PF!$A:$T,20,FALSE),"")) -> 40239 | H7: =IF($A7="","",IFERROR(VLOOKUP($A7,AI_PF!$A:$V,22,FALSE),"")) -> 2958465 | I7: =IF($A7="","",IFERROR(VLOOKUP($A7,AI_PF!$A:$EU,151,FALSE),"")) -> ~2016 | J7: =IF($A7="","",IFERROR(VLOOKUP($A7,AI_PF!$A:$C,3,FALSE),"")) -> 6000000000250 | K7: =IF($A7="","",IFERROR(VLOOKUP($A7,Data_Raw!$A:$G,2,FALSE),"")) -> Infrastructure | L7: =IF($A7="","",IFERROR(VLOOKUP($A7,Data_Raw!$A:$G,3,FALSE),"")) -> 청정상주 | M7: =IF($A7="","",IFERROR(VLOOKUP($A7,Data_Raw!$A:$G,4,FALSE),"")) -> IBK기업은행 | N7: =IF($A7="","",IFERROR(VLOOKUP($A7,AI_PF!$A:$EU,29,FALSE),"")) -> 해당없음 | O7: =IF($A7="","",IFERROR(VLOOKUP($A7,Data_Raw!$A:$G,5,FALSE),"")) -> KOR | P7: =IF($A7="","",IFERROR(VLOOKUP($A7,Data_Raw!$A:$G,6,FALSE),"")) -> BTL | Q7: =IF($A7="","",IFERROR(VLOOKUP($A7,Data_Raw!$A:$G,7,FALSE),"")) -> Environmental | R7: =IF($A7="","",SUMIFS(AI_PF!$AP:$AP,AI_PF!$A:$A,$A7)) -> 16529000000 | S7: =IF($A7="","",SUMIFS(AI_PF!$AW:$AW,AI_PF!$A:$A,$A7)) -> 15180000000 | T7: =IF($A7="","",SUMIFS(AI_PF!$AZ:$AZ,AI_PF!$A:$A,$A7)) -> 11646513839 | U7: =IF($A7="","",SUMIFS(AI_PF!$CA:$CA,AI_PF!$A:$A,$A7)) -> 4857565965 | V7: =IF($A7="","",SUMIFS(AI_PF!$CE:$CE,AI_PF!$A:$A,$A7)) -> 4856859126 | W7: =IF($A7="","",IFERROR(VLOOKUP($A7,AI_PF!$A:$CO,93,FALSE),"")) -> 3.7224182 | X7: =IF($A7="","",COUNTIF(AI_PF!$A:$A,$A7)) -> 3 | Y7: =IF($A7="","",COUNTIF(LookThrough!$A:$A,J7)) -> 0
A8: BS00000034 | B8: =IF($A8="","",IFERROR(VLOOKUP($A8,AI_PF!$A:$D,4,FALSE),"")) -> 남양강진씨앤지 | C8: =IF($A8="","",IFERROR(VLOOKUP($A8,AI_PF!$A:$G,7,FALSE),"")) -> BTL | D8: =IF($A8="","",IFERROR(VLOOKUP($A8,AI_PF!$A:$H,8,FALSE),"")) -> 하수관거 | E8: =IF($A8="","",IFERROR(VLOOKUP($A8,AI_PF!$A:$N,14,FALSE),"")) -> 대출 | F8: =IF($A8="","",IFERROR(VLOOKUP($A8,AI_PF!$A:$R,18,FALSE),"")) -> KRW | G8: =IF($A8="","",IFERROR(VLOOKUP($A8,AI_PF!$A:$T,20,FALSE),"")) -> 40231 | H8: =IF($A8="","",IFERROR(VLOOKUP($A8,AI_PF!$A:$V,22,FALSE),"")) -> 2958465 | I8: =IF($A8="","",IFERROR(VLOOKUP($A8,AI_PF!$A:$EU,151,FALSE),"")) -> ~2016 | J8: =IF($A8="","",IFERROR(VLOOKUP($A8,AI_PF!$A:$C,3,FALSE),"")) -> 6000000000127 | K8: =IF($A8="","",IFERROR(VLOOKUP($A8,Data_Raw!$A:$G,2,FALSE),"")) -> Infrastructure | L8: =IF($A8="","",IFERROR(VLOOKUP($A8,Data_Raw!$A:$G,3,FALSE),"")) -> 남양강진씨앤지 | M8: =IF($A8="","",IFERROR(VLOOKUP($A8,Data_Raw!$A:$G,4,FALSE),"")) -> IBK기업은행 | N8: =IF($A8="","",IFERROR(VLOOKUP($A8,AI_PF!$A:$EU,29,FALSE),"")) -> 해당없음 | O8: =IF($A8="","",IFERROR(VLOOKUP($A8,Data_Raw!$A:$G,5,FALSE),"")) -> KOR | P8: =IF($A8="","",IFERROR(VLOOKUP($A8,Data_Raw!$A:$G,6,FALSE),"")) -> BTL | Q8: =IF($A8="","",IFERROR(VLOOKUP($A8,Data_Raw!$A:$G,7,FALSE),"")) -> Environmental | R8: =IF($A8="","",SUMIFS(AI_PF!$AP:$AP,AI_PF!$A:$A,$A8)) -> 8152918700 | S8: =IF($A8="","",SUMIFS(AI_PF!$AW:$AW,AI_PF!$A:$A,$A8)) -> 7632860000 | T8: =IF($A8="","",SUMIFS(AI_PF!$AZ:$AZ,AI_PF!$A:$A,$A8)) -> 5971592320 | U8: =IF($A8="","",SUMIFS(AI_PF!$CA:$CA,AI_PF!$A:$A,$A8)) -> 2181658700 | V8: =IF($A8="","",SUMIFS(AI_PF!$CE:$CE,AI_PF!$A:$A,$A8)) -> 2181326380 | W8: =IF($A8="","",IFERROR(VLOOKUP($A8,AI_PF!$A:$CO,93,FALSE),"")) -> 3.8884949 | X8: =IF($A8="","",COUNTIF(AI_PF!$A:$A,$A8)) -> 4 | Y8: =IF($A8="","",COUNTIF(LookThrough!$A:$A,J8)) -> 0
A9: BS00000035 | B9: =IF($A9="","",IFERROR(VLOOKUP($A9,AI_PF!$A:$D,4,FALSE),"")) -> 울산1지구 교육사업 | C9: =IF($A9="","",IFERROR(VLOOKUP($A9,AI_PF!$A:$G,7,FALSE),"")) -> BTL | D9: =IF($A9="","",IFERROR(VLOOKUP($A9,AI_PF!$A:$H,8,FALSE),"")) -> 교육시설 | E9: =IF($A9="","",IFERROR(VLOOKUP($A9,AI_PF!$A:$N,14,FALSE),"")) -> 대출 | F9: =IF($A9="","",IFERROR(VLOOKUP($A9,AI_PF!$A:$R,18,FALSE),"")) -> KRW | G9: =IF($A9="","",IFERROR(VLOOKUP($A9,AI_PF!$A:$T,20,FALSE),"")) -> 39668 | H9: =IF($A9="","",IFERROR(VLOOKUP($A9,AI_PF!$A:$V,22,FALSE),"")) -> 46310 | I9: =IF($A9="","",IFERROR(VLOOKUP($A9,AI_PF!$A:$EU,151,FALSE),"")) -> ~2016 | J9: =IF($A9="","",IFERROR(VLOOKUP($A9,AI_PF!$A:$C,3,FALSE),"")) -> 6000000000139 | K9: =IF($A9="","",IFERROR(VLOOKUP($A9,Data_Raw!$A:$G,2,FALSE),"")) -> Infrastructure | L9: =IF($A9="","",IFERROR(VLOOKUP($A9,Data_Raw!$A:$G,3,FALSE),"")) -> 울산1지구 교육사업 | M9: =IF($A9="","",IFERROR(VLOOKUP($A9,Data_Raw!$A:$G,4,FALSE),"")) -> IBK기업은행 | N9: =IF($A9="","",IFERROR(VLOOKUP($A9,AI_PF!$A:$EU,29,FALSE),"")) -> 해당없음 | O9: =IF($A9="","",IFERROR(VLOOKUP($A9,Data_Raw!$A:$G,5,FALSE),"")) -> KOR | P9: =IF($A9="","",IFERROR(VLOOKUP($A9,Data_Raw!$A:$G,6,FALSE),"")) -> BTL | Q9: =IF($A9="","",IFERROR(VLOOKUP($A9,Data_Raw!$A:$G,7,FALSE),"")) -> Social | R9: =IF($A9="","",SUMIFS(AI_PF!$AP:$AP,AI_PF!$A:$A,$A9)) -> 16584000000 | S9: =IF($A9="","",SUMIFS(AI_PF!$AW:$AW,AI_PF!$A:$A,$A9)) -> 16192000000 | T9: =IF($A9="","",SUMIFS(AI_PF!$AZ:$AZ,AI_PF!$A:$A,$A9)) -> 16176116078 | U9: =IF($A9="","",SUMIFS(AI_PF!$CA:$CA,AI_PF!$A:$A,$A9)) -> 15887100 | V9: =IF($A9="","",SUMIFS(AI_PF!$CE:$CE,AI_PF!$A:$A,$A9)) -> 15883922 | W9: =IF($A9="","",IFERROR(VLOOKUP($A9,AI_PF!$A:$CO,93,FALSE),"")) -> 4.3845332 | X9: =IF($A9="","",COUNTIF(AI_PF!$A:$A,$A9)) -> 10 | Y9: =IF($A9="","",COUNTIF(LookThrough!$A:$A,J9)) -> 0
A10: BS00000037 | B10: =IF($A10="","",IFERROR(VLOOKUP($A10,AI_PF!$A:$D,4,FALSE),"")) -> 울산3지구 교육사업 | C10: =IF($A10="","",IFERROR(VLOOKUP($A10,AI_PF!$A:$G,7,FALSE),"")) -> BTL | D10: =IF($A10="","",IFERROR(VLOOKUP($A10,AI_PF!$A:$H,8,FALSE),"")) -> 교육시설 | E10: =IF($A10="","",IFERROR(VLOOKUP($A10,AI_PF!$A:$N,14,FALSE),"")) -> 대출 | F10: =IF($A10="","",IFERROR(VLOOKUP($A10,AI_PF!$A:$R,18,FALSE),"")) -> KRW | G10: =IF($A10="","",IFERROR(VLOOKUP($A10,AI_PF!$A:$T,20,FALSE),"")) -> 39668 | H10: =IF($A10="","",IFERROR(VLOOKUP($A10,AI_PF!$A:$V,22,FALSE),"")) -> 46127 | I10: =IF($A10="","",IFERROR(VLOOKUP($A10,AI_PF!$A:$EU,151,FALSE),"")) -> ~2016 | J10: =IF($A10="","",IFERROR(VLOOKUP($A10,AI_PF!$A:$C,3,FALSE),"")) -> 6000000000098 | K10: =IF($A10="","",IFERROR(VLOOKUP($A10,Data_Raw!$A:$G,2,FALSE),"")) -> Infrastructure | L10: =IF($A10="","",IFERROR(VLOOKUP($A10,Data_Raw!$A:$G,3,FALSE),"")) -> 울산3지구 교육사업 | M10: =IF($A10="","",IFERROR(VLOOKUP($A10,Data_Raw!$A:$G,4,FALSE),"")) -> IBK기업은행 | N10: =IF($A10="","",IFERROR(VLOOKUP($A10,AI_PF!$A:$EU,29,FALSE),"")) -> 해당없음 | O10: =IF($A10="","",IFERROR(VLOOKUP($A10,Data_Raw!$A:$G,5,FALSE),"")) -> KOR | P10: =IF($A10="","",IFERROR(VLOOKUP($A10,Data_Raw!$A:$G,6,FALSE),"")) -> BTL | Q10: =IF($A10="","",IFERROR(VLOOKUP($A10,Data_Raw!$A:$G,7,FALSE),"")) -> Social | R10: =IF($A10="","",SUMIFS(AI_PF!$AP:$AP,AI_PF!$A:$A,$A10)) -> 9619000000 | S10: =IF($A10="","",SUMIFS(AI_PF!$AW:$AW,AI_PF!$A:$A,$A10)) -> 9619000000 | T10: =IF($A10="","",SUMIFS(AI_PF!$AZ:$AZ,AI_PF!$A:$A,$A10)) -> 9404493910 | U10: =IF($A10="","",SUMIFS(AI_PF!$CA:$CA,AI_PF!$A:$A,$A10)) -> 214549000 | V10: =IF($A10="","",SUMIFS(AI_PF!$CE:$CE,AI_PF!$A:$A,$A10)) -> 214506090 | W10: =IF($A10="","",IFERROR(VLOOKUP($A10,AI_PF!$A:$CO,93,FALSE),"")) -> 3.3200604 | X10: =IF($A10="","",COUNTIF(AI_PF!$A:$A,$A10)) -> 6 | Y10: =IF($A10="","",COUNTIF(LookThrough!$A:$A,J10)) -> 0
A11: BS00000039 | B11: =IF($A11="","",IFERROR(VLOOKUP($A11,AI_PF!$A:$D,4,FALSE),"")) -> 강원학교관리 | C11: =IF($A11="","",IFERROR(VLOOKUP($A11,AI_PF!$A:$G,7,FALSE),"")) -> BTL | D11: =IF($A11="","",IFERROR(VLOOKUP($A11,AI_PF!$A:$H,8,FALSE),"")) -> 교육시설 | E11: =IF($A11="","",IFERROR(VLOOKUP($A11,AI_PF!$A:$N,14,FALSE),"")) -> 대출 | F11: =IF($A11="","",IFERROR(VLOOKUP($A11,AI_PF!$A:$R,18,FALSE),"")) -> KRW | G11: =IF($A11="","",IFERROR(VLOOKUP($A11,AI_PF!$A:$T,20,FALSE),"")) -> 39631 | H11: =IF($A11="","",IFERROR(VLOOKUP($A11,AI_PF!$A:$V,22,FALSE),"")) -> 46042 | I11: =IF($A11="","",IFERROR(VLOOKUP($A11,AI_PF!$A:$EU,151,FALSE),"")) -> ~2016 | J11: =IF($A11="","",IFERROR(VLOOKUP($A11,AI_PF!$A:$C,3,FALSE),"")) -> 6000000000087 | K11: =IF($A11="","",IFERROR(VLOOKUP($A11,Data_Raw!$A:$G,2,FALSE),"")) -> Infrastructure | L11: =IF($A11="","",IFERROR(VLOOKUP($A11,Data_Raw!$A:$G,3,FALSE),"")) -> 강원학교관리 | M11: =IF($A11="","",IFERROR(VLOOKUP($A11,Data_Raw!$A:$G,4,FALSE),"")) -> IBK기업은행 | N11: =IF($A11="","",IFERROR(VLOOKUP($A11,AI_PF!$A:$EU,29,FALSE),"")) -> 해당없음 | O11: =IF($A11="","",IFERROR(VLOOKUP($A11,Data_Raw!$A:$G,5,FALSE),"")) -> KOR | P11: =IF($A11="","",IFERROR(VLOOKUP($A11,Data_Raw!$A:$G,6,FALSE),"")) -> BTL | Q11: =IF($A11="","",IFERROR(VLOOKUP($A11,Data_Raw!$A:$G,7,FALSE),"")) -> Social | R11: =IF($A11="","",SUMIFS(AI_PF!$AP:$AP,AI_PF!$A:$A,$A11)) -> 9179500000 | S11: =IF($A11="","",SUMIFS(AI_PF!$AW:$AW,AI_PF!$A:$A,$A11)) -> 8385600000 | T11: =IF($A11="","",SUMIFS(AI_PF!$AZ:$AZ,AI_PF!$A:$A,$A11)) -> 8226507650 | U11: =IF($A11="","",SUMIFS(AI_PF!$CA:$CA,AI_PF!$A:$A,$A11)) -> 159138800 | V11: =IF($A11="","",SUMIFS(AI_PF!$CE:$CE,AI_PF!$A:$A,$A11)) -> 159092350 | W11: =IF($A11="","",IFERROR(VLOOKUP($A11,AI_PF!$A:$CO,93,FALSE),"")) -> 4.5679509 | X11: =IF($A11="","",COUNTIF(AI_PF!$A:$A,$A11)) -> 18 | Y11: =IF($A11="","",COUNTIF(LookThrough!$A:$A,J11)) -> 0
A12: BS00000040 | B12: =IF($A12="","",IFERROR(VLOOKUP($A12,AI_PF!$A:$D,4,FALSE),"")) -> 푸른아산지키미 | C12: =IF($A12="","",IFERROR(VLOOKUP($A12,AI_PF!$A:$G,7,FALSE),"")) -> BTL | D12: =IF($A12="","",IFERROR(VLOOKUP($A12,AI_PF!$A:$H,8,FALSE),"")) -> 하수관거 | E12: =IF($A12="","",IFERROR(VLOOKUP($A12,AI_PF!$A:$N,14,FALSE),"")) -> 대출 | F12: =IF($A12="","",IFERROR(VLOOKUP($A12,AI_PF!$A:$R,18,FALSE),"")) -> KRW | G12: =IF($A12="","",IFERROR(VLOOKUP($A12,AI_PF!$A:$T,20,FALSE),"")) -> 40345 | H12: =IF($A12="","",IFERROR(VLOOKUP($A12,AI_PF!$A:$V,22,FALSE),"")) -> 2958465 | I12: =IF($A12="","",IFERROR(VLOOKUP($A12,AI_PF!$A:$EU,151,FALSE),"")) -> ~2016 | J12: =IF($A12="","",IFERROR(VLOOKUP($A12,AI_PF!$A:$C,3,FALSE),"")) -> 6000000000122 | K12: =IF($A12="","",IFERROR(VLOOKUP($A12,Data_Raw!$A:$G,2,FALSE),"")) -> Infrastructure | L12: =IF($A12="","",IFERROR(VLOOKUP($A12,Data_Raw!$A:$G,3,FALSE),"")) -> 푸른아산지키미 | M12: =IF($A12="","",IFERROR(VLOOKUP($A12,Data_Raw!$A:$G,4,FALSE),"")) -> IBK기업은행 | N12: =IF($A12="","",IFERROR(VLOOKUP($A12,AI_PF!$A:$EU,29,FALSE),"")) -> 해당없음 | O12: =IF($A12="","",IFERROR(VLOOKUP($A12,Data_Raw!$A:$G,5,FALSE),"")) -> KOR | P12: =IF($A12="","",IFERROR(VLOOKUP($A12,Data_Raw!$A:$G,6,FALSE),"")) -> BTL | Q12: =IF($A12="","",IFERROR(VLOOKUP($A12,Data_Raw!$A:$G,7,FALSE),"")) -> Environmental | R12: =IF($A12="","",SUMIFS(AI_PF!$AP:$AP,AI_PF!$A:$A,$A12)) -> 19530000000 | S12: =IF($A12="","",SUMIFS(AI_PF!$AW:$AW,AI_PF!$A:$A,$A12)) -> 17997000000 | T12: =IF($A12="","",SUMIFS(AI_PF!$AZ:$AZ,AI_PF!$A:$A,$A12)) -> 14020009557 | U12: =IF($A12="","",SUMIFS(AI_PF!$CA:$CA,AI_PF!$A:$A,$A12)) -> 5384898033 | V12: =IF($A12="","",SUMIFS(AI_PF!$CE:$CE,AI_PF!$A:$A,$A12)) -> 5384102476 | W12: =IF($A12="","",IFERROR(VLOOKUP($A12,AI_PF!$A:$CO,93,FALSE),"")) -> 3.619427 | X12: =IF($A12="","",COUNTIF(AI_PF!$A:$A,$A12)) -> 3 | Y12: =IF($A12="","",COUNTIF(LookThrough!$A:$A,J12)) -> 0
A13: BS00000041 | B13: =IF($A13="","",IFERROR(VLOOKUP($A13,AI_PF!$A:$D,4,FALSE),"")) -> 푸른여수지키미 | C13: =IF($A13="","",IFERROR(VLOOKUP($A13,AI_PF!$A:$G,7,FALSE),"")) -> BTL | D13: =IF($A13="","",IFERROR(VLOOKUP($A13,AI_PF!$A:$H,8,FALSE),"")) -> 하수관거 | E13: =IF($A13="","",IFERROR(VLOOKUP($A13,AI_PF!$A:$N,14,FALSE),"")) -> 대출 | F13: =IF($A13="","",IFERROR(VLOOKUP($A13,AI_PF!$A:$R,18,FALSE),"")) -> KRW | G13: =IF($A13="","",IFERROR(VLOOKUP($A13,AI_PF!$A:$T,20,FALSE),"")) -> 40267 | H13: =IF($A13="","",IFERROR(VLOOKUP($A13,AI_PF!$A:$V,22,FALSE),"")) -> 2958465 | I13: =IF($A13="","",IFERROR(VLOOKUP($A13,AI_PF!$A:$EU,151,FALSE),"")) -> ~2016 | J13: =IF($A13="","",IFERROR(VLOOKUP($A13,AI_PF!$A:$C,3,FALSE),"")) -> 6000000000151 | K13: =IF($A13="","",IFERROR(VLOOKUP($A13,Data_Raw!$A:$G,2,FALSE),"")) -> Infrastructure | L13: =IF($A13="","",IFERROR(VLOOKUP($A13,Data_Raw!$A:$G,3,FALSE),"")) -> 푸른여수지키미 | M13: =IF($A13="","",IFERROR(VLOOKUP($A13,Data_Raw!$A:$G,4,FALSE),"")) -> IBK기업은행 | N13: =IF($A13="","",IFERROR(VLOOKUP($A13,AI_PF!$A:$EU,29,FALSE),"")) -> 해당없음 | O13: =IF($A13="","",IFERROR(VLOOKUP($A13,Data_Raw!$A:$G,5,FALSE),"")) -> KOR | P13: =IF($A13="","",IFERROR(VLOOKUP($A13,Data_Raw!$A:$G,6,FALSE),"")) -> BTL | Q13: =IF($A13="","",IFERROR(VLOOKUP($A13,Data_Raw!$A:$G,7,FALSE),"")) -> Environmental | R13: =IF($A13="","",SUMIFS(AI_PF!$AP:$AP,AI_PF!$A:$A,$A13)) -> 11149330175 | S13: =IF($A13="","",SUMIFS(AI_PF!$AW:$AW,AI_PF!$A:$A,$A13)) -> 8735960000 | T13: =IF($A13="","",SUMIFS(AI_PF!$AZ:$AZ,AI_PF!$A:$A,$A13)) -> 6515210239 | U13: =IF($A13="","",SUMIFS(AI_PF!$CA:$CA,AI_PF!$A:$A,$A13)) -> 2879484175 | V13: =IF($A13="","",SUMIFS(AI_PF!$CE:$CE,AI_PF!$A:$A,$A13)) -> 2879039936 | W13: =IF($A13="","",IFERROR(VLOOKUP($A13,AI_PF!$A:$CO,93,FALSE),"")) -> 4.1665648 | X13: =IF($A13="","",COUNTIF(AI_PF!$A:$A,$A13)) -> 4 | Y13: =IF($A13="","",COUNTIF(LookThrough!$A:$A,J13)) -> 0
... A385: BS00001661 | B385: =IF($A385="","",IFERROR(VLOOKUP($A385,AI_PF!$A:$D,4,FALSE),"")) -> SIFC 담보대출 리파이낸싱(2026년) | C385: =IF($A385="","",IFERROR(VLOOKUP($A385,AI_PF!$A:$G,7,FALSE),"")) -> 수익형 | D385: =IF($A385="","",IFERROR(VLOOKUP($A385,AI_PF!$A:$H,8,FALSE),"")) -> 오피스 | E385: =IF($A385="","",IFERROR(VLOOKUP($A385,AI_PF!$A:$N,14,FALSE),"")) -> 대출 | F385: =IF($A385="","",IFERROR(VLOOKUP($A385,AI_PF!$A:$R,18,FALSE),"")) -> KRW | G385: =IF($A385="","",IFERROR(VLOOKUP($A385,AI_PF!$A:$T,20,FALSE),"")) -> 45747 | H385: =IF($A385="","",IFERROR(VLOOKUP($A385,AI_PF!$A:$V,22,FALSE),"")) -> 46843 | I385: =IF($A385="","",IFERROR(VLOOKUP($A385,AI_PF!$A:$EU,151,FALSE),"")) -> 2026 | J385: =IF($A385="","",IFERROR(VLOOKUP($A385,AI_PF!$A:$C,3,FALSE),"")) -> 6000000001330 | K385: =IF($A385="","",IFERROR(VLOOKUP($A385,Data_Raw!$A:$G,2,FALSE),"")) -> Real_Estate | L385: =IF($A385="","",IFERROR(VLOOKUP($A385,Data_Raw!$A:$G,3,FALSE),"")) -> SIFC 담보대출 리파이낸싱(2026년) | M385: =IF($A385="","",IFERROR(VLOOKUP($A385,Data_Raw!$A:$G,4,FALSE),"")) -> 국민은행 | N385: =IF($A385="","",IFERROR(VLOOKUP($A385,AI_PF!$A:$EU,29,FALSE),"")) -> 해당없음 | O385: =IF($A385="","",IFERROR(VLOOKUP($A385,Data_Raw!$A:$G,5,FALSE),"")) -> KOR | P385: =IF($A385="","",IFERROR(VLOOKUP($A385,Data_Raw!$A:$G,6,FALSE),"")) -> 담보대출 | Q385: =IF($A385="","",IFERROR(VLOOKUP($A385,Data_Raw!$A:$G,7,FALSE),"")) -> Office | R385: =IF($A385="","",SUMIFS(AI_PF!$AP:$AP,AI_PF!$A:$A,$A385)) -> 300000000000 | S385: =IF($A385="","",SUMIFS(AI_PF!$AW:$AW,AI_PF!$A:$A,$A385)) -> 300000000000 | T385: =IF($A385="","",SUMIFS(AI_PF!$AZ:$AZ,AI_PF!$A:$A,$A385)) -> 3346833601 | U385: =IF($A385="","",SUMIFS(AI_PF!$CA:$CA,AI_PF!$A:$A,$A385)) -> 300000000000 | V385: =IF($A385="","",SUMIFS(AI_PF!$CE:$CE,AI_PF!$A:$A,$A385)) -> 296653166399 | W385: =IF($A385="","",IFERROR(VLOOKUP($A385,AI_PF!$A:$CO,93,FALSE),"")) -> 4.5011406 | X385: =IF($A385="","",COUNTIF(AI_PF!$A:$A,$A385)) -> 4 | Y385: =IF($A385="","",COUNTIF(LookThrough!$A:$A,J385)) -> 0
B386: =IF($A386="","",IFERROR(VLOOKUP($A386,AI_PF!$A:$D,4,FALSE),"")) | C386: =IF($A386="","",IFERROR(VLOOKUP($A386,AI_PF!$A:$G,7,FALSE),"")) | D386: =IF($A386="","",IFERROR(VLOOKUP($A386,AI_PF!$A:$H,8,FALSE),"")) | E386: =IF($A386="","",IFERROR(VLOOKUP($A386,AI_PF!$A:$N,14,FALSE),"")) | F386: =IF($A386="","",IFERROR(VLOOKUP($A386,AI_PF!$A:$R,18,FALSE),"")) | G386: =IF($A386="","",IFERROR(VLOOKUP($A386,AI_PF!$A:$T,20,FALSE),"")) | H386: =IF($A386="","",IFERROR(VLOOKUP($A386,AI_PF!$A:$V,22,FALSE),"")) | I386: =IF($A386="","",IFERROR(VLOOKUP($A386,AI_PF!$A:$EU,151,FALSE),"")) | J386: =IF($A386="","",IFERROR(VLOOKUP($A386,AI_PF!$A:$C,3,FALSE),"")) | K386: =IF($A386="","",IFERROR(VLOOKUP($A386,Data_Raw!$A:$G,2,FALSE),"")) | L386: =IF($A386="","",IFERROR(VLOOKUP($A386,Data_Raw!$A:$G,3,FALSE),"")) | M386: =IF($A386="","",IFERROR(VLOOKUP($A386,Data_Raw!$A:$G,4,FALSE),"")) | N386: =IF($A386="","",IFERROR(VLOOKUP($A386,AI_PF!$A:$EU,29,FALSE),"")) | O386: =IF($A386="","",IFERROR(VLOOKUP($A386,Data_Raw!$A:$G,5,FALSE),"")) | P386: =IF($A386="","",IFERROR(VLOOKUP($A386,Data_Raw!$A:$G,6,FALSE),"")) | Q386: =IF($A386="","",IFERROR(VLOOKUP($A386,Data_Raw!$A:$G,7,FALSE),"")) | R386: =IF($A386="","",SUMIFS(AI_PF!$AP:$AP,AI_PF!$A:$A,$A386)) | S386: =IF($A386="","",SUMIFS(AI_PF!$AW:$AW,AI_PF!$A:$A,$A386)) | T386: =IF($A386="","",SUMIFS(AI_PF!$AZ:$AZ,AI_PF!$A:$A,$A386)) | U386: =IF($A386="","",SUMIFS(AI_PF!$CA:$CA,AI_PF!$A:$A,$A386)) | V386: =IF($A386="","",SUMIFS(AI_PF!$CE:$CE,AI_PF!$A:$A,$A386)) | W386: =IF($A386="","",IFERROR(VLOOKUP($A386,AI_PF!$A:$CO,93,FALSE),"")) | X386: =IF($A386="","",COUNTIF(AI_PF!$A:$A,$A386)) | Y386: =IF($A386="","",COUNTIF(LookThrough!$A:$A,J386))
B387: =IF($A387="","",IFERROR(VLOOKUP($A387,AI_PF!$A:$D,4,FALSE),"")) | C387: =IF($A387="","",IFERROR(VLOOKUP($A387,AI_PF!$A:$G,7,FALSE),"")) | D387: =IF($A387="","",IFERROR(VLOOKUP($A387,AI_PF!$A:$H,8,FALSE),"")) | E387: =IF($A387="","",IFERROR(VLOOKUP($A387,AI_PF!$A:$N,14,FALSE),"")) | F387: =IF($A387="","",IFERROR(VLOOKUP($A387,AI_PF!$A:$R,18,FALSE),"")) | G387: =IF($A387="","",IFERROR(VLOOKUP($A387,AI_PF!$A:$T,20,FALSE),"")) | H387: =IF($A387="","",IFERROR(VLOOKUP($A387,AI_PF!$A:$V,22,FALSE),"")) | I387: =IF($A387="","",IFERROR(VLOOKUP($A387,AI_PF!$A:$EU,151,FALSE),"")) | J387: =IF($A387="","",IFERROR(VLOOKUP($A387,AI_PF!$A:$C,3,FALSE),"")) | K387: =IF($A387="","",IFERROR(VLOOKUP($A387,Data_Raw!$A:$G,2,FALSE),"")) | L387: =IF($A387="","",IFERROR(VLOOKUP($A387,Data_Raw!$A:$G,3,FALSE),"")) | M387: =IF($A387="","",IFERROR(VLOOKUP($A387,Data_Raw!$A:$G,4,FALSE),"")) | N387: =IF($A387="","",IFERROR(VLOOKUP($A387,AI_PF!$A:$EU,29,FALSE),"")) | O387: =IF($A387="","",IFERROR(VLOOKUP($A387,Data_Raw!$A:$G,5,FALSE),"")) | P387: =IF($A387="","",IFERROR(VLOOKUP($A387,Data_Raw!$A:$G,6,FALSE),"")) | Q387: =IF($A387="","",IFERROR(VLOOKUP($A387,Data_Raw!$A:$G,7,FALSE),"")) | R387: =IF($A387="","",SUMIFS(AI_PF!$AP:$AP,AI_PF!$A:$A,$A387)) | S387: =IF($A387="","",SUMIFS(AI_PF!$AW:$AW,AI_PF!$A:$A,$A387)) | T387: =IF($A387="","",SUMIFS(AI_PF!$AZ:$AZ,AI_PF!$A:$A,$A387)) | U387: =IF($A387="","",SUMIFS(AI_PF!$CA:$CA,AI_PF!$A:$A,$A387)) | V387: =IF($A387="","",SUMIFS(AI_PF!$CE:$CE,AI_PF!$A:$A,$A387)) | W387: =IF($A387="","",IFERROR(VLOOKUP($A387,AI_PF!$A:$CO,93,FALSE),"")) | X387: =IF($A387="","",COUNTIF(AI_PF!$A:$A,$A387)) | Y387: =IF($A387="","",COUNTIF(LookThrough!$A:$A,J387))
B388: =IF($A388="","",IFERROR(VLOOKUP($A388,AI_PF!$A:$D,4,FALSE),"")) | C388: =IF($A388="","",IFERROR(VLOOKUP($A388,AI_PF!$A:$G,7,FALSE),"")) | D388: =IF($A388="","",IFERROR(VLOOKUP($A388,AI_PF!$A:$H,8,FALSE),"")) | E388: =IF($A388="","",IFERROR(VLOOKUP($A388,AI_PF!$A:$N,14,FALSE),"")) | F388: =IF($A388="","",IFERROR(VLOOKUP($A388,AI_PF!$A:$R,18,FALSE),"")) | G388: =IF($A388="","",IFERROR(VLOOKUP($A388,AI_PF!$A:$T,20,FALSE),"")) | H388: =IF($A388="","",IFERROR(VLOOKUP($A388,AI_PF!$A:$V,22,FALSE),"")) | I388: =IF($A388="","",IFERROR(VLOOKUP($A388,AI_PF!$A:$EU,151,FALSE),"")) | J388: =IF($A388="","",IFERROR(VLOOKUP($A388,AI_PF!$A:$C,3,FALSE),"")) | K388: =IF($A388="","",IFERROR(VLOOKUP($A388,Data_Raw!$A:$G,2,FALSE),"")) | L388: =IF($A388="","",IFERROR(VLOOKUP($A388,Data_Raw!$A:$G,3,FALSE),"")) | M388: =IF($A388="","",IFERROR(VLOOKUP($A388,Data_Raw!$A:$G,4,FALSE),"")) | N388: =IF($A388="","",IFERROR(VLOOKUP($A388,AI_PF!$A:$EU,29,FALSE),"")) | O388: =IF($A388="","",IFERROR(VLOOKUP($A388,Data_Raw!$A:$G,5,FALSE),"")) | P388: =IF($A388="","",IFERROR(VLOOKUP($A388,Data_Raw!$A:$G,6,FALSE),"")) | Q388: =IF($A388="","",IFERROR(VLOOKUP($A388,Data_Raw!$A:$G,7,FALSE),"")) | R388: =IF($A388="","",SUMIFS(AI_PF!$AP:$AP,AI_PF!$A:$A,$A388)) | S388: =IF($A388="","",SUMIFS(AI_PF!$AW:$AW,AI_PF!$A:$A,$A388)) | T388: =IF($A388="","",SUMIFS(AI_PF!$AZ:$AZ,AI_PF!$A:$A,$A388)) | U388: =IF($A388="","",SUMIFS(AI_PF!$CA:$CA,AI_PF!$A:$A,$A388)) | V388: =IF($A388="","",SUMIFS(AI_PF!$CE:$CE,AI_PF!$A:$A,$A388)) | W388: =IF($A388="","",IFERROR(VLOOKUP($A388,AI_PF!$A:$CO,93,FALSE),"")) | X388: =IF($A388="","",COUNTIF(AI_PF!$A:$A,$A388)) | Y388: =IF($A388="","",COUNTIF(LookThrough!$A:$A,J388))
B389: =IF($A389="","",IFERROR(VLOOKUP($A389,AI_PF!$A:$D,4,FALSE),"")) | C389: =IF($A389="","",IFERROR(VLOOKUP($A389,AI_PF!$A:$G,7,FALSE),"")) | D389: =IF($A389="","",IFERROR(VLOOKUP($A389,AI_PF!$A:$H,8,FALSE),"")) | E389: =IF($A389="","",IFERROR(VLOOKUP($A389,AI_PF!$A:$N,14,FALSE),"")) | F389: =IF($A389="","",IFERROR(VLOOKUP($A389,AI_PF!$A:$R,18,FALSE),"")) | G389: =IF($A389="","",IFERROR(VLOOKUP($A389,AI_PF!$A:$T,20,FALSE),"")) | H389: =IF($A389="","",IFERROR(VLOOKUP($A389,AI_PF!$A:$V,22,FALSE),"")) | I389: =IF($A389="","",IFERROR(VLOOKUP($A389,AI_PF!$A:$EU,151,FALSE),"")) | J389: =IF($A389="","",IFERROR(VLOOKUP($A389,AI_PF!$A:$C,3,FALSE),"")) | K389: =IF($A389="","",IFERROR(VLOOKUP($A389,Data_Raw!$A:$G,2,FALSE),"")) | L389: =IF($A389="","",IFERROR(VLOOKUP($A389,Data_Raw!$A:$G,3,FALSE),"")) | M389: =IF($A389="","",IFERROR(VLOOKUP($A389,Data_Raw!$A:$G,4,FALSE),"")) | N389: =IF($A389="","",IFERROR(VLOOKUP($A389,AI_PF!$A:$EU,29,FALSE),"")) | O389: =IF($A389="","",IFERROR(VLOOKUP($A389,Data_Raw!$A:$G,5,FALSE),"")) | P389: =IF($A389="","",IFERROR(VLOOKUP($A389,Data_Raw!$A:$G,6,FALSE),"")) | Q389: =IF($A389="","",IFERROR(VLOOKUP($A389,Data_Raw!$A:$G,7,FALSE),"")) | R389: =IF($A389="","",SUMIFS(AI_PF!$AP:$AP,AI_PF!$A:$A,$A389)) | S389: =IF($A389="","",SUMIFS(AI_PF!$AW:$AW,AI_PF!$A:$A,$A389)) | T389: =IF($A389="","",SUMIFS(AI_PF!$AZ:$AZ,AI_PF!$A:$A,$A389)) | U389: =IF($A389="","",SUMIFS(AI_PF!$CA:$CA,AI_PF!$A:$A,$A389)) | V389: =IF($A389="","",SUMIFS(AI_PF!$CE:$CE,AI_PF!$A:$A,$A389)) | W389: =IF($A389="","",IFERROR(VLOOKUP($A389,AI_PF!$A:$CO,93,FALSE),"")) | X389: =IF($A389="","",COUNTIF(AI_PF!$A:$A,$A389)) | Y389: =IF($A389="","",COUNTIF(LookThrough!$A:$A,J389))
B390: =IF($A390="","",IFERROR(VLOOKUP($A390,AI_PF!$A:$D,4,FALSE),"")) | C390: =IF($A390="","",IFERROR(VLOOKUP($A390,AI_PF!$A:$G,7,FALSE),"")) | D390: =IF($A390="","",IFERROR(VLOOKUP($A390,AI_PF!$A:$H,8,FALSE),"")) | E390: =IF($A390="","",IFERROR(VLOOKUP($A390,AI_PF!$A:$N,14,FALSE),"")) | F390: =IF($A390="","",IFERROR(VLOOKUP($A390,AI_PF!$A:$R,18,FALSE),"")) | G390: =IF($A390="","",IFERROR(VLOOKUP($A390,AI_PF!$A:$T,20,FALSE),"")) | H390: =IF($A390="","",IFERROR(VLOOKUP($A390,AI_PF!$A:$V,22,FALSE),"")) | I390: =IF($A390="","",IFERROR(VLOOKUP($A390,AI_PF!$A:$EU,151,FALSE),"")) | J390: =IF($A390="","",IFERROR(VLOOKUP($A390,AI_PF!$A:$C,3,FALSE),"")) | K390: =IF($A390="","",IFERROR(VLOOKUP($A390,Data_Raw!$A:$G,2,FALSE),"")) | L390: =IF($A390="","",IFERROR(VLOOKUP($A390,Data_Raw!$A:$G,3,FALSE),"")) | M390: =IF($A390="","",IFERROR(VLOOKUP($A390,Data_Raw!$A:$G,4,FALSE),"")) | N390: =IF($A390="","",IFERROR(VLOOKUP($A390,AI_PF!$A:$EU,29,FALSE),"")) | O390: =IF($A390="","",IFERROR(VLOOKUP($A390,Data_Raw!$A:$G,5,FALSE),"")) | P390: =IF($A390="","",IFERROR(VLOOKUP($A390,Data_Raw!$A:$G,6,FALSE),"")) | Q390: =IF($A390="","",IFERROR(VLOOKUP($A390,Data_Raw!$A:$G,7,FALSE),"")) | R390: =IF($A390="","",SUMIFS(AI_PF!$AP:$AP,AI_PF!$A:$A,$A390)) | S390: =IF($A390="","",SUMIFS(AI_PF!$AW:$AW,AI_PF!$A:$A,$A390)) | T390: =IF($A390="","",SUMIFS(AI_PF!$AZ:$AZ,AI_PF!$A:$A,$A390)) | U390: =IF($A390="","",SUMIFS(AI_PF!$CA:$CA,AI_PF!$A:$A,$A390)) | V390: =IF($A390="","",SUMIFS(AI_PF!$CE:$CE,AI_PF!$A:$A,$A390)) | W390: =IF($A390="","",IFERROR(VLOOKUP($A390,AI_PF!$A:$CO,93,FALSE),"")) | X390: =IF($A390="","",COUNTIF(AI_PF!$A:$A,$A390)) | Y390: =IF($A390="","",COUNTIF(LookThrough!$A:$A,J390))
B391: =IF($A391="","",IFERROR(VLOOKUP($A391,AI_PF!$A:$D,4,FALSE),"")) | C391: =IF($A391="","",IFERROR(VLOOKUP($A391,AI_PF!$A:$G,7,FALSE),"")) | D391: =IF($A391="","",IFERROR(VLOOKUP($A391,AI_PF!$A:$H,8,FALSE),"")) | E391: =IF($A391="","",IFERROR(VLOOKUP($A391,AI_PF!$A:$N,14,FALSE),"")) | F391: =IF($A391="","",IFERROR(VLOOKUP($A391,AI_PF!$A:$R,18,FALSE),"")) | G391: =IF($A391="","",IFERROR(VLOOKUP($A391,AI_PF!$A:$T,20,FALSE),"")) | H391: =IF($A391="","",IFERROR(VLOOKUP($A391,AI_PF!$A:$V,22,FALSE),"")) | I391: =IF($A391="","",IFERROR(VLOOKUP($A391,AI_PF!$A:$EU,151,FALSE),"")) | J391: =IF($A391="","",IFERROR(VLOOKUP($A391,AI_PF!$A:$C,3,FALSE),"")) | K391: =IF($A391="","",IFERROR(VLOOKUP($A391,Data_Raw!$A:$G,2,FALSE),"")) | L391: =IF($A391="","",IFERROR(VLOOKUP($A391,Data_Raw!$A:$G,3,FALSE),"")) | M391: =IF($A391="","",IFERROR(VLOOKUP($A391,Data_Raw!$A:$G,4,FALSE),"")) | N391: =IF($A391="","",IFERROR(VLOOKUP($A391,AI_PF!$A:$EU,29,FALSE),"")) | O391: =IF($A391="","",IFERROR(VLOOKUP($A391,Data_Raw!$A:$G,5,FALSE),"")) | P391: =IF($A391="","",IFERROR(VLOOKUP($A391,Data_Raw!$A:$G,6,FALSE),"")) | Q391: =IF($A391="","",IFERROR(VLOOKUP($A391,Data_Raw!$A:$G,7,FALSE),"")) | R391: =IF($A391="","",SUMIFS(AI_PF!$AP:$AP,AI_PF!$A:$A,$A391)) | S391: =IF($A391="","",SUMIFS(AI_PF!$AW:$AW,AI_PF!$A:$A,$A391)) | T391: =IF($A391="","",SUMIFS(AI_PF!$AZ:$AZ,AI_PF!$A:$A,$A391)) | U391: =IF($A391="","",SUMIFS(AI_PF!$CA:$CA,AI_PF!$A:$A,$A391)) | V391: =IF($A391="","",SUMIFS(AI_PF!$CE:$CE,AI_PF!$A:$A,$A391)) | W391: =IF($A391="","",IFERROR(VLOOKUP($A391,AI_PF!$A:$CO,93,FALSE),"")) | X391: =IF($A391="","",COUNTIF(AI_PF!$A:$A,$A391)) | Y391: =IF($A391="","",COUNTIF(LookThrough!$A:$A,J391))
B392: =IF($A392="","",IFERROR(VLOOKUP($A392,AI_PF!$A:$D,4,FALSE),"")) | C392: =IF($A392="","",IFERROR(VLOOKUP($A392,AI_PF!$A:$G,7,FALSE),"")) | D392: =IF($A392="","",IFERROR(VLOOKUP($A392,AI_PF!$A:$H,8,FALSE),"")) | E392: =IF($A392="","",IFERROR(VLOOKUP($A392,AI_PF!$A:$N,14,FALSE),"")) | F392: =IF($A392="","",IFERROR(VLOOKUP($A392,AI_PF!$A:$R,18,FALSE),"")) | G392: =IF($A392="","",IFERROR(VLOOKUP($A392,AI_PF!$A:$T,20,FALSE),"")) | H392: =IF($A392="","",IFERROR(VLOOKUP($A392,AI_PF!$A:$V,22,FALSE),"")) | I392: =IF($A392="","",IFERROR(VLOOKUP($A392,AI_PF!$A:$EU,151,FALSE),"")) | J392: =IF($A392="","",IFERROR(VLOOKUP($A392,AI_PF!$A:$C,3,FALSE),"")) | K392: =IF($A392="","",IFERROR(VLOOKUP($A392,Data_Raw!$A:$G,2,FALSE),"")) | L392: =IF($A392="","",IFERROR(VLOOKUP($A392,Data_Raw!$A:$G,3,FALSE),"")) | M392: =IF($A392="","",IFERROR(VLOOKUP($A392,Data_Raw!$A:$G,4,FALSE),"")) | N392: =IF($A392="","",IFERROR(VLOOKUP($A392,AI_PF!$A:$EU,29,FALSE),"")) | O392: =IF($A392="","",IFERROR(VLOOKUP($A392,Data_Raw!$A:$G,5,FALSE),"")) | P392: =IF($A392="","",IFERROR(VLOOKUP($A392,Data_Raw!$A:$G,6,FALSE),"")) | Q392: =IF($A392="","",IFERROR(VLOOKUP($A392,Data_Raw!$A:$G,7,FALSE),"")) | R392: =IF($A392="","",SUMIFS(AI_PF!$AP:$AP,AI_PF!$A:$A,$A392)) | S392: =IF($A392="","",SUMIFS(AI_PF!$AW:$AW,AI_PF!$A:$A,$A392)) | T392: =IF($A392="","",SUMIFS(AI_PF!$AZ:$AZ,AI_PF!$A:$A,$A392)) | U392: =IF($A392="","",SUMIFS(AI_PF!$CA:$CA,AI_PF!$A:$A,$A392)) | V392: =IF($A392="","",SUMIFS(AI_PF!$CE:$CE,AI_PF!$A:$A,$A392)) | W392: =IF($A392="","",IFERROR(VLOOKUP($A392,AI_PF!$A:$CO,93,FALSE),"")) | X392: =IF($A392="","",COUNTIF(AI_PF!$A:$A,$A392)) | Y392: =IF($A392="","",COUNTIF(LookThrough!$A:$A,J392))
B393: =IF($A393="","",IFERROR(VLOOKUP($A393,AI_PF!$A:$D,4,FALSE),"")) | C393: =IF($A393="","",IFERROR(VLOOKUP($A393,AI_PF!$A:$G,7,FALSE),"")) | D393: =IF($A393="","",IFERROR(VLOOKUP($A393,AI_PF!$A:$H,8,FALSE),"")) | E393: =IF($A393="","",IFERROR(VLOOKUP($A393,AI_PF!$A:$N,14,FALSE),"")) | F393: =IF($A393="","",IFERROR(VLOOKUP($A393,AI_PF!$A:$R,18,FALSE),"")) | G393: =IF($A393="","",IFERROR(VLOOKUP($A393,AI_PF!$A:$T,20,FALSE),"")) | H393: =IF($A393="","",IFERROR(VLOOKUP($A393,AI_PF!$A:$V,22,FALSE),"")) | I393: =IF($A393="","",IFERROR(VLOOKUP($A393,AI_PF!$A:$EU,151,FALSE),"")) | J393: =IF($A393="","",IFERROR(VLOOKUP($A393,AI_PF!$A:$C,3,FALSE),"")) | K393: =IF($A393="","",IFERROR(VLOOKUP($A393,Data_Raw!$A:$G,2,FALSE),"")) | L393: =IF($A393="","",IFERROR(VLOOKUP($A393,Data_Raw!$A:$G,3,FALSE),"")) | M393: =IF($A393="","",IFERROR(VLOOKUP($A393,Data_Raw!$A:$G,4,FALSE),"")) | N393: =IF($A393="","",IFERROR(VLOOKUP($A393,AI_PF!$A:$EU,29,FALSE),"")) | O393: =IF($A393="","",IFERROR(VLOOKUP($A393,Data_Raw!$A:$G,5,FALSE),"")) | P393: =IF($A393="","",IFERROR(VLOOKUP($A393,Data_Raw!$A:$G,6,FALSE),"")) | Q393: =IF($A393="","",IFERROR(VLOOKUP($A393,Data_Raw!$A:$G,7,FALSE),"")) | R393: =IF($A393="","",SUMIFS(AI_PF!$AP:$AP,AI_PF!$A:$A,$A393)) | S393: =IF($A393="","",SUMIFS(AI_PF!$AW:$AW,AI_PF!$A:$A,$A393)) | T393: =IF($A393="","",SUMIFS(AI_PF!$AZ:$AZ,AI_PF!$A:$A,$A393)) | U393: =IF($A393="","",SUMIFS(AI_PF!$CA:$CA,AI_PF!$A:$A,$A393)) | V393: =IF($A393="","",SUMIFS(AI_PF!$CE:$CE,AI_PF!$A:$A,$A393)) | W393: =IF($A393="","",IFERROR(VLOOKUP($A393,AI_PF!$A:$CO,93,FALSE),"")) | X393: =IF($A393="","",COUNTIF(AI_PF!$A:$A,$A393)) | Y393: =IF($A393="","",COUNTIF(LookThrough!$A:$A,J393))
B394: =IF($A394="","",IFERROR(VLOOKUP($A394,AI_PF!$A:$D,4,FALSE),"")) | C394: =IF($A394="","",IFERROR(VLOOKUP($A394,AI_PF!$A:$G,7,FALSE),"")) | D394: =IF($A394="","",IFERROR(VLOOKUP($A394,AI_PF!$A:$H,8,FALSE),"")) | E394: =IF($A394="","",IFERROR(VLOOKUP($A394,AI_PF!$A:$N,14,FALSE),"")) | F394: =IF($A394="","",IFERROR(VLOOKUP($A394,AI_PF!$A:$R,18,FALSE),"")) | G394: =IF($A394="","",IFERROR(VLOOKUP($A394,AI_PF!$A:$T,20,FALSE),"")) | H394: =IF($A394="","",IFERROR(VLOOKUP($A394,AI_PF!$A:$V,22,FALSE),"")) | I394: =IF($A394="","",IFERROR(VLOOKUP($A394,AI_PF!$A:$EU,151,FALSE),"")) | J394: =IF($A394="","",IFERROR(VLOOKUP($A394,AI_PF!$A:$C,3,FALSE),"")) | K394: =IF($A394="","",IFERROR(VLOOKUP($A394,Data_Raw!$A:$G,2,FALSE),"")) | L394: =IF($A394="","",IFERROR(VLOOKUP($A394,Data_Raw!$A:$G,3,FALSE),"")) | M394: =IF($A394="","",IFERROR(VLOOKUP($A394,Data_Raw!$A:$G,4,FALSE),"")) | N394: =IF($A394="","",IFERROR(VLOOKUP($A394,AI_PF!$A:$EU,29,FALSE),"")) | O394: =IF($A394="","",IFERROR(VLOOKUP($A394,Data_Raw!$A:$G,5,FALSE),"")) | P394: =IF($A394="","",IFERROR(VLOOKUP($A394,Data_Raw!$A:$G,6,FALSE),"")) | Q394: =IF($A394="","",IFERROR(VLOOKUP($A394,Data_Raw!$A:$G,7,FALSE),"")) | R394: =IF($A394="","",SUMIFS(AI_PF!$AP:$AP,AI_PF!$A:$A,$A394)) | S394: =IF($A394="","",SUMIFS(AI_PF!$AW:$AW,AI_PF!$A:$A,$A394)) | T394: =IF($A394="","",SUMIFS(AI_PF!$AZ:$AZ,AI_PF!$A:$A,$A394)) | U394: =IF($A394="","",SUMIFS(AI_PF!$CA:$CA,AI_PF!$A:$A,$A394)) | V394: =IF($A394="","",SUMIFS(AI_PF!$CE:$CE,AI_PF!$A:$A,$A394)) | W394: =IF($A394="","",IFERROR(VLOOKUP($A394,AI_PF!$A:$CO,93,FALSE),"")) | X394: =IF($A394="","",COUNTIF(AI_PF!$A:$A,$A394)) | Y394: =IF($A394="","",COUNTIF(LookThrough!$A:$A,J394))
B395: =IF($A395="","",IFERROR(VLOOKUP($A395,AI_PF!$A:$D,4,FALSE),"")) | C395: =IF($A395="","",IFERROR(VLOOKUP($A395,AI_PF!$A:$G,7,FALSE),"")) | D395: =IF($A395="","",IFERROR(VLOOKUP($A395,AI_PF!$A:$H,8,FALSE),"")) | E395: =IF($A395="","",IFERROR(VLOOKUP($A395,AI_PF!$A:$N,14,FALSE),"")) | F395: =IF($A395="","",IFERROR(VLOOKUP($A395,AI_PF!$A:$R,18,FALSE),"")) | G395: =IF($A395="","",IFERROR(VLOOKUP($A395,AI_PF!$A:$T,20,FALSE),"")) | H395: =IF($A395="","",IFERROR(VLOOKUP($A395,AI_PF!$A:$V,22,FALSE),"")) | I395: =IF($A395="","",IFERROR(VLOOKUP($A395,AI_PF!$A:$EU,151,FALSE),"")) | J395: =IF($A395="","",IFERROR(VLOOKUP($A395,AI_PF!$A:$C,3,FALSE),"")) | K395: =IF($A395="","",IFERROR(VLOOKUP($A395,Data_Raw!$A:$G,2,FALSE),"")) | L395: =IF($A395="","",IFERROR(VLOOKUP($A395,Data_Raw!$A:$G,3,FALSE),"")) | M395: =IF($A395="","",IFERROR(VLOOKUP($A395,Data_Raw!$A:$G,4,FALSE),"")) | N395: =IF($A395="","",IFERROR(VLOOKUP($A395,AI_PF!$A:$EU,29,FALSE),"")) | O395: =IF($A395="","",IFERROR(VLOOKUP($A395,Data_Raw!$A:$G,5,FALSE),"")) | P395: =IF($A395="","",IFERROR(VLOOKUP($A395,Data_Raw!$A:$G,6,FALSE),"")) | Q395: =IF($A395="","",IFERROR(VLOOKUP($A395,Data_Raw!$A:$G,7,FALSE),"")) | R395: =IF($A395="","",SUMIFS(AI_PF!$AP:$AP,AI_PF!$A:$A,$A395)) | S395: =IF($A395="","",SUMIFS(AI_PF!$AW:$AW,AI_PF!$A:$A,$A395)) | T395: =IF($A395="","",SUMIFS(AI_PF!$AZ:$AZ,AI_PF!$A:$A,$A395)) | U395: =IF($A395="","",SUMIFS(AI_PF!$CA:$CA,AI_PF!$A:$A,$A395)) | V395: =IF($A395="","",SUMIFS(AI_PF!$CE:$CE,AI_PF!$A:$A,$A395)) | W395: =IF($A395="","",IFERROR(VLOOKUP($A395,AI_PF!$A:$CO,93,FALSE),"")) | X395: =IF($A395="","",COUNTIF(AI_PF!$A:$A,$A395)) | Y395: =IF($A395="","",COUNTIF(LookThrough!$A:$A,J395))
B396: =IF($A396="","",IFERROR(VLOOKUP($A396,AI_PF!$A:$D,4,FALSE),"")) | C396: =IF($A396="","",IFERROR(VLOOKUP($A396,AI_PF!$A:$G,7,FALSE),"")) | D396: =IF($A396="","",IFERROR(VLOOKUP($A396,AI_PF!$A:$H,8,FALSE),"")) | E396: =IF($A396="","",IFERROR(VLOOKUP($A396,AI_PF!$A:$N,14,FALSE),"")) | F396: =IF($A396="","",IFERROR(VLOOKUP($A396,AI_PF!$A:$R,18,FALSE),"")) | G396: =IF($A396="","",IFERROR(VLOOKUP($A396,AI_PF!$A:$T,20,FALSE),"")) | H396: =IF($A396="","",IFERROR(VLOOKUP($A396,AI_PF!$A:$V,22,FALSE),"")) | I396: =IF($A396="","",IFERROR(VLOOKUP($A396,AI_PF!$A:$EU,151,FALSE),"")) | J396: =IF($A396="","",IFERROR(VLOOKUP($A396,AI_PF!$A:$C,3,FALSE),"")) | K396: =IF($A396="","",IFERROR(VLOOKUP($A396,Data_Raw!$A:$G,2,FALSE),"")) | L396: =IF($A396="","",IFERROR(VLOOKUP($A396,Data_Raw!$A:$G,3,FALSE),"")) | M396: =IF($A396="","",IFERROR(VLOOKUP($A396,Data_Raw!$A:$G,4,FALSE),"")) | N396: =IF($A396="","",IFERROR(VLOOKUP($A396,AI_PF!$A:$EU,29,FALSE),"")) | O396: =IF($A396="","",IFERROR(VLOOKUP($A396,Data_Raw!$A:$G,5,FALSE),"")) | P396: =IF($A396="","",IFERROR(VLOOKUP($A396,Data_Raw!$A:$G,6,FALSE),"")) | Q396: =IF($A396="","",IFERROR(VLOOKUP($A396,Data_Raw!$A:$G,7,FALSE),"")) | R396: =IF($A396="","",SUMIFS(AI_PF!$AP:$AP,AI_PF!$A:$A,$A396)) | S396: =IF($A396="","",SUMIFS(AI_PF!$AW:$AW,AI_PF!$A:$A,$A396)) | T396: =IF($A396="","",SUMIFS(AI_PF!$AZ:$AZ,AI_PF!$A:$A,$A396)) | U396: =IF($A396="","",SUMIFS(AI_PF!$CA:$CA,AI_PF!$A:$A,$A396)) | V396: =IF($A396="","",SUMIFS(AI_PF!$CE:$CE,AI_PF!$A:$A,$A396)) | W396: =IF($A396="","",IFERROR(VLOOKUP($A396,AI_PF!$A:$CO,93,FALSE),"")) | X396: =IF($A396="","",COUNTIF(AI_PF!$A:$A,$A396)) | Y396: =IF($A396="","",COUNTIF(LookThrough!$A:$A,J396))
B397: =IF($A397="","",IFERROR(VLOOKUP($A397,AI_PF!$A:$D,4,FALSE),"")) | C397: =IF($A397="","",IFERROR(VLOOKUP($A397,AI_PF!$A:$G,7,FALSE),"")) | D397: =IF($A397="","",IFERROR(VLOOKUP($A397,AI_PF!$A:$H,8,FALSE),"")) | E397: =IF($A397="","",IFERROR(VLOOKUP($A397,AI_PF!$A:$N,14,FALSE),"")) | F397: =IF($A397="","",IFERROR(VLOOKUP($A397,AI_PF!$A:$R,18,FALSE),"")) | G397: =IF($A397="","",IFERROR(VLOOKUP($A397,AI_PF!$A:$T,20,FALSE),"")) | H397: =IF($A397="","",IFERROR(VLOOKUP($A397,AI_PF!$A:$V,22,FALSE),"")) | I397: =IF($A397="","",IFERROR(VLOOKUP($A397,AI_PF!$A:$EU,151,FALSE),"")) | J397: =IF($A397="","",IFERROR(VLOOKUP($A397,AI_PF!$A:$C,3,FALSE),"")) | K397: =IF($A397="","",IFERROR(VLOOKUP($A397,Data_Raw!$A:$G,2,FALSE),"")) | L397: =IF($A397="","",IFERROR(VLOOKUP($A397,Data_Raw!$A:$G,3,FALSE),"")) | M397: =IF($A397="","",IFERROR(VLOOKUP($A397,Data_Raw!$A:$G,4,FALSE),"")) | N397: =IF($A397="","",IFERROR(VLOOKUP($A397,AI_PF!$A:$EU,29,FALSE),"")) | O397: =IF($A397="","",IFERROR(VLOOKUP($A397,Data_Raw!$A:$G,5,FALSE),"")) | P397: =IF($A397="","",IFERROR(VLOOKUP($A397,Data_Raw!$A:$G,6,FALSE),"")) | Q397: =IF($A397="","",IFERROR(VLOOKUP($A397,Data_Raw!$A:$G,7,FALSE),"")) | R397: =IF($A397="","",SUMIFS(AI_PF!$AP:$AP,AI_PF!$A:$A,$A397)) | S397: =IF($A397="","",SUMIFS(AI_PF!$AW:$AW,AI_PF!$A:$A,$A397)) | T397: =IF($A397="","",SUMIFS(AI_PF!$AZ:$AZ,AI_PF!$A:$A,$A397)) | U397: =IF($A397="","",SUMIFS(AI_PF!$CA:$CA,AI_PF!$A:$A,$A397)) | V397: =IF($A397="","",SUMIFS(AI_PF!$CE:$CE,AI_PF!$A:$A,$A397)) | W397: =IF($A397="","",IFERROR(VLOOKUP($A397,AI_PF!$A:$CO,93,FALSE),"")) | X397: =IF($A397="","",COUNTIF(AI_PF!$A:$A,$A397)) | Y397: =IF($A397="","",COUNTIF(LookThrough!$A:$A,J397))
... B524: =IF($A524="","",IFERROR(VLOOKUP($A524,AI_PF!$A:$D,4,FALSE),"")) | C524: =IF($A524="","",IFERROR(VLOOKUP($A524,AI_PF!$A:$G,7,FALSE),"")) | D524: =IF($A524="","",IFERROR(VLOOKUP($A524,AI_PF!$A:$H,8,FALSE),"")) | E524: =IF($A524="","",IFERROR(VLOOKUP($A524,AI_PF!$A:$N,14,FALSE),"")) | F524: =IF($A524="","",IFERROR(VLOOKUP($A524,AI_PF!$A:$R,18,FALSE),"")) | G524: =IF($A524="","",IFERROR(VLOOKUP($A524,AI_PF!$A:$T,20,FALSE),"")) | H524: =IF($A524="","",IFERROR(VLOOKUP($A524,AI_PF!$A:$V,22,FALSE),"")) | I524: =IF($A524="","",IFERROR(VLOOKUP($A524,AI_PF!$A:$EU,151,FALSE),"")) | J524: =IF($A524="","",IFERROR(VLOOKUP($A524,AI_PF!$A:$C,3,FALSE),"")) | K524: =IF($A524="","",IFERROR(VLOOKUP($A524,Data_Raw!$A:$G,2,FALSE),"")) | L524: =IF($A524="","",IFERROR(VLOOKUP($A524,Data_Raw!$A:$G,3,FALSE),"")) | M524: =IF($A524="","",IFERROR(VLOOKUP($A524,Data_Raw!$A:$G,4,FALSE),"")) | N524: =IF($A524="","",IFERROR(VLOOKUP($A524,AI_PF!$A:$EU,29,FALSE),"")) | O524: =IF($A524="","",IFERROR(VLOOKUP($A524,Data_Raw!$A:$G,5,FALSE),"")) | P524: =IF($A524="","",IFERROR(VLOOKUP($A524,Data_Raw!$A:$G,6,FALSE),"")) | Q524: =IF($A524="","",IFERROR(VLOOKUP($A524,Data_Raw!$A:$G,7,FALSE),"")) | R524: =IF($A524="","",SUMIFS(AI_PF!$AP:$AP,AI_PF!$A:$A,$A524)) | S524: =IF($A524="","",SUMIFS(AI_PF!$AW:$AW,AI_PF!$A:$A,$A524)) | T524: =IF($A524="","",SUMIFS(AI_PF!$AZ:$AZ,AI_PF!$A:$A,$A524)) | U524: =IF($A524="","",SUMIFS(AI_PF!$CA:$CA,AI_PF!$A:$A,$A524)) | V524: =IF($A524="","",SUMIFS(AI_PF!$CE:$CE,AI_PF!$A:$A,$A524)) | W524: =IF($A524="","",IFERROR(VLOOKUP($A524,AI_PF!$A:$CO,93,FALSE),"")) | X524: =IF($A524="","",COUNTIF(AI_PF!$A:$A,$A524)) | Y524: =IF($A524="","",COUNTIF(LookThrough!$A:$A,J524))
A525: BS00001626 | B525: =IF($A525="","",IFERROR(VLOOKUP($A525,AI_PF!$A:$D,4,FALSE),"")) -> 이지스글로벌일반사모부동산투자신탁576호(재간접형) | C525: =IF($A525="","",IFERROR(VLOOKUP($A525,AI_PF!$A:$G,7,FALSE),"")) -> 수익형 | D525: =IF($A525="","",IFERROR(VLOOKUP($A525,AI_PF!$A:$H,8,FALSE),"")) -> 혼합 | E525: =IF($A525="","",IFERROR(VLOOKUP($A525,AI_PF!$A:$N,14,FALSE),"")) -> 수익증권 | F525: =IF($A525="","",IFERROR(VLOOKUP($A525,AI_PF!$A:$R,18,FALSE),"")) -> KRW | G525: =IF($A525="","",IFERROR(VLOOKUP($A525,AI_PF!$A:$T,20,FALSE),"")) -> 45985 | H525: =IF($A525="","",IFERROR(VLOOKUP($A525,AI_PF!$A:$V,22,FALSE),"")) -> 49453 | I525: =IF($A525="","",IFERROR(VLOOKUP($A525,AI_PF!$A:$EU,151,FALSE),"")) -> 2025 | J525: =IF($A525="","",IFERROR(VLOOKUP($A525,AI_PF!$A:$C,3,FALSE),"")) -> 210002230 | K525: =IF($A525="","",IFERROR(VLOOKUP($A525,Data_Raw!$A:$G,2,FALSE),"")) -> Real_Estate | L525: =IF($A525="","",IFERROR(VLOOKUP($A525,Data_Raw!$A:$G,3,FALSE),"")) -> 이지스글로벌일반사모부동산투자신탁576호(재간접형) | M525: =IF($A525="","",IFERROR(VLOOKUP($A525,Data_Raw!$A:$G,4,FALSE),"")) -> 이지스자산운용 | N525: =IF($A525="","",IFERROR(VLOOKUP($A525,AI_PF!$A:$EU,29,FALSE),"")) -> Rockwood Capital | O525: =IF($A525="","",IFERROR(VLOOKUP($A525,Data_Raw!$A:$G,5,FALSE),"")) -> US | P525: =IF($A525="","",IFERROR(VLOOKUP($A525,Data_Raw!$A:$G,6,FALSE),"")) -> 담보대출 | Q525: =IF($A525="","",IFERROR(VLOOKUP($A525,Data_Raw!$A:$G,7,FALSE),"")) -> Mixed | R525: =IF($A525="","",SUMIFS(AI_PF!$AP:$AP,AI_PF!$A:$A,$A525)) -> 150000000000 | S525: =IF($A525="","",SUMIFS(AI_PF!$AW:$AW,AI_PF!$A:$A,$A525)) -> 116308997342 | T525: =IF($A525="","",SUMIFS(AI_PF!$AZ:$AZ,AI_PF!$A:$A,$A525)) -> 0 | U525: =IF($A525="","",SUMIFS(AI_PF!$CA:$CA,AI_PF!$A:$A,$A525)) -> 116308997342 | V525: =IF($A525="","",SUMIFS(AI_PF!$CE:$CE,AI_PF!$A:$A,$A525)) -> 116658883064 | W525: =IF($A525="","",IFERROR(VLOOKUP($A525,AI_PF!$A:$CO,93,FALSE),"")) -> 1.3677809 | X525: =IF($A525="","",COUNTIF(AI_PF!$A:$A,$A525)) -> 1 | Y525: =IF($A525="","",COUNTIF(LookThrough!$A:$A,J525)) -> 0
B526: =IF($A526="","",IFERROR(VLOOKUP($A526,AI_PF!$A:$D,4,FALSE),"")) | C526: =IF($A526="","",IFERROR(VLOOKUP($A526,AI_PF!$A:$G,7,FALSE),"")) | D526: =IF($A526="","",IFERROR(VLOOKUP($A526,AI_PF!$A:$H,8,FALSE),"")) | E526: =IF($A526="","",IFERROR(VLOOKUP($A526,AI_PF!$A:$N,14,FALSE),"")) | F526: =IF($A526="","",IFERROR(VLOOKUP($A526,AI_PF!$A:$R,18,FALSE),"")) | G526: =IF($A526="","",IFERROR(VLOOKUP($A526,AI_PF!$A:$T,20,FALSE),"")) | H526: =IF($A526="","",IFERROR(VLOOKUP($A526,AI_PF!$A:$V,22,FALSE),"")) | I526: =IF($A526="","",IFERROR(VLOOKUP($A526,AI_PF!$A:$EU,151,FALSE),"")) | J526: =IF($A526="","",IFERROR(VLOOKUP($A526,AI_PF!$A:$C,3,FALSE),"")) | K526: =IF($A526="","",IFERROR(VLOOKUP($A526,Data_Raw!$A:$G,2,FALSE),"")) | L526: =IF($A526="","",IFERROR(VLOOKUP($A526,Data_Raw!$A:$G,3,FALSE),"")) | M526: =IF($A526="","",IFERROR(VLOOKUP($A526,Data_Raw!$A:$G,4,FALSE),"")) | N526: =IF($A526="","",IFERROR(VLOOKUP($A526,AI_PF!$A:$EU,29,FALSE),"")) | O526: =IF($A526="","",IFERROR(VLOOKUP($A526,Data_Raw!$A:$G,5,FALSE),"")) | P526: =IF($A526="","",IFERROR(VLOOKUP($A526,Data_Raw!$A:$G,6,FALSE),"")) | Q526: =IF($A526="","",IFERROR(VLOOKUP($A526,Data_Raw!$A:$G,7,FALSE),"")) | R526: =IF($A526="","",SUMIFS(AI_PF!$AP:$AP,AI_PF!$A:$A,$A526)) | S526: =IF($A526="","",SUMIFS(AI_PF!$AW:$AW,AI_PF!$A:$A,$A526)) | T526: =IF($A526="","",SUMIFS(AI_PF!$AZ:$AZ,AI_PF!$A:$A,$A526)) | U526: =IF($A526="","",SUMIFS(AI_PF!$CA:$CA,AI_PF!$A:$A,$A526)) | V526: =IF($A526="","",SUMIFS(AI_PF!$CE:$CE,AI_PF!$A:$A,$A526)) | W526: =IF($A526="","",IFERROR(VLOOKUP($A526,AI_PF!$A:$CO,93,FALSE),"")) | X526: =IF($A526="","",COUNTIF(AI_PF!$A:$A,$A526)) | Y526: =IF($A526="","",COUNTIF(LookThrough!$A:$A,J526))
B527: =IF($A527="","",IFERROR(VLOOKUP($A527,AI_PF!$A:$D,4,FALSE),"")) | C527: =IF($A527="","",IFERROR(VLOOKUP($A527,AI_PF!$A:$G,7,FALSE),"")) | D527: =IF($A527="","",IFERROR(VLOOKUP($A527,AI_PF!$A:$H,8,FALSE),"")) | E527: =IF($A527="","",IFERROR(VLOOKUP($A527,AI_PF!$A:$N,14,FALSE),"")) | F527: =IF($A527="","",IFERROR(VLOOKUP($A527,AI_PF!$A:$R,18,FALSE),"")) | G527: =IF($A527="","",IFERROR(VLOOKUP($A527,AI_PF!$A:$T,20,FALSE),"")) | H527: =IF($A527="","",IFERROR(VLOOKUP($A527,AI_PF!$A:$V,22,FALSE),"")) | I527: =IF($A527="","",IFERROR(VLOOKUP($A527,AI_PF!$A:$EU,151,FALSE),"")) | J527: =IF($A527="","",IFERROR(VLOOKUP($A527,AI_PF!$A:$C,3,FALSE),"")) | K527: =IF($A527="","",IFERROR(VLOOKUP($A527,Data_Raw!$A:$G,2,FALSE),"")) | L527: =IF($A527="","",IFERROR(VLOOKUP($A527,Data_Raw!$A:$G,3,FALSE),"")) | M527: =IF($A527="","",IFERROR(VLOOKUP($A527,Data_Raw!$A:$G,4,FALSE),"")) | N527: =IF($A527="","",IFERROR(VLOOKUP($A527,AI_PF!$A:$EU,29,FALSE),"")) | O527: =IF($A527="","",IFERROR(VLOOKUP($A527,Data_Raw!$A:$G,5,FALSE),"")) | P527: =IF($A527="","",IFERROR(VLOOKUP($A527,Data_Raw!$A:$G,6,FALSE),"")) | Q527: =IF($A527="","",IFERROR(VLOOKUP($A527,Data_Raw!$A:$G,7,FALSE),"")) | R527: =IF($A527="","",SUMIFS(AI_PF!$AP:$AP,AI_PF!$A:$A,$A527)) | S527: =IF($A527="","",SUMIFS(AI_PF!$AW:$AW,AI_PF!$A:$A,$A527)) | T527: =IF($A527="","",SUMIFS(AI_PF!$AZ:$AZ,AI_PF!$A:$A,$A527)) | U527: =IF($A527="","",SUMIFS(AI_PF!$CA:$CA,AI_PF!$A:$A,$A527)) | V527: =IF($A527="","",SUMIFS(AI_PF!$CE:$CE,AI_PF!$A:$A,$A527)) | W527: =IF($A527="","",IFERROR(VLOOKUP($A527,AI_PF!$A:$CO,93,FALSE),"")) | X527: =IF($A527="","",COUNTIF(AI_PF!$A:$A,$A527)) | Y527: =IF($A527="","",COUNTIF(LookThrough!$A:$A,J527))
B528: =IF($A528="","",IFERROR(VLOOKUP($A528,AI_PF!$A:$D,4,FALSE),"")) | C528: =IF($A528="","",IFERROR(VLOOKUP($A528,AI_PF!$A:$G,7,FALSE),"")) | D528: =IF($A528="","",IFERROR(VLOOKUP($A528,AI_PF!$A:$H,8,FALSE),"")) | E528: =IF($A528="","",IFERROR(VLOOKUP($A528,AI_PF!$A:$N,14,FALSE),"")) | F528: =IF($A528="","",IFERROR(VLOOKUP($A528,AI_PF!$A:$R,18,FALSE),"")) | G528: =IF($A528="","",IFERROR(VLOOKUP($A528,AI_PF!$A:$T,20,FALSE),"")) | H528: =IF($A528="","",IFERROR(VLOOKUP($A528,AI_PF!$A:$V,22,FALSE),"")) | I528: =IF($A528="","",IFERROR(VLOOKUP($A528,AI_PF!$A:$EU,151,FALSE),"")) | J528: =IF($A528="","",IFERROR(VLOOKUP($A528,AI_PF!$A:$C,3,FALSE),"")) | K528: =IF($A528="","",IFERROR(VLOOKUP($A528,Data_Raw!$A:$G,2,FALSE),"")) | L528: =IF($A528="","",IFERROR(VLOOKUP($A528,Data_Raw!$A:$G,3,FALSE),"")) | M528: =IF($A528="","",IFERROR(VLOOKUP($A528,Data_Raw!$A:$G,4,FALSE),"")) | N528: =IF($A528="","",IFERROR(VLOOKUP($A528,AI_PF!$A:$EU,29,FALSE),"")) | O528: =IF($A528="","",IFERROR(VLOOKUP($A528,Data_Raw!$A:$G,5,FALSE),"")) | P528: =IF($A528="","",IFERROR(VLOOKUP($A528,Data_Raw!$A:$G,6,FALSE),"")) | Q528: =IF($A528="","",IFERROR(VLOOKUP($A528,Data_Raw!$A:$G,7,FALSE),"")) | R528: =IF($A528="","",SUMIFS(AI_PF!$AP:$AP,AI_PF!$A:$A,$A528)) | S528: =IF($A528="","",SUMIFS(AI_PF!$AW:$AW,AI_PF!$A:$A,$A528)) | T528: =IF($A528="","",SUMIFS(AI_PF!$AZ:$AZ,AI_PF!$A:$A,$A528)) | U528: =IF($A528="","",SUMIFS(AI_PF!$CA:$CA,AI_PF!$A:$A,$A528)) | V528: =IF($A528="","",SUMIFS(AI_PF!$CE:$CE,AI_PF!$A:$A,$A528)) | W528: =IF($A528="","",IFERROR(VLOOKUP($A528,AI_PF!$A:$CO,93,FALSE),"")) | X528: =IF($A528="","",COUNTIF(AI_PF!$A:$A,$A528)) | Y528: =IF($A528="","",COUNTIF(LookThrough!$A:$A,J528))
B529: =IF($A529="","",IFERROR(VLOOKUP($A529,AI_PF!$A:$D,4,FALSE),"")) | C529: =IF($A529="","",IFERROR(VLOOKUP($A529,AI_PF!$A:$G,7,FALSE),"")) | D529: =IF($A529="","",IFERROR(VLOOKUP($A529,AI_PF!$A:$H,8,FALSE),"")) | E529: =IF($A529="","",IFERROR(VLOOKUP($A529,AI_PF!$A:$N,14,FALSE),"")) | F529: =IF($A529="","",IFERROR(VLOOKUP($A529,AI_PF!$A:$R,18,FALSE),"")) | G529: =IF($A529="","",IFERROR(VLOOKUP($A529,AI_PF!$A:$T,20,FALSE),"")) | H529: =IF($A529="","",IFERROR(VLOOKUP($A529,AI_PF!$A:$V,22,FALSE),"")) | I529: =IF($A529="","",IFERROR(VLOOKUP($A529,AI_PF!$A:$EU,151,FALSE),"")) | J529: =IF($A529="","",IFERROR(VLOOKUP($A529,AI_PF!$A:$C,3,FALSE),"")) | K529: =IF($A529="","",IFERROR(VLOOKUP($A529,Data_Raw!$A:$G,2,FALSE),"")) | L529: =IF($A529="","",IFERROR(VLOOKUP($A529,Data_Raw!$A:$G,3,FALSE),"")) | M529: =IF($A529="","",IFERROR(VLOOKUP($A529,Data_Raw!$A:$G,4,FALSE),"")) | N529: =IF($A529="","",IFERROR(VLOOKUP($A529,AI_PF!$A:$EU,29,FALSE),"")) | O529: =IF($A529="","",IFERROR(VLOOKUP($A529,Data_Raw!$A:$G,5,FALSE),"")) | P529: =IF($A529="","",IFERROR(VLOOKUP($A529,Data_Raw!$A:$G,6,FALSE),"")) | Q529: =IF($A529="","",IFERROR(VLOOKUP($A529,Data_Raw!$A:$G,7,FALSE),"")) | R529: =IF($A529="","",SUMIFS(AI_PF!$AP:$AP,AI_PF!$A:$A,$A529)) | S529: =IF($A529="","",SUMIFS(AI_PF!$AW:$AW,AI_PF!$A:$A,$A529)) | T529: =IF($A529="","",SUMIFS(AI_PF!$AZ:$AZ,AI_PF!$A:$A,$A529)) | U529: =IF($A529="","",SUMIFS(AI_PF!$CA:$CA,AI_PF!$A:$A,$A529)) | V529: =IF($A529="","",SUMIFS(AI_PF!$CE:$CE,AI_PF!$A:$A,$A529)) | W529: =IF($A529="","",IFERROR(VLOOKUP($A529,AI_PF!$A:$CO,93,FALSE),"")) | X529: =IF($A529="","",COUNTIF(AI_PF!$A:$A,$A529)) | Y529: =IF($A529="","",COUNTIF(LookThrough!$A:$A,J529))
B530: =IF($A530="","",IFERROR(VLOOKUP($A530,AI_PF!$A:$D,4,FALSE),"")) | C530: =IF($A530="","",IFERROR(VLOOKUP($A530,AI_PF!$A:$G,7,FALSE),"")) | D530: =IF($A530="","",IFERROR(VLOOKUP($A530,AI_PF!$A:$H,8,FALSE),"")) | E530: =IF($A530="","",IFERROR(VLOOKUP($A530,AI_PF!$A:$N,14,FALSE),"")) | F530: =IF($A530="","",IFERROR(VLOOKUP($A530,AI_PF!$A:$R,18,FALSE),"")) | G530: =IF($A530="","",IFERROR(VLOOKUP($A530,AI_PF!$A:$T,20,FALSE),"")) | H530: =IF($A530="","",IFERROR(VLOOKUP($A530,AI_PF!$A:$V,22,FALSE),"")) | I530: =IF($A530="","",IFERROR(VLOOKUP($A530,AI_PF!$A:$EU,151,FALSE),"")) | J530: =IF($A530="","",IFERROR(VLOOKUP($A530,AI_PF!$A:$C,3,FALSE),"")) | K530: =IF($A530="","",IFERROR(VLOOKUP($A530,Data_Raw!$A:$G,2,FALSE),"")) | L530: =IF($A530="","",IFERROR(VLOOKUP($A530,Data_Raw!$A:$G,3,FALSE),"")) | M530: =IF($A530="","",IFERROR(VLOOKUP($A530,Data_Raw!$A:$G,4,FALSE),"")) | N530: =IF($A530="","",IFERROR(VLOOKUP($A530,AI_PF!$A:$EU,29,FALSE),"")) | O530: =IF($A530="","",IFERROR(VLOOKUP($A530,Data_Raw!$A:$G,5,FALSE),"")) | P530: =IF($A530="","",IFERROR(VLOOKUP($A530,Data_Raw!$A:$G,6,FALSE),"")) | Q530: =IF($A530="","",IFERROR(VLOOKUP($A530,Data_Raw!$A:$G,7,FALSE),"")) | R530: =IF($A530="","",SUMIFS(AI_PF!$AP:$AP,AI_PF!$A:$A,$A530)) | S530: =IF($A530="","",SUMIFS(AI_PF!$AW:$AW,AI_PF!$A:$A,$A530)) | T530: =IF($A530="","",SUMIFS(AI_PF!$AZ:$AZ,AI_PF!$A:$A,$A530)) | U530: =IF($A530="","",SUMIFS(AI_PF!$CA:$CA,AI_PF!$A:$A,$A530)) | V530: =IF($A530="","",SUMIFS(AI_PF!$CE:$CE,AI_PF!$A:$A,$A530)) | W530: =IF($A530="","",IFERROR(VLOOKUP($A530,AI_PF!$A:$CO,93,FALSE),"")) | X530: =IF($A530="","",COUNTIF(AI_PF!$A:$A,$A530)) | Y530: =IF($A530="","",COUNTIF(LookThrough!$A:$A,J530))
B531: =IF($A531="","",IFERROR(VLOOKUP($A531,AI_PF!$A:$D,4,FALSE),"")) | C531: =IF($A531="","",IFERROR(VLOOKUP($A531,AI_PF!$A:$G,7,FALSE),"")) | D531: =IF($A531="","",IFERROR(VLOOKUP($A531,AI_PF!$A:$H,8,FALSE),"")) | E531: =IF($A531="","",IFERROR(VLOOKUP($A531,AI_PF!$A:$N,14,FALSE),"")) | F531: =IF($A531="","",IFERROR(VLOOKUP($A531,AI_PF!$A:$R,18,FALSE),"")) | G531: =IF($A531="","",IFERROR(VLOOKUP($A531,AI_PF!$A:$T,20,FALSE),"")) | H531: =IF($A531="","",IFERROR(VLOOKUP($A531,AI_PF!$A:$V,22,FALSE),"")) | I531: =IF($A531="","",IFERROR(VLOOKUP($A531,AI_PF!$A:$EU,151,FALSE),"")) | J531: =IF($A531="","",IFERROR(VLOOKUP($A531,AI_PF!$A:$C,3,FALSE),"")) | K531: =IF($A531="","",IFERROR(VLOOKUP($A531,Data_Raw!$A:$G,2,FALSE),"")) | L531: =IF($A531="","",IFERROR(VLOOKUP($A531,Data_Raw!$A:$G,3,FALSE),"")) | M531: =IF($A531="","",IFERROR(VLOOKUP($A531,Data_Raw!$A:$G,4,FALSE),"")) | N531: =IF($A531="","",IFERROR(VLOOKUP($A531,AI_PF!$A:$EU,29,FALSE),"")) | O531: =IF($A531="","",IFERROR(VLOOKUP($A531,Data_Raw!$A:$G,5,FALSE),"")) | P531: =IF($A531="","",IFERROR(VLOOKUP($A531,Data_Raw!$A:$G,6,FALSE),"")) | Q531: =IF($A531="","",IFERROR(VLOOKUP($A531,Data_Raw!$A:$G,7,FALSE),"")) | R531: =IF($A531="","",SUMIFS(AI_PF!$AP:$AP,AI_PF!$A:$A,$A531)) | S531: =IF($A531="","",SUMIFS(AI_PF!$AW:$AW,AI_PF!$A:$A,$A531)) | T531: =IF($A531="","",SUMIFS(AI_PF!$AZ:$AZ,AI_PF!$A:$A,$A531)) | U531: =IF($A531="","",SUMIFS(AI_PF!$CA:$CA,AI_PF!$A:$A,$A531)) | V531: =IF($A531="","",SUMIFS(AI_PF!$CE:$CE,AI_PF!$A:$A,$A531)) | W531: =IF($A531="","",IFERROR(VLOOKUP($A531,AI_PF!$A:$CO,93,FALSE),"")) | X531: =IF($A531="","",COUNTIF(AI_PF!$A:$A,$A531)) | Y531: =IF($A531="","",COUNTIF(LookThrough!$A:$A,J531))
B532: =IF($A532="","",IFERROR(VLOOKUP($A532,AI_PF!$A:$D,4,FALSE),"")) | C532: =IF($A532="","",IFERROR(VLOOKUP($A532,AI_PF!$A:$G,7,FALSE),"")) | D532: =IF($A532="","",IFERROR(VLOOKUP($A532,AI_PF!$A:$H,8,FALSE),"")) | E532: =IF($A532="","",IFERROR(VLOOKUP($A532,AI_PF!$A:$N,14,FALSE),"")) | F532: =IF($A532="","",IFERROR(VLOOKUP($A532,AI_PF!$A:$R,18,FALSE),"")) | G532: =IF($A532="","",IFERROR(VLOOKUP($A532,AI_PF!$A:$T,20,FALSE),"")) | H532: =IF($A532="","",IFERROR(VLOOKUP($A532,AI_PF!$A:$V,22,FALSE),"")) | I532: =IF($A532="","",IFERROR(VLOOKUP($A532,AI_PF!$A:$EU,151,FALSE),"")) | J532: =IF($A532="","",IFERROR(VLOOKUP($A532,AI_PF!$A:$C,3,FALSE),"")) | K532: =IF($A532="","",IFERROR(VLOOKUP($A532,Data_Raw!$A:$G,2,FALSE),"")) | L532: =IF($A532="","",IFERROR(VLOOKUP($A532,Data_Raw!$A:$G,3,FALSE),"")) | M532: =IF($A532="","",IFERROR(VLOOKUP($A532,Data_Raw!$A:$G,4,FALSE),"")) | N532: =IF($A532="","",IFERROR(VLOOKUP($A532,AI_PF!$A:$EU,29,FALSE),"")) | O532: =IF($A532="","",IFERROR(VLOOKUP($A532,Data_Raw!$A:$G,5,FALSE),"")) | P532: =IF($A532="","",IFERROR(VLOOKUP($A532,Data_Raw!$A:$G,6,FALSE),"")) | Q532: =IF($A532="","",IFERROR(VLOOKUP($A532,Data_Raw!$A:$G,7,FALSE),"")) | R532: =IF($A532="","",SUMIFS(AI_PF!$AP:$AP,AI_PF!$A:$A,$A532)) | S532: =IF($A532="","",SUMIFS(AI_PF!$AW:$AW,AI_PF!$A:$A,$A532)) | T532: =IF($A532="","",SUMIFS(AI_PF!$AZ:$AZ,AI_PF!$A:$A,$A532)) | U532: =IF($A532="","",SUMIFS(AI_PF!$CA:$CA,AI_PF!$A:$A,$A532)) | V532: =IF($A532="","",SUMIFS(AI_PF!$CE:$CE,AI_PF!$A:$A,$A532)) | W532: =IF($A532="","",IFERROR(VLOOKUP($A532,AI_PF!$A:$CO,93,FALSE),"")) | X532: =IF($A532="","",COUNTIF(AI_PF!$A:$A,$A532)) | Y532: =IF($A532="","",COUNTIF(LookThrough!$A:$A,J532))
B533: =IF($A533="","",IFERROR(VLOOKUP($A533,AI_PF!$A:$D,4,FALSE),"")) | C533: =IF($A533="","",IFERROR(VLOOKUP($A533,AI_PF!$A:$G,7,FALSE),"")) | D533: =IF($A533="","",IFERROR(VLOOKUP($A533,AI_PF!$A:$H,8,FALSE),"")) | E533: =IF($A533="","",IFERROR(VLOOKUP($A533,AI_PF!$A:$N,14,FALSE),"")) | F533: =IF($A533="","",IFERROR(VLOOKUP($A533,AI_PF!$A:$R,18,FALSE),"")) | G533: =IF($A533="","",IFERROR(VLOOKUP($A533,AI_PF!$A:$T,20,FALSE),"")) | H533: =IF($A533="","",IFERROR(VLOOKUP($A533,AI_PF!$A:$V,22,FALSE),"")) | I533: =IF($A533="","",IFERROR(VLOOKUP($A533,AI_PF!$A:$EU,151,FALSE),"")) | J533: =IF($A533="","",IFERROR(VLOOKUP($A533,AI_PF!$A:$C,3,FALSE),"")) | K533: =IF($A533="","",IFERROR(VLOOKUP($A533,Data_Raw!$A:$G,2,FALSE),"")) | L533: =IF($A533="","",IFERROR(VLOOKUP($A533,Data_Raw!$A:$G,3,FALSE),"")) | M533: =IF($A533="","",IFERROR(VLOOKUP($A533,Data_Raw!$A:$G,4,FALSE),"")) | N533: =IF($A533="","",IFERROR(VLOOKUP($A533,AI_PF!$A:$EU,29,FALSE),"")) | O533: =IF($A533="","",IFERROR(VLOOKUP($A533,Data_Raw!$A:$G,5,FALSE),"")) | P533: =IF($A533="","",IFERROR(VLOOKUP($A533,Data_Raw!$A:$G,6,FALSE),"")) | Q533: =IF($A533="","",IFERROR(VLOOKUP($A533,Data_Raw!$A:$G,7,FALSE),"")) | R533: =IF($A533="","",SUMIFS(AI_PF!$AP:$AP,AI_PF!$A:$A,$A533)) | S533: =IF($A533="","",SUMIFS(AI_PF!$AW:$AW,AI_PF!$A:$A,$A533)) | T533: =IF($A533="","",SUMIFS(AI_PF!$AZ:$AZ,AI_PF!$A:$A,$A533)) | U533: =IF($A533="","",SUMIFS(AI_PF!$CA:$CA,AI_PF!$A:$A,$A533)) | V533: =IF($A533="","",SUMIFS(AI_PF!$CE:$CE,AI_PF!$A:$A,$A533)) | W533: =IF($A533="","",IFERROR(VLOOKUP($A533,AI_PF!$A:$CO,93,FALSE),"")) | X533: =IF($A533="","",COUNTIF(AI_PF!$A:$A,$A533)) | Y533: =IF($A533="","",COUNTIF(LookThrough!$A:$A,J533))
B534: =IF($A534="","",IFERROR(VLOOKUP($A534,AI_PF!$A:$D,4,FALSE),"")) | C534: =IF($A534="","",IFERROR(VLOOKUP($A534,AI_PF!$A:$G,7,FALSE),"")) | D534: =IF($A534="","",IFERROR(VLOOKUP($A534,AI_PF!$A:$H,8,FALSE),"")) | E534: =IF($A534="","",IFERROR(VLOOKUP($A534,AI_PF!$A:$N,14,FALSE),"")) | F534: =IF($A534="","",IFERROR(VLOOKUP($A534,AI_PF!$A:$R,18,FALSE),"")) | G534: =IF($A534="","",IFERROR(VLOOKUP($A534,AI_PF!$A:$T,20,FALSE),"")) | H534: =IF($A534="","",IFERROR(VLOOKUP($A534,AI_PF!$A:$V,22,FALSE),"")) | I534: =IF($A534="","",IFERROR(VLOOKUP($A534,AI_PF!$A:$EU,151,FALSE),"")) | J534: =IF($A534="","",IFERROR(VLOOKUP($A534,AI_PF!$A:$C,3,FALSE),"")) | K534: =IF($A534="","",IFERROR(VLOOKUP($A534,Data_Raw!$A:$G,2,FALSE),"")) | L534: =IF($A534="","",IFERROR(VLOOKUP($A534,Data_Raw!$A:$G,3,FALSE),"")) | M534: =IF($A534="","",IFERROR(VLOOKUP($A534,Data_Raw!$A:$G,4,FALSE),"")) | N534: =IF($A534="","",IFERROR(VLOOKUP($A534,AI_PF!$A:$EU,29,FALSE),"")) | O534: =IF($A534="","",IFERROR(VLOOKUP($A534,Data_Raw!$A:$G,5,FALSE),"")) | P534: =IF($A534="","",IFERROR(VLOOKUP($A534,Data_Raw!$A:$G,6,FALSE),"")) | Q534: =IF($A534="","",IFERROR(VLOOKUP($A534,Data_Raw!$A:$G,7,FALSE),"")) | R534: =IF($A534="","",SUMIFS(AI_PF!$AP:$AP,AI_PF!$A:$A,$A534)) | S534: =IF($A534="","",SUMIFS(AI_PF!$AW:$AW,AI_PF!$A:$A,$A534)) | T534: =IF($A534="","",SUMIFS(AI_PF!$AZ:$AZ,AI_PF!$A:$A,$A534)) | U534: =IF($A534="","",SUMIFS(AI_PF!$CA:$CA,AI_PF!$A:$A,$A534)) | V534: =IF($A534="","",SUMIFS(AI_PF!$CE:$CE,AI_PF!$A:$A,$A534)) | W534: =IF($A534="","",IFERROR(VLOOKUP($A534,AI_PF!$A:$CO,93,FALSE),"")) | X534: =IF($A534="","",COUNTIF(AI_PF!$A:$A,$A534)) | Y534: =IF($A534="","",COUNTIF(LookThrough!$A:$A,J534))
B535: =IF($A535="","",IFERROR(VLOOKUP($A535,AI_PF!$A:$D,4,FALSE),"")) | C535: =IF($A535="","",IFERROR(VLOOKUP($A535,AI_PF!$A:$G,7,FALSE),"")) | D535: =IF($A535="","",IFERROR(VLOOKUP($A535,AI_PF!$A:$H,8,FALSE),"")) | E535: =IF($A535="","",IFERROR(VLOOKUP($A535,AI_PF!$A:$N,14,FALSE),"")) | F535: =IF($A535="","",IFERROR(VLOOKUP($A535,AI_PF!$A:$R,18,FALSE),"")) | G535: =IF($A535="","",IFERROR(VLOOKUP($A535,AI_PF!$A:$T,20,FALSE),"")) | H535: =IF($A535="","",IFERROR(VLOOKUP($A535,AI_PF!$A:$V,22,FALSE),"")) | I535: =IF($A535="","",IFERROR(VLOOKUP($A535,AI_PF!$A:$EU,151,FALSE),"")) | J535: =IF($A535="","",IFERROR(VLOOKUP($A535,AI_PF!$A:$C,3,FALSE),"")) | K535: =IF($A535="","",IFERROR(VLOOKUP($A535,Data_Raw!$A:$G,2,FALSE),"")) | L535: =IF($A535="","",IFERROR(VLOOKUP($A535,Data_Raw!$A:$G,3,FALSE),"")) | M535: =IF($A535="","",IFERROR(VLOOKUP($A535,Data_Raw!$A:$G,4,FALSE),"")) | N535: =IF($A535="","",IFERROR(VLOOKUP($A535,AI_PF!$A:$EU,29,FALSE),"")) | O535: =IF($A535="","",IFERROR(VLOOKUP($A535,Data_Raw!$A:$G,5,FALSE),"")) | P535: =IF($A535="","",IFERROR(VLOOKUP($A535,Data_Raw!$A:$G,6,FALSE),"")) | Q535: =IF($A535="","",IFERROR(VLOOKUP($A535,Data_Raw!$A:$G,7,FALSE),"")) | R535: =IF($A535="","",SUMIFS(AI_PF!$AP:$AP,AI_PF!$A:$A,$A535)) | S535: =IF($A535="","",SUMIFS(AI_PF!$AW:$AW,AI_PF!$A:$A,$A535)) | T535: =IF($A535="","",SUMIFS(AI_PF!$AZ:$AZ,AI_PF!$A:$A,$A535)) | U535: =IF($A535="","",SUMIFS(AI_PF!$CA:$CA,AI_PF!$A:$A,$A535)) | V535: =IF($A535="","",SUMIFS(AI_PF!$CE:$CE,AI_PF!$A:$A,$A535)) | W535: =IF($A535="","",IFERROR(VLOOKUP($A535,AI_PF!$A:$CO,93,FALSE),"")) | X535: =IF($A535="","",COUNTIF(AI_PF!$A:$A,$A535)) | Y535: =IF($A535="","",COUNTIF(LookThrough!$A:$A,J535))
B536: =IF($A536="","",IFERROR(VLOOKUP($A536,AI_PF!$A:$D,4,FALSE),"")) | C536: =IF($A536="","",IFERROR(VLOOKUP($A536,AI_PF!$A:$G,7,FALSE),"")) | D536: =IF($A536="","",IFERROR(VLOOKUP($A536,AI_PF!$A:$H,8,FALSE),"")) | E536: =IF($A536="","",IFERROR(VLOOKUP($A536,AI_PF!$A:$N,14,FALSE),"")) | F536: =IF($A536="","",IFERROR(VLOOKUP($A536,AI_PF!$A:$R,18,FALSE),"")) | G536: =IF($A536="","",IFERROR(VLOOKUP($A536,AI_PF!$A:$T,20,FALSE),"")) | H536: =IF($A536="","",IFERROR(VLOOKUP($A536,AI_PF!$A:$V,22,FALSE),"")) | I536: =IF($A536="","",IFERROR(VLOOKUP($A536,AI_PF!$A:$EU,151,FALSE),"")) | J536: =IF($A536="","",IFERROR(VLOOKUP($A536,AI_PF!$A:$C,3,FALSE),"")) | K536: =IF($A536="","",IFERROR(VLOOKUP($A536,Data_Raw!$A:$G,2,FALSE),"")) | L536: =IF($A536="","",IFERROR(VLOOKUP($A536,Data_Raw!$A:$G,3,FALSE),"")) | M536: =IF($A536="","",IFERROR(VLOOKUP($A536,Data_Raw!$A:$G,4,FALSE),"")) | N536: =IF($A536="","",IFERROR(VLOOKUP($A536,AI_PF!$A:$EU,29,FALSE),"")) | O536: =IF($A536="","",IFERROR(VLOOKUP($A536,Data_Raw!$A:$G,5,FALSE),"")) | P536: =IF($A536="","",IFERROR(VLOOKUP($A536,Data_Raw!$A:$G,6,FALSE),"")) | Q536: =IF($A536="","",IFERROR(VLOOKUP($A536,Data_Raw!$A:$G,7,FALSE),"")) | R536: =IF($A536="","",SUMIFS(AI_PF!$AP:$AP,AI_PF!$A:$A,$A536)) | S536: =IF($A536="","",SUMIFS(AI_PF!$AW:$AW,AI_PF!$A:$A,$A536)) | T536: =IF($A536="","",SUMIFS(AI_PF!$AZ:$AZ,AI_PF!$A:$A,$A536)) | U536: =IF($A536="","",SUMIFS(AI_PF!$CA:$CA,AI_PF!$A:$A,$A536)) | V536: =IF($A536="","",SUMIFS(AI_PF!$CE:$CE,AI_PF!$A:$A,$A536)) | W536: =IF($A536="","",IFERROR(VLOOKUP($A536,AI_PF!$A:$CO,93,FALSE),"")) | X536: =IF($A536="","",COUNTIF(AI_PF!$A:$A,$A536)) | Y536: =IF($A536="","",COUNTIF(LookThrough!$A:$A,J536))
B537: =IF($A537="","",IFERROR(VLOOKUP($A537,AI_PF!$A:$D,4,FALSE),"")) | C537: =IF($A537="","",IFERROR(VLOOKUP($A537,AI_PF!$A:$G,7,FALSE),"")) | D537: =IF($A537="","",IFERROR(VLOOKUP($A537,AI_PF!$A:$H,8,FALSE),"")) | E537: =IF($A537="","",IFERROR(VLOOKUP($A537,AI_PF!$A:$N,14,FALSE),"")) | F537: =IF($A537="","",IFERROR(VLOOKUP($A537,AI_PF!$A:$R,18,FALSE),"")) | G537: =IF($A537="","",IFERROR(VLOOKUP($A537,AI_PF!$A:$T,20,FALSE),"")) | H537: =IF($A537="","",IFERROR(VLOOKUP($A537,AI_PF!$A:$V,22,FALSE),"")) | I537: =IF($A537="","",IFERROR(VLOOKUP($A537,AI_PF!$A:$EU,151,FALSE),"")) | J537: =IF($A537="","",IFERROR(VLOOKUP($A537,AI_PF!$A:$C,3,FALSE),"")) | K537: =IF($A537="","",IFERROR(VLOOKUP($A537,Data_Raw!$A:$G,2,FALSE),"")) | L537: =IF($A537="","",IFERROR(VLOOKUP($A537,Data_Raw!$A:$G,3,FALSE),"")) | M537: =IF($A537="","",IFERROR(VLOOKUP($A537,Data_Raw!$A:$G,4,FALSE),"")) | N537: =IF($A537="","",IFERROR(VLOOKUP($A537,AI_PF!$A:$EU,29,FALSE),"")) | O537: =IF($A537="","",IFERROR(VLOOKUP($A537,Data_Raw!$A:$G,5,FALSE),"")) | P537: =IF($A537="","",IFERROR(VLOOKUP($A537,Data_Raw!$A:$G,6,FALSE),"")) | Q537: =IF($A537="","",IFERROR(VLOOKUP($A537,Data_Raw!$A:$G,7,FALSE),"")) | R537: =IF($A537="","",SUMIFS(AI_PF!$AP:$AP,AI_PF!$A:$A,$A537)) | S537: =IF($A537="","",SUMIFS(AI_PF!$AW:$AW,AI_PF!$A:$A,$A537)) | T537: =IF($A537="","",SUMIFS(AI_PF!$AZ:$AZ,AI_PF!$A:$A,$A537)) | U537: =IF($A537="","",SUMIFS(AI_PF!$CA:$CA,AI_PF!$A:$A,$A537)) | V537: =IF($A537="","",SUMIFS(AI_PF!$CE:$CE,AI_PF!$A:$A,$A537)) | W537: =IF($A537="","",IFERROR(VLOOKUP($A537,AI_PF!$A:$CO,93,FALSE),"")) | X537: =IF($A537="","",COUNTIF(AI_PF!$A:$A,$A537)) | Y537: =IF($A537="","",COUNTIF(LookThrough!$A:$A,J537))
... B1033: =IF($A1033="","",IFERROR(VLOOKUP($A1033,AI_PF!$A:$D,4,FALSE),"")) | C1033: =IF($A1033="","",IFERROR(VLOOKUP($A1033,AI_PF!$A:$G,7,FALSE),"")) | D1033: =IF($A1033="","",IFERROR(VLOOKUP($A1033,AI_PF!$A:$H,8,FALSE),"")) | E1033: =IF($A1033="","",IFERROR(VLOOKUP($A1033,AI_PF!$A:$N,14,FALSE),"")) | F1033: =IF($A1033="","",IFERROR(VLOOKUP($A1033,AI_PF!$A:$R,18,FALSE),"")) | G1033: =IF($A1033="","",IFERROR(VLOOKUP($A1033,AI_PF!$A:$T,20,FALSE),"")) | H1033: =IF($A1033="","",IFERROR(VLOOKUP($A1033,AI_PF!$A:$V,22,FALSE),"")) | I1033: =IF($A1033="","",IFERROR(VLOOKUP($A1033,AI_PF!$A:$EU,151,FALSE),"")) | J1033: =IF($A1033="","",IFERROR(VLOOKUP($A1033,AI_PF!$A:$C,3,FALSE),"")) | K1033: =IF($A1033="","",IFERROR(VLOOKUP($A1033,Data_Raw!$A:$G,2,FALSE),"")) | L1033: =IF($A1033="","",IFERROR(VLOOKUP($A1033,Data_Raw!$A:$G,3,FALSE),"")) | M1033: =IF($A1033="","",IFERROR(VLOOKUP($A1033,Data_Raw!$A:$G,4,FALSE),"")) | N1033: =IF($A1033="","",IFERROR(VLOOKUP($A1033,AI_PF!$A:$EU,29,FALSE),"")) | O1033: =IF($A1033="","",IFERROR(VLOOKUP($A1033,Data_Raw!$A:$G,5,FALSE),"")) | P1033: =IF($A1033="","",IFERROR(VLOOKUP($A1033,Data_Raw!$A:$G,6,FALSE),"")) | Q1033: =IF($A1033="","",IFERROR(VLOOKUP($A1033,Data_Raw!$A:$G,7,FALSE),"")) | R1033: =IF($A1033="","",SUMIFS(AI_PF!$AP:$AP,AI_PF!$A:$A,$A1033)) | S1033: =IF($A1033="","",SUMIFS(AI_PF!$AW:$AW,AI_PF!$A:$A,$A1033)) | T1033: =IF($A1033="","",SUMIFS(AI_PF!$AZ:$AZ,AI_PF!$A:$A,$A1033)) | U1033: =IF($A1033="","",SUMIFS(AI_PF!$CA:$CA,AI_PF!$A:$A,$A1033)) | V1033: =IF($A1033="","",SUMIFS(AI_PF!$CE:$CE,AI_PF!$A:$A,$A1033)) | W1033: =IF($A1033="","",IFERROR(VLOOKUP($A1033,AI_PF!$A:$CO,93,FALSE),"")) | X1033: =IF($A1033="","",COUNTIF(AI_PF!$A:$A,$A1033)) | Y1033: =IF($A1033="","",COUNTIF(LookThrough!$A:$A,J1033))

Sheet AI_PF
A1: 프로젝트ID | B1: 약정ID | C1: 종목ID/트렌치ID | D1: 프로젝트명 | E1: 종목명 | F1: 자산군 | G1: 투자유형 | H1: 세부유형 | I1: 지역분류1 | J1: 지역분류2 | K1: 지역분류3 | L1: 지역분류4 | M1: 지역분류5(국내부동산) | N1: 자본구조1(SAP) | O1: 자본구조2(하위자산) | P1: 자본구조3(하위자산) | Q1: 형태 | R1: 약정통화 | S1: 투자통화 | T1: 최초인출일 | U1: 투자종료일 | V1: 만기일 | W1: 최종상환일 | X1: 규제형태(국내인프라) | Y1: 수익기반(국내인프라) | Z1: 보증형태(국내인프라부동산) | AA1: 보증내용(국내인프라부동산) | AB1: 운용사(국내) | AC1: 운용사(해외) | AD1: 담당자(심사팀) | AE1: 담당자(사업부) | AF1: 담당자(기획팀) | AG1: 관리단계 | AH1: 약정년월 | AI1: 금년약정&최초인출 | AJ1: 조직구분1 | AK1: 조직구분2 | AL1: D/E분류 | AM1: 인출여부 | AN1: 상환여부 | AO1: 약정금액(외화) | AP1: 약정금액(원화) | AQ1: 약정금액(신규,당월) | AR1: 약정금액(신규,연누계) | AS1: 실행(신규,당월) | AT1: 실행(신규,연누계) | AU1: 실행(당월) | AV1: 실행(연누계) | AW1: 실행(누적) | AX1: 상환(당월) | AY1: 상환(연누계) | AZ1: 상환(누적) | BA1: 순증(당월) | BB1: 순증(연누계) | BC1: 순증(누적) | BD1: 수익(당월) | BE1: 수익(연누계) | BF1: 수익(누적) | BG1: 배당(연누계) | BH1: 이자(연누계) | BI1: 수수료(연누계) | BJ1: 처분손익(연누계) | BK1: IG배당(연누계) | BL1: IG이자(연누계) | BM1: CG(당월) | BN1: CG(연누계) | BO1: IG(당월) | BP1: IG(연누계) | BQ1: CG+IG(당월) | BR1: CG+IG(연누계) | BS1: 미실현평가손익(당월) | BT1: 미실현평가손익(연누계) | BU1: 미실현평가손익(누적) | BV1: 실질손익(당월) | BW1: 실질손익(연누계) | BX1: 실질손익률(당월) | BY1: 실질손익률(연누계) | BZ1: 장부가액(외화,당월) | CA1: 장부가액(원화,당월) | CB1: 장부가액(원화,전월) | CC1: 장부가액(원화,전년말) | CD1: 평가금액(외화,당월) | CE1: 평가금액(원화,당월) | CF1: 평가금액(원화,전월) | CG1: 평가금액(원화,전년말) | CH1: 평가금액(원화,환X,당월) | CI1: 평가금액(원화,환X,전월) | CJ1: 평가금액(원화,환X,전년말) | CK1: 평가변동(전년비) | CL1: 감액(누적) | CM1: 수익률(원화,MTD) | CN1: 수익률(원화,YTD) | CO1: 수익률(원화,누적) | CP1: 평가금액*수익률(원화,MTD) | CQ1: 평가금액*수익률(원화,YTD) | CR1: 평가금액*수익률(원화,누적) | CS1: MOIC(원화,누적) | CT1: 평가금액*MOIC(원화,누적) | CU1: 보유금리(당월) | CV1: 실행금리(당월) | CW1: 실행금리(연누계) | CX1: 상환금리(당월) | CY1: 상환금리(연누계) | CZ1: 장부가액*보유금리(당월) | DA1: 실행금액*실행금리(당월) | DB1: 실행금액*실행금리(연누계) | DC1: 상환금액*상환금리(당월) | DD1: 상환금액*상환금리(연누계) | DE1: 장부가액(대출,당월,원화) | DF1: 실행(대출,당월) | DG1: 상환(대출,당월) | DH1: Debt% | DI1: Equity% | DJ1: 평가금액(Debt,당월) | DK1: 평가금액(Equity,당월) | DL1: 평가금액(Debt,전년말) | DM1: 평가금액(Equity,전년말) | DN1: 실행(Debt,연누계) | DO1: 실행(Equity,연누계) | DP1: 상환(Debt,연누계) | DQ1: 상환(Equity,연누계) | DR1: 실행(신규,Debt,연누계) | DS1: 실행(신규,Equity,연누계) | DT1: 약정금액(신규,Debt,연누계) | DU1: 약정금액(신규,Equity,연누계) | DV1: 리스크계산기준(23.12L/T) | DW1: 신용리스크 | DX1: 부동산리스크 | DY1: 주식리스크 | DZ1: 외환리스크 | EA1: 금리리스크 | EB1: 리스크합계 | EC1: 리스크비중 | ED1: 리스크가중합계 | EE1: 리스크추정(금액) | EF1: 외환손익(당월) | EG1: 이자,배당 및 수수료(당월) | EH1: 매매 및 기타손익(당월) | EI1: 파생손익(당월) | EJ1: 평가손익(당월) | EK1: 외환손익(연누계) | EL1: 이자,배당 및 수수료(연누계) | EM1: 매매 및 기타손익(연누계) | EN1: 파생손익(연누계) | EO1: 평가손익(연누계) | EP1: 종목총손익(당월) | EQ1: 종목총손익(연누계) | ER1: 검증(연누계) | ES1: 투자전략(PE/VC) | ET1: 투자전략(해외부동산) | EU1: 빈티지 | EV1: 투자구분 | EW1: 외환손익(당월)_D | EX1: 이자,배당 및 수수료(당월)_D | EY1: 매매 및 기타손익(당월)_D | EZ1: 파생손익(당월)_D | FA1: 평가손익(당월)_D | FB1: 외환손익(연누계)_D | FC1: 이자,배당 및 수수료(연누계)_D | FD1: 매매 및 기타손익(연누계)_D | FE1: 파생손익(연누계)_D | FF1: 평가손익(연누계)_D | FG1: 외환손익(당월)_E | FH1: 이자,배당 및 수수료(당월)_E | FI1: 매매 및 기타손익(당월)_E | FJ1: 파생손익(당월)_E | FK1: 평가손익(당월)_E | FL1: 외환손익(연누계)_E | FM1: 이자,배당 및 수수료(연누계)_E | FN1: 매매 및 기타손익(연누계)_E | FO1: 파생손익(연누계)_E | FP1: 평가손익(연누계)_E | FQ1: 검증 당월 | FR1: 검증 누계
A2: BS00000001 | B2: 5055740000 | C2: 6000000000277 | D2: 신대구부산고속도로 | E2: 신대구부산고속도로(주) [대구~부산간 고속도로] | F2: 인프라 | G2: BTO | H2: 도로 | I2: 국내 | J2: 아시아 | K2: 이머징 | L2: 한국 | M2: 해당없음 | N2: 대출 | O2: 선순위 | P2: 대출 | Q2: 프로젝트 | R2: KRW | S2: KRW | T2: 39440 | U2: 45832 | V2: 45832 | W2: 45286 | X2: PPP | Y2: Merchant(정부) | Z2: 해지시 지급금 | AA2: 해지시 지급금 전액 커버, MRG | AB2: 국민은행 | AC2: 해당없음 | AD2: 상환/확인필요 | AF2: 유재섭 | AG2: 정상 | AI2: 기보유 | AJ2: 국내실물 | AK2: 인프라 | AL2: Debt | AM2: 인출 | AN2: 상환 | AO2: 0 | AP2: 21469000000 | AQ2: 0 | AR2: 0 | AS2: 0 | AT2: 0 | AU2: 0 | AV2: 0 | AW2: 0 | AX2: 0 | AY2: 0 | AZ2: 0 | BA2: 0 | BB2: 0 | BC2: 0 | BD2: 0 | BE2: 0 | BF2: 0 | BG2: 0 | BH2: 0 | BI2: 0 | BJ2: 0 | BK2: 0 | BL2: 0 | BM2: 0 | BN2: 0 | BO2: 0 | BP2: 0 | BQ2: 0 | BR2: 0 | BS2: 0 | BT2: 0 | BU2: 0 | BV2: 0 | BW2: 0 | BX2: 0 | BY2: 0 | BZ2: 0 | CA2: 0 | CB2: 0 | CC2: 0 | CD2: 0 | CE2: 0 | CF2: 0 | CG2: 0 | CH2: 0 | CI2: 0 | CJ2: 0 | CK2: 0 | CL2: 0 | CM2: 0 | CN2: 0 | CO2: 0 | CP2: 0 | CQ2: 0 | CR2: 0 | CS2: 0 | CT2: 0 | CU2: 0 | CV2: 0 | CW2: 0 | CX2: 0 | CY2: 0 | CZ2: 0 | DA2: 0 | DB2: 0 | DC2: 0 | DD2: 0 | DE2: 0 | DF2: 0 | DG2: 0 | DH2: 1 | DI2: 0 | DJ2: 0 | DK2: 0 | DL2: 0 | DM2: 0 | DN2: 0 | DO2: 0 | DP2: 0 | DQ2: 0 | DR2: 0 | DS2: 0 | DT2: 0 | DU2: 0 | DV2: 0 | DW2: 0 | DX2: 0 | DY2: 0 | DZ2: 0 | EA2: 0 | EB2: 0 | EC2: 0 | ED2: 0 | EE2: 0 | EF2: 0 | EG2: 0 | EH2: 0 | EI2: 0 | EJ2: 0 | EK2: 0 | EL2: 0 | EM2: 0 | EN2: 0 | EO2: 0 | EP2: 0 | EQ2: 0 | ER2: 450 | EU2: ~2016 | EV2: 국내대출 | EW2: 0 | EX2: 0 | EY2: 0 | EZ2: 0 | FA2: 0 | FB2: 0 | FC2: 0 | FD2: 0 | FE2: 0 | FF2: 0 | FG2: 0 | FH2: 0 | FI2: 0 | FJ2: 0 | FK2: 0 | FL2: 0 | FM2: 0 | FN2: 0 | FO2: 0 | FP2: 0 | FQ2: TRUE | FR2: TRUE
A3: BS00000001 | B3: 5055740000 | C3: 6000000000278 | D3: 신대구-부산고속도로 | E3: 신대구부산고속도로(주) [대구~부산간 고속도로] | F3: 인프라 | G3: BTO | H3: 도로 | I3: 국내 | J3: 아시아 | K3: 이머징 | L3: 한국 | M3: 해당없음 | N3: 대출 | O3: 선순위 | P3: 대출 | Q3: 프로젝트 | R3: KRW | S3: KRW | T3: 39440 | U3: 45832 | V3: 45832 | W3: 45286 | X3: PPP | Y3: Merchant(정부) | Z3: 해지시 지급금 | AA3: 해지시 지급금 전액 커버, MRG | AB3: 국민은행 | AC3: 해당없음 | AD3: 상환/확인필요 | AF3: 유재섭 | AG3: 정상 | AI3: 기보유 | AJ3: 국내실물 | AK3: 인프라 | AL3: Debt | AM3: 인출 | AN3: 상환 | AO3: 0 | AP3: 80000000000 | AQ3: 0 | AR3: 0 | AS3: 0 | AT3: 0 | AU3: 0 | AV3: 0 | AW3: 0 | AX3: 0 | AY3: 0 | AZ3: 0 | BA3: 0 | BB3: 0 | BC3: 0 | BD3: 0 | BE3: 0 | BF3: 0 | BG3: 0 | BH3: 0 | BI3: 0 | BJ3: 0 | BK3: 0 | BL3: 0 | BM3: 0 | BN3: 0 | BO3: 0 | BP3: 0 | BQ3: 0 | BR3: 0 | BS3: 0 | BT3: 0 | BU3: 0 | BV3: 0 | BW3: 0 | BX3: 0 | BY3: 0 | BZ3: 0 | CA3: 0 | CB3: 0 | CC3: 0 | CD3: 0 | CE3: 0 | CF3: 0 | CG3: 0 | CH3: 0 | CI3: 0 | CJ3: 0 | CK3: 0 | CL3: 0 | CM3: 0 | CN3: 0 | CO3: 0 | CP3: 0 | CQ3: 0 | CR3: 0 | CS3: 0 | CT3: 0 | CU3: 0 | CV3: 0 | CW3: 0 | CX3: 0 | CY3: 0 | CZ3: 0 | DA3: 0 | DB3: 0 | DC3: 0 | DD3: 0 | DE3: 0 | DF3: 0 | DG3: 0 | DH3: 1 | DI3: 0 | DJ3: 0 | DK3: 0 | DL3: 0 | DM3: 0 | DN3: 0 | DO3: 0 | DP3: 0 | DQ3: 0 | DR3: 0 | DS3: 0 | DT3: 0 | DU3: 0 | DV3: 0 | DW3: 0 | DX3: 0 | DY3: 0 | DZ3: 0 | EA3: 0 | EB3: 0 | EC3: 0 | ED3: 0 | EE3: 0 | EF3: 0 | EG3: 0 | EH3: 0 | EI3: 0 | EJ3: 0 | EK3: 0 | EL3: 0 | EM3: 0 | EN3: 0 | EO3: 0 | EP3: 0 | EQ3: 0 | ER3: 450 | EU3: ~2016 | EV3: 국내대출 | EW3: 0 | EX3: 0 | EY3: 0 | EZ3: 0 | FA3: 0 | FB3: 0 | FC3: 0 | FD3: 0 | FE3: 0 | FF3: 0 | FG3: 0 | FH3: 0 | FI3: 0 | FJ3: 0 | FK3: 0 | FL3: 0 | FM3: 0 | FN3: 0 | FO3: 0 | FP3: 0 | FQ3: TRUE | FR3: TRUE
A4: BS00000001 | B4: 5055740000 | C4: 6000000000397 | D4: 신대구-부산고속도로 | E4: 신대구부산고속도로(주) [대구~부산간 고속도로] | F4: 인프라 | G4: BTO | H4: 도로 | I4: 국내 | J4: 아시아 | K4: 이머징 | L4: 한국 | M4: 해당없음 | N4: 대출 | O4: 선순위 | P4: 대출 | Q4: 프로젝트 | R4: KRW | S4: KRW | T4: 39440 | U4: 45832 | V4: 45832 | W4: 45286 | X4: PPP | Y4: Merchant(정부) | Z4: 해지시 지급금 | AA4: 해지시 지급금 전액 커버, MRG | AB4: 국민은행 | AC4: 해당없음 | AD4: 상환/확인필요 | AF4: 유재섭 | AG4: 정상 | AI4: 기보유 | AJ4: 국내실물 | AK4: 인프라 | AL4: Debt | AM4: 인출 | AN4: 상환 | AO4: 0 | AP4: 25362000000 | AQ4: 0 | AR4: 0 | AS4: 0 | AT4: 0 | AU4: 0 | AV4: 0 | AW4: 0 | AX4: 0 | AY4: 0 | AZ4: 0 | BA4: 0 | BB4: 0 | BC4: 0 | BD4: 0 | BE4: 0 | BF4: 0 | BG4: 0 | BH4: 0 | BI4: 0 | BJ4: 0 | BK4: 0 | BL4: 0 | BM4: 0 | BN4: 0 | BO4: 0 | BP4: 0 | BQ4: 0 | BR4: 0 | BS4: 0 | BT4: 0 | BU4: 0 | BV4: 0 | BW4: 0 | BX4: 0 | BY4: 0 | BZ4: 0 | CA4: 0 | CB4: 0 | CC4: 0 | CD4: 0 | CE4: 0 | CF4: 0 | CG4: 0 | CH4: 0 | CI4: 0 | CJ4: 0 | CK4: 0 | CL4: 0 | CM4: 0 | CN4: 0 | CO4: 0 | CP4: 0 | CQ4: 0 | CR4: 0 | CS4: 0 | CT4: 0 | CU4: 0 | CV4: 0 | CW4: 0 | CX4: 0 | CY4: 0 | CZ4: 0 | DA4: 0 | DB4: 0 | DC4: 0 | DD4: 0 | DE4: 0 | DF4: 0 | DG4: 0 | DH4: 1 | DI4: 0 | DJ4: 0 | DK4: 0 | DL4: 0 | DM4: 0 | DN4: 0 | DO4: 0 | DP4: 0 | DQ4: 0 | DR4: 0 | DS4: 0 | DT4: 0 | DU4: 0 | DV4: 0 | DW4: 0 | DX4: 0 | DY4: 0 | DZ4: 0 | EA4: 0 | EB4: 0 | EC4: 0 | ED4: 0 | EE4: 0 | EF4: 0 | EG4: 0 | EH4: 0 | EI4: 0 | EJ4: 0 | EK4: 0 | EL4: 0 | EM4: 0 | EN4: 0 | EO4: 0 | EP4: 0 | EQ4: 0 | ER4: 450 | EU4: ~2016 | EV4: 국내대출 | EW4: 0 | EX4: 0 | EY4: 0 | EZ4: 0 | FA4: 0 | FB4: 0 | FC4: 0 | FD4: 0 | FE4: 0 | FF4: 0 | FG4: 0 | FH4: 0 | FI4: 0 | FJ4: 0 | FK4: 0 | FL4: 0 | FM4: 0 | FN4: 0 | FO4: 0 | FP4: 0 | FQ4: TRUE | FR4: TRUE
A5: BS00000004 | B5: 405139761401 | C5: 6000000000138 | D5: 서울고속도로 리파이낸싱 | E5: 서울고속도로(Ref.) [일산~퇴계원간 고속도로] | F5: 인프라 | G5: BTO | H5: 도로 | I5: 국내 | J5: 아시아 | K5: 이머징 | L5: 한국 | M5: 해당없음 | N5: 대출 | O5: 선순위 | P5: 대출 | Q5: 프로젝트 | R5: KRW | S5: KRW | T5: 40723 | U5: 48394 | V5: 48394 | X5: PPP | Y5: Merchant(정부) | Z5: 해지시 지급금 | AA5: 해지시 지급금 전액 커버, MRG | AB5: 칸서스자산운용 | AC5: 해당없음 | AD5: 허강혁 | AF5: 유재섭 | AG5: 정상 | AH5: 40723 | AI5: 기보유 | AJ5: 국내실물 | AK5: 인프라 | AL5: Debt | AM5: 인출 | AN5: 운영 | AO5: 0 | AP5: 14000000000 | AQ5: 0 | AR5: 0 | AS5: 0 | AT5: 0 | AU5: 0 | AV5: 0 | AW5: 14000000000 | AX5: 315000000 | AY5: 315000000 | AZ5: 4737712417 | BA5: -315000000 | BB5: -315000000 | BC5: 9262287583 | BD5: 172147068 | BE5: 172147068 | BF5: 10163624546 | BG5: 0 | BH5: 172147068 | BI5: 0 | BJ5: 0 | BK5: 0 | BL5: 170344755 | BM5: 0 | BN5: 0 | BO5: 58396906 | BP5: 170408115 | BQ5: 58396906 | BR5: 170408115 | BS5: 0 | BT5: 0 | BU5: 0 | BV5: 58396906 | BW5: 170408115 | BX5: 0.62189026 | BY5: 1.8256688 | BZ5: 0 | CA5: 9275000000 | CB5: 9590000000 | CC5: 9590000000 | CD5: 0 | CE5: 9262287583 | CF5: 9576562891 | CG5: 9576141196 | CH5: 9262287583 | CI5: 9576562891 | CJ5: 9576141196 | CK5: 1146387 | CL5: 0 | CM5: 0.61934664 | CN5: 7.4321597 | CO5: 7.4321597 | CP5: 5.7365667e+09 | CQ5: 6.8838801e+10 | CR5: 6.8838801e+10 | CS5: 1.7259732 | CT5: 1.598646e+10 | CU5: 7.2 | CV5: 0 | CW5: 0 | CX5: 7.2 | CY5: 7.2 | CZ5: 6.6688471e+10 | DA5: 0 | DB5: 0 | DC5: 2268000000 | DD5: 2268000000 | DE5: 9262287583 | DF5: 0 | DG5: 315000000 | DH5: 1 | DI5: 0 | DJ5: 9262287583 | DK5: 0 | DL5: 9576141196 | DM5: 0 | DN5: 0 | DO5: 0 | DP5: 315000000 | DQ5: 0 | DR5: 0 | DS5: 0 | DT5: 0 | DU5: 0 | DV5: 1.099362e+10 | DW5: 0 | DX5: 0 | DY5: 0 | DZ5: 0 | EA5: 0 | EB5: 0 | EC5: 0 | ED5: 0 | EE5: 0 | EF5: 0 | EG5: 58396906 | EH5: 0 | EI5: 0 | EJ5: 0 | EK5: 0 | EL5: 170408115 | EM5: 0 | EN5: 0 | EO5: 0 | EP5: 58396906 | EQ5: 170408115 | ER5: 254 | EU5: ~2016 | EV5: 국내대출 | EW5: 0 | EX5: 58396906 | EY5: 0 | EZ5: 0 | FA5: 0 | FB5: 0 | FC5: 170408115 | FD5: 0 | FE5: 0 | FF5: 0 | FG5: 0 | FH5: 0 | FI5: 0 | FJ5: 0 | FK5: 0 | FL5: 0 | FM5: 0 | FN5: 0 | FO5: 0 | FP5: 0 | FQ5: TRUE | FR5: TRUE
A6: BS00000005 | B6: BS0000000501 | C6: 100001946 | D6: 신공항하이웨이 리파이낸싱 (지분) | E6: 신공항하이웨이 | F6: 인프라 | G6: BTO | H6: 도로 | I6: 국내 | J6: 아시아 | K6: 이머징 | L6: 한국 | M6: 해당없음 | N6: 출자 | O6: 지분 | P6: 주식형 | Q6: 프로젝트 | R6: KRW | S6: KRW | T6: 37984 | U6: 2958465 | V6: 2958465 | X6: PPP | Y6: Merchant(정부) | Z6: 해지시 지급금 | AA6: 해지시 지급금 전액 커버, MRG | AB6: 우리은행 | AC6: 해당없음 | AD6: 상환/확인필요 | AF6: 유재섭 | AG6: 정상 | AI6: 기보유 | AJ6: 국내실물 | AK6: 인프라 | AL6: Equity | AM6: 인출 | AN6: 운영 | AO6: 0 | AP6: 8453000000 | AQ6: 0 | AR6: 0 | AS6: 0 | AT6: 0 | AU6: 0 | AV6: 0 | AW6: 0 | AX6: 0 | AY6: 0 | AZ6: 5031495000 | BA6: 0 | BB6: 0 | BC6: -5031495000 | BD6: 4550108948 | BE6: 4550108948 | BF6: 48127453423 | BG6: 4550108948 | BH6: 0 | BI6: 0 | BJ6: 0 | BK6: 4550108948 | BL6: 0 | BM6: 0 | BN6: 0 | BO6: 4550108948 | BP6: 4550108948 | BQ6: 4550108948 | BR6: 4550108948 | BS6: 0 | BT6: 0 | BU6: 0 | BV6: 4550108948 | BW6: 4550108948 | BX6: 79.588334 | BY6: 79.588334 | BZ6: 0 | CA6: 7992109627 | CB6: 7992109627 | CC6: 7992109627 | CD6: 0 | CE6: 7992109627 | CF6: 7992109627 | CG6: 7992109627 | CH6: 7992109627 | CI6: 7992109627 | CJ6: 7992109627 | CK6: 0 | CL6: 0 | CM6: 20054.032 | CN6: 521.90589 | CO6: 0 | CP6: 1.6027402e+14 | CQ6: 4.1711291e+12 | CR6: 0 | CS6: 0 | CT6: 0 | CU6: 0 | CV6: 0 | CW6: 0 | CX6: 0 | CY6: 0 | CZ6: 0 | DA6: 0 | DB6: 0 | DC6: 0 | DD6: 0 | DE6: 0 | DF6: 0 | DG6: 0 | DH6: 0 | DI6: 1 | DJ6: 0 | DK6: 7992109627 | DL6: 0 | DM6: 7992109627 | DN6: 0 | DO6: 0 | DP6: 0 | DQ6: 0 | DR6: 0 | DS6: 0 | DT6: 0 | DU6: 0 | DV6: 0 | DW6: 0 | DX6: 0 | DY6: 0 | DZ6: 0 | EA6: 0 | EB6: 0 | EC6: 0.49 | ED6: 0 | EE6: 3.9161337e+09 | EF6: 0 | EG6: 4550108948 | EH6: 0 | EI6: 0 | EJ6: 0 | EK6: 0 | EL6: 4550108948 | EM6: 0 | EN6: 0 | EO6: 0 | EP6: 4550108948 | EQ6: 4550108948 | ER6: 34 | EU6: ~2016 | EV6: 국내출자 | EW6: 0 | EX6: 0 | EY6: 0 | EZ6: 0 | FA6: 0 | FB6: 0 | FC6: 0 | FD6: 0 | FE6: 0 | FF6: 0 | FG6: 0 | FH6: 4550108948 | FI6: 0 | FJ6: 0 | FK6: 0 | FL6: 0 | FM6: 4550108948 | FN6: 0 | FO6: 0 | FP6: 0 | FQ6: TRUE | FR6: TRUE
A7: BS00000009 | B7: 205202806201 | C7: 6000000000220 | D7: 광주제2순환도로 리파이낸싱 | E7: 광주제2순환도로(주) (Ref.) [광주시 제2순환도로 4구간] | F7: 인프라 | G7: BTO | H7: 도로 | I7: 국내 | J7: 아시아 | K7: 이머징 | L7: 한국 | M7: 해당없음 | N7: 대출 | O7: 선순위 | P7: 대출 | Q7: 프로젝트 | R7: KRW | S7: KRW | T7: 41074 | U7: 48196 | V7: 48196 | X7: PPP | Y7: Merchant(정부) | Z7: 해지시 지급금 | AA7: 해지시 지급금 전액 커버, MRG | AB7: 신한자산운용 | AC7: 해당없음 | AD7: 허강혁 | AF7: 유재섭 | AG7: 정상 | AH7: 41071 | AI7: 기보유 | AJ7: 국내실물 | AK7: 인프라 | AL7: Debt | AM7: 인출 | AN7: 운영 | AO7: 0 | AP7: 15306000000 | AQ7: 0 | AR7: 0 | AS7: 0 | AT7: 0 | AU7: 0 | AV7: 0 | AW7: 14475000000 | AX7: 289500000 | AY7: 289500000 | AZ7: 5696073794 | BA7: -289500000 | BB7: -289500000 | BC7: 8778926206 | BD7: 268229038 | BE7: 268229038 | BF7: 15199669900 | BG7: 0 | BH7: 268229038 | BI7: 0 | BJ7: 0 | BK7: 0 | BL7: 268489291 | BM7: 0 | BN7: 0 | BO7: 92685930 | BP7: 268547139 | BQ7: 92685930 | BR7: 268547139 | BS7: 0 | BT7: 0 | BU7: 0 | BV7: 92685930 | BW7: 268547139 | BX7: 1.0442371 | BY7: 3.0561794 | BZ7: 0 | CA7: 8827989192 | CB7: 9117489192 | CC7: 9117489192 | CD7: 0 | CE7: 8778926206 | CF7: 9065653205 | CG7: 9063663954 | CH7: 8778926206 | CI7: 9065653205 | CJ7: 9063663954 | CK7: 4762252 | CL7: 0 | CM7: 1.0453127 | CN7: 12.543752 | CO7: 12.543752 | CP7: 9.1767228e+09 | CQ7: 1.1012067e+11 | CR7: 1.1012067e+11 | CS7: 2.0500636 | CT7: 1.7997357e+10 | CU7: 11.8 | CV7: 0 | CW7: 0 | CX7: 11.8 | CY7: 11.8 | CZ7: 1.0359133e+11 | DA7: 0 | DB7: 0 | DC7: 3416100000 | DD7: 3416100000 | DE7: 8778926206 | DF7: 0 | DG7: 289500000 | DH7: 1 | DI7: 0 | DJ7: 8778926206 | DK7: 0 | DL7: 9063663954 | DM7: 0 | DN7: 0 | DO7: 0 | DP7: 289500000 | DQ7: 0 | DR7: 0 | DS7: 0 | DT7: 0 | DU7: 0 | DV7: 1.0569895e+10 | DW7: 0 | DX7: 0 | DY7: 0 | DZ7: 0 | EA7: 0 | EB7: 0 | EC7: 0 | ED7: 0 | EE7: 0 | EF7: 0 | EG7: 92685930 | EH7: 0 | EI7: 0 | EJ7: 0 | EK7: 0 | EL7: 268547139 | EM7: 0 | EN7: 0 | EO7: 0 | EP7: 92685930 | EQ7: 268547139 | ER7: 233 | EU7: ~2016 | EV7: 국내대출 | EW7: 0 | EX7: 92685930 | EY7: 0 | EZ7: 0 | FA7: 0 | FB7: 0 | FC7: 268547139 | FD7: 0 | FE7: 0 | FF7: 0 | FG7: 0 | FH7: 0 | FI7: 0 | FJ7: 0 | FK7: 0 | FL7: 0 | FM7: 0 | FN7: 0 | FO7: 0 | FP7: 0 | FQ7: TRUE | FR7: TRUE
A8: BS00000009 | B8: BS0000000901 | C8: 100001936 | D8: 광주제2순환도로 리파이낸싱 | E8: 광주제2순환도로 | F8: 인프라 | G8: BTO | H8: 도로 | I8: 국내 | J8: 아시아 | K8: 이머징 | L8: 한국 | M8: 해당없음 | N8: 출자 | O8: 지분 | P8: 주식형 | Q8: 프로젝트 | R8: KRW | S8: KRW | T8: 40542 | U8: 2958465 | V8: 2958465 | X8: PPP | Y8: Merchant(정부) | Z8: 해지시 지급금 | AA8: 해지시 지급금 전액 커버, MRG | AB8: 신한자산운용 | AC8: 해당없음 | AD8: 허강혁 | AF8: 유재섭 | AG8: 정상 | AI8: 기보유 | AJ8: 국내실물 | AK8: 인프라 | AL8: Equity | AM8: 인출 | AN8: 운영 | AO8: 0 | AP8: 7514000000 | AQ8: 0 | AR8: 0 | AS8: 0 | AT8: 0 | AU8: 0 | AV8: 0 | AW8: 0 | AX8: 0 | AY8: 0 | AZ8: 0 | BA8: 0 | BB8: 0 | BC8: 0 | BD8: 0 | BE8: 0 | BF8: 3456279000 | BG8: 0 | BH8: 0 | BI8: 0 | BJ8: 0 | BK8: 0 | BL8: 0 | BM8: 0 | BN8: 0 | BO8: 0 | BP8: 0 | BQ8: 0 | BR8: 0 | BS8: 0 | BT8: 0 | BU8: 0 | BV8: 0 | BW8: 0 | BX8: 0 | BY8: 0 | BZ8: 0 | CA8: 4637073861 | CB8: 4637073861 | CC8: 4637073861 | CD8: 0 | CE8: 4637073861 | CF8: 4637073861 | CG8: 4637073861 | CH8: 4637073861 | CI8: 4637073861 | CJ8: 4637073861 | CK8: 0 | CL8: 0 | CM8: 2.9802322e-07 | CN8: 2.9802322e-07 | CO8: 0 | CP8: 1381.9557 | CQ8: 1381.9557 | CR8: 0 | CS8: 0 | CT8: 0 | CU8: 0 | CV8: 0 | CW8: 0 | CX8: 0 | CY8: 0 | CZ8: 0 | DA8: 0 | DB8: 0 | DC8: 0 | DD8: 0 | DE8: 0 | DF8: 0 | DG8: 0 | DH8: 0 | DI8: 1 | DJ8: 0 | DK8: 4637073861 | DL8: 0 | DM8: 4637073861 | DN8: 0 | DO8: 0 | DP8: 0 | DQ8: 0 | DR8: 0 | DS8: 0 | DT8: 0 | DU8: 0 | DV8: 0 | DW8: 0 | DX8: 0 | DY8: 0 | DZ8: 0 | EA8: 0 | EB8: 0 | EC8: 0.49 | ED8: 0 | EE8: 2.2721662e+09 | EF8: 0 | EG8: 0 | EH8: 0 | EI8: 0 | EJ8: 0 | EK8: 0 | EL8: 0 | EM8: 0 | EN8: 0 | EO8: 0 | EP8: 0 | EQ8: 0 | ER8: 450 | EU8: ~2016 | EV8: 국내출자 | EW8: 0 | EX8: 0 | EY8: 0 | EZ8: 0 | FA8: 0 | FB8: 0 | FC8: 0 | FD8: 0 | FE8: 0 | FF8: 0 | FG8: 0 | FH8: 0 | FI8: 0 | FJ8: 0 | FK8: 0 | FL8: 0 | FM8: 0 | FN8: 0 | FO8: 0 | FP8: 0 | FQ8: TRUE | FR8: TRUE
A9: BS00000009 | B9: BS0000000902 | C9: 200000307 | D9: 광주제2순환도로 리파이낸싱 | E9: 한화광주순환도로사모특별자산투자신탁1호(인프라) | F9: 인프라 | G9: BTO | H9: 도로 | I9: 국내 | J9: 아시아 | K9: 이머징 | L9: 한국 | M9: 해당없음 | N9: 수익증권 | O9: 지분 | P9: 채권형 | Q9: 프로젝트 | R9: KRW | S9: KRW | T9: 40542 | U9: 49307 | V9: 49307 | X9: PPP | Y9: Merchant(정부) | Z9: 해지시 지급금 | AA9: 해지시 지급금 전액 커버, MRG | AB9: 한화자산운용 | AC9: 해당없음 | AD9: 허강혁 | AF9: 유재섭 | AG9: 정상 | AI9: 기보유 | AJ9: 국내실물 | AK9: 인프라 | AL9: Equity | AM9: 인출 | AN9: 운영 | AO9: 0 | AP9: 26000000000 | AQ9: 0 | AR9: 0 | AS9: 0 | AT9: 0 | AU9: 0 | AV9: 0 | AW9: 24342500000 | AX9: 376360000 | AY9: 376360000 | AZ9: 7341309131 | BA9: -376360000 | BB9: -376360000 | BC9: 17001190869 | BD9: 326964052 | BE9: 326964052 | BF9: 29662909086 | BG9: 326964052 | BH9: 0 | BI9: 0 | BJ9: -338987075 | BK9: 326964052 | BL9: 0 | BM9: -4606357116 | BN9: -4606357116 | BO9: 326964052 | BP9: 326964052 | BQ9: -4279393064 | BR9: -4279393064 | BS9: 0 | BT9: 0 | BU9: 0 | BV9: -4279393064 | BW9: -4279393064 | BX9: -12.988891 | BY9: -12.988891 | BZ9: 0 | CA9: 17044368061 | CB9: 17418571933 | CC9: 17418571933 | CD9: 0 | CE9: 28315507222 | CF9: 33298224338 | CG9: 33298224338 | CH9: 28315507222 | CI9: 33298224338 | CJ9: 33298224338 | CK9: -4606357116 | CL9: 0 | CM9: -80.228171 | CN9: -42.766382 | CO9: 10.677803 | CP9: -2.2717013e+12 | CQ9: -1.2109518e+12 | CR9: 3.0234741e+11 | CS9: 2.6833614 | CT9: 7.598074e+10 | CU9: 0 | CV9: 0 | CW9: 0 | CX9: 0 | CY9: 0 | CZ9: 0 | DA9: 0 | DB9: 0 | DC9: 0 | DD9: 0 | DE9: 0 | DF9: 0 | DG9: 0 | DH9: 0.46218409 | DI9: 0.53781591 | DJ9: 1.3086977e+10 | DK9: 1.522853e+10 | DL9: 1.538991e+10 | DM9: 1.7908315e+10 | DN9: 0 | DO9: 0 | DP9: 1.739476e+08 | DQ9: 2.024124e+08 | DR9: 0 | DS9: 0 | DT9: 0 | DU9: 0 | DV9: 30632504548 | DW9: 4.4920186e+08 | DX9: 0 | DY9: 3.0039875e+09 | DZ9: 0 | EA9: 0 | EB9: 3.4531894e+09 | EC9: 0.11272958 | ED9: 3.4531894e+09 | EE9: 3.1919953e+09 | EF9: 0 | EG9: 326964052 | EH9: -338987075 | EI9: 0 | EJ9: -4267370041 | EK9: 0 | EL9: 326964052 | EM9: -338987075 | EN9: 0 | EO9: -4267370041 | EP9: -4279393064 | EQ9: -4279393064 | ER9: 755 | EU9: ~2016 | EV9: 국내간접투자 | EW9: 0 | EX9: 1.5111758e+08 | EY9: -1.5667443e+08 | EZ9: 0 | FA9: -1.9723105e+09 | FB9: 0 | FC9: 1.5111758e+08 | FD9: -1.5667443e+08 | FE9: 0 | FF9: -1.9723105e+09 | FG9: 0 | FH9: 1.7584647e+08 | FI9: -1.8231264e+08 | FJ9: 0 | FK9: -2.2950595e+09 | FL9: 0 | FM9: 1.7584647e+08 | FN9: -1.8231264e+08 | FO9: 0 | FP9: -2.2950595e+09 | FQ9: TRUE | FR9: TRUE
A10: BS00000021 | B10: BS0000002101 | C10: 200000318 | D10: 흥국 인프라 사모특별자산투자신탁 2호 (대구동부순환도로 리파이낸싱) | E10: 흥국인프라사모특별자산투자신탁2호 | F10: 인프라 | G10: BTO | H10: 도로 | I10: 국내 | J10: 아시아 | K10: 이머징 | L10: 한국 | M10: 해당없음 | N10: 수익증권 | O10: 선순위 | P10: 채권형 | Q10: 프로젝트 | R10: KRW | S10: KRW | T10: 41085 | U10: 46562 | V10: 46562 | X10: PPP | Y10: Merchant(정부) | Z10: 해지시 지급금 | AA10: 정부재정지원금에 의해 투자금 상환 | AB10: 흥국자산운용 | AC10: 해당없음 | AD10: 허강혁 | AF10: 유재섭 | AG10: 정상 | AI10: 기보유 | AJ10: 국내실물 | AK10: 인프라 | AL10: Debt | AM10: 인출 | AN10: 운영 | AO10: 0 | AP10: 90000000000 | AQ10: 0 | AR10: 0 | AS10: 0 | AT10: 0 | AU10: 0 | AV10: 0 | AW10: 90000000000 | AX10: 0 | AY10: 3713559383 | AZ10: 85685503961 | BA10: 0 | BB10: -3713559383 | BC10: 4314496039 | BD10: 0 | BE10: 58729548 | BF10: 33598027940 | BG10: 58729548 | BH10: 0 | BI10: 0 | BJ10: -20722697 | BK10: 58729548 | BL10: 0 | BM10: -56904267 | BN10: -77626964 | BO10: 0 | BP10: 58729548 | BQ10: -56904267 | BR10: -18897416 | BS10: 0 | BT10: 0 | BU10: 0 | BV10: -56904267 | BW10: -18897416 | BX10: -1.3006076 | BY10: -0.30365373 | BZ10: 0 | CA10: 4351144467 | CB10: 4351144467 | CC10: 8064889537 | CD10: 0 | CE10: 4318302029 | CF10: 4375206296 | CG10: 8109488376 | CH10: 4318302029 | CI10: 4375206296 | CJ10: 8109488376 | CK10: -77626964 | CL10: 0 | CM10: -14.284853 | CN10: -1.3333544 | CO10: 4.6826825 | CP10: -6.1686308e+10 | CQ10: -5.7578271e+09 | CR10: 2.0221237e+10 | CS10: 1.3733537 | CT10: 5.9305561e+09 | CU10: 0 | CV10: 0 | CW10: 0 | CX10: 0 | CY10: 0 | CZ10: 0 | DA10: 0 | DB10: 0 | DC10: 0 | DD10: 0 | DE10: 0 | DF10: 0 | DG10: 0 | DH10: 0.97900569 | DI10: 0.020994315 | DJ10: 4.2276422e+09 | DK10: 90659792 | DL10: 7.9392352e+09 | DM10: 1.7025315e+08 | DN10: 0 | DO10: 0 | DP10: 3.6355957e+09 | DQ10: 77963635 | DR10: 0 | DS10: 0 | DT10: 0 | DU10: 0 | DV10: 12366205950 | DW10: 1.7984159e+08 | DX10: 0 | DY10: 71566935 | DZ10: 0 | EA10: 0 | EB10: 2.5140853e+08 | EC10: 0.020330288 | ED10: 2.5140853e+08 | EE10: 87792323 | EF10: 0 | EG10: 0 | EH10: 0 | EI10: 0 | EJ10: -56904267 | EK10: 0 | EL10: 58729548 | EM10: -20722697 | EN10: 0 | EO10: -56904267 | EP10: -56904267 | EQ10: -18897416 | ER10: 708 | EU10: ~2016 | EV10: 국내간접투자 | EW10: 0 | EX10: 0 | EY10: 0 | EZ10: 0 | FA10: -55709601 | FB10: 0 | FC10: 57496561 | FD10: -20287638 | FE10: 0 | FF10: -55709601 | FG10: 0 | FH10: 0 | FI10: 0 | FJ10: 0 | FK10: -1194666.1 | FL10: 0 | FM10: 1232986.6 | FN10: -435058.82 | FO10: 0 | FP10: -1194666.1 | FQ10: TRUE | FR10: TRUE
A11: BS00000028 | B11: BS0000002801 | C11: 100001931 | D11: 대구 이시아폴리스 선순위담보대출 (지분) | E11: 이시아폴리스 | F11: 부동산 | G11: 수익형 | H11: 리테일 | I11: 국내 | J11: 아시아 | K11: 이머징 | L11: 한국 | M11: 기타 | N11: 출자 | O11: 지분 | P11: 주식형 | Q11: 프로젝트 | R11: KRW | S11: KRW | T11: 38852 | U11: 45016 | V11: 45016 | W11: 45016 | X11: 해당없음 | Y11: 해당없음 | Z11: 우량임차인 책임임차 | AA11: 우량임차인 책임임차 | AB11: 마스턴투자운용 | AC11: 해당없음 | AD11: 상환/확인필요 | AF11: 하아연 | AG11: 정상 | AI11: 기보유 | AJ11: 국내실물 | AK11: 부동산 | AL11: Equity | AM11: 인출 | AN11: 상환 | AO11: 0 | AP11: 855000000 | AQ11: 0 | AR11: 0 | AS11: 0 | AT11: 0 | AU11: 0 | AV11: 0 | AW11: 0 | AX11: 0 | AY11: 0 | AZ11: 0 | BA11: 0 | BB11: 0 | BC11: 0 | BD11: 0 | BE11: 0 | BF11: 0 | BG11: 0 | BH11: 0 | BI11: 0 | BJ11: 0 | BK11: 0 | BL11: 0 | BM11: 0 | BN11: 0 | BO11: 0 | BP11: 0 | BQ11: 0 | BR11: 0 | BS11: 0 | BT11: 0 | BU11: 0 | BV11: 0 | BW11: 0 | BX11: 0 | BY11: 0 | BZ11: 0 | CA11: 0 | CB11: 0 | CC11: 0 | CD11: 0 | CE11: 0 | CF11: 0 | CG11: 0 | CH11: 0 | CI11: 0 | CJ11: 0 | CK11: 0 | CL11: 0 | CM11: 0 | CN11: 0 | CO11: 0 | CP11: 0 | CQ11: 0 | CR11: 0 | CS11: 0 | CT11: 0 | CU11: 0 | CV11: 0 | CW11: 0 | CX11: 0 | CY11: 0 | CZ11: 0 | DA11: 0 | DB11: 0 | DC11: 0 | DD11: 0 | DE11: 0 | DF11: 0 | DG11: 0 | DH11: 0 | DI11: 1 | DJ11: 0 | DK11: 0 | DL11: 0 | DM11: 0 | DN11: 0 | DO11: 0 | DP11: 0 | DQ11: 0 | DR11: 0 | DS11: 0 | DT11: 0 | DU11: 0 | DV11: 0 | DW11: 0 | DX11: 0 | DY11: 0 | DZ11: 0 | EA11: 0 | EB11: 0 | EC11: 0 | ED11: 0 | EE11: 0 | EF11: 0 | EG11: 0 | EH11: 0 | EI11: 0 | EJ11: 0 | EK11: 0 | EL11: 0 | EM11: 0 | EN11: 0 | EO11: 0 | EP11: 0 | EQ11: 0 | ER11: 450 | EU11: ~2016 | EV11: 국내출자 | EW11: 0 | EX11: 0 | EY11: 0 | EZ11: 0 | FA11: 0 | FB11: 0 | FC11: 0 | FD11: 0 | FE11: 0 | FF11: 0 | FG11: 0 | FH11: 0 | FI11: 0 | FJ11: 0 | FK11: 0 | FL11: 0 | FM11: 0 | FN11: 0 | FO11: 0 | FP11: 0 | FQ11: TRUE | FR11: TRUE
A12: BS00000029 | B12: 905362440900 | C12: 6000000000209 | D12: 푸른김해지키미 | E12: 푸른김해지키미 | F12: 인프라 | G12: BTL | H12: 하수관거 | I12: 국내 | J12: 아시아 | K12: 이머징 | L12: 한국 | M12: 해당없음 | N12: 대출 | O12: 선순위 | P12: 대출 | Q12: 프로젝트 | R12: KRW | S12: KRW | T12: 40289 | U12: 2958465 | V12: 2958465 | X12: PPP | Y12: Availability(정부) | Z12: 정부보증 | AA12: 정부가 임대료 지급 | AB12: IBK기업은행 | AC12: 해당없음 | AD12: 이건희 | AF12: 유재섭 | AG12: 정상 | AH12: 38833 | AI12: 기보유 | AJ12: 국내실물 | AK12: 인프라 | AL12: Debt | AM12: 인출 | AN12: 운영 | AO12: 0 | AP12: 16135000000 | AQ12: 0 | AR12: 0 | AS12: 0 | AT12: 0 | AU12: 0 | AV12: 0 | AW12: 13173000000 | AX12: 257000000 | AY12: 257000000 | AZ12: 10338256442 | BA12: -257000000 | BB12: -257000000 | BC12: 2834743558 | BD12: 26534566 | BE12: 26534566 | BF12: 1589620445 | BG12: 0 | BH12: 26534566 | BI12: 0 | BJ12: 0 | BK12: 0 | BL12: 26510063 | BM12: 0 | BN12: 0 | BO12: 9170065 | BP12: 26561468 | BQ12: 9170065 | BR12: 26561468 | BS12: 0 | BT12: 0 | BU12: 0 | BV12: 9170065 | BW12: 26561468 | BX12: 0.30994265 | BY12: 0.90040794 | BZ12: 0 | CA12: 2835310620 | CB12: 3092310620 | CC12: 3092310620 | CD12: 0 | CE12: 2834743558 | CF12: 3091692158 | CG12: 3091692158 | CH12: 2834743558 | CI12: 3091692158 | CJ12: 3091692158 | CK12: 51400 | CL12: 0 | CM12: 0.29291694 | CN12: 3.5150033 | CO12: 3.5150033 | CP12: 8.3034441e+08 | CQ12: 9.964133e+09 | CR12: 9.964133e+09 | CS12: 1.1206726 | CT12: 3.1768195e+09 | CU12: 3.48 | CV12: 0 | CW12: 0 | CX12: 3.48 | CY12: 3.48 | CZ12: 9.8649076e+09 | DA12: 0 | DB12: 0 | DC12: 894360000 | DD12: 894360000 | DE12: 2834743558 | DF12: 0 | DG12: 257000000 | DH12: 1 | DI12: 0 | DJ12: 2834743558 | DK12: 0 | DL12: 3091692158 | DM12: 0 | DN12: 0 | DO12: 0 | DP12: 257000000 | DQ12: 0 | DR12: 0 | DS12: 0 | DT12: 0 | DU12: 0 | DV12: 3.6532799e+09 | DW12: 0 | DX12: 0 | DY12: 0 | DZ12: 0 | EA12: 0 | EB12: 0 | EC12: 0 | ED12: 0 | EE12: 0 | EF12: 0 | EG12: 9170065 | EH12: 0 | EI12: 0 | EJ12: 0 | EK12: 0 | EL12: 26561468 | EM12: 0 | EN12: 0 | EO12: 0 | EP12: 9170065 | EQ12: 26561468 | ER12: 330 | EU12: ~2016 | EV12: 국내대출 | EW12: 0 | EX12: 9170065 | EY12: 0 | EZ12: 0 | FA12: 0 | FB12: 0 | FC12: 26561468 | FD12: 0 | FE12: 0 | FF12: 0 | FG12: 0 | FH12: 0 | FI12: 0 | FJ12: 0 | FK12: 0 | FL12: 0 | FM12: 0 | FN12: 0 | FO12: 0 | FP12: 0 | FQ12: TRUE | FR12: TRUE
A13: BS00000029 | B13: 905362440900 | C13: 6000000000350 | D13: 푸른김해지키미 | E13: 푸른김해지키미 | F13: 인프라 | G13: BTL | H13: 하수관거 | I13: 국내 | J13: 아시아 | K13: 이머징 | L13: 한국 | M13: 해당없음 | N13: 대출 | O13: 선순위 | P13: 대출 | Q13: 프로젝트 | R13: KRW | S13: KRW | T13: 40289 | U13: 2958465 | V13: 2958465 | X13: PPP | Y13: Availability(정부) | Z13: 정부보증 | AA13: 정부가 임대료 지급 | AB13: IBK기업은행 | AC13: 해당없음 | AD13: 이건희 | AF13: 유재섭 | AG13: 정상 | AH13: 38833 | AI13: 기보유 | AJ13: 국내실물 | AK13: 인프라 | AL13: Debt | AM13: 인출 | AN13: 운영 | AO13: 0 | AP13: 2850270000 | AQ13: 0 | AR13: 0 | AS13: 0 | AT13: 0 | AU13: 0 | AV13: 0 | AW13: 2850270000 | AX13: 56000000 | AY13: 56000000 | AZ13: 2230870338 | BA13: -56000000 | BB13: -56000000 | BC13: 619399662 | BD13: 12625813 | BE13: 12625813 | BF13: 768105592 | BG13: 0 | BH13: 12625813 | BI13: 0 | BJ13: 0 | BK13: 0 | BL13: 12614183 | BM13: 0 | BN13: 0 | BO13: 4350118 | BP13: 12625385 | BQ13: 4350118 | BR13: 12625385 | BS13: 0 | BT13: 0 | BU13: 0 | BV13: 4350118 | BW13: 12625385 | BX13: 0.67420798 | BY13: 1.9693888 | BZ13: 0 | CA13: 619523567 | CB13: 675523567 | CC13: 675523567 | CD13: 0 | CE13: 619399662 | CF13: 675388462 | CG13: 675388462 | CH13: 619399662 | CI13: 675388462 | CJ13: 675388462 | CK13: 11200 | CL13: 0 | CM13: 0.64776099 | CN13: 7.7731319 | CO13: 7.7731319 | CP13: 4.0122294e+08 | CQ13: 4.8146753e+09 | CR13: 4.8146753e+09 | CS13: 1.2694852 | CT13: 7.8631871e+08 | CU13: 7.58 | CV13: 0 | CW13: 0 | CX13: 7.58 | CY13: 7.58 | CZ13: 4.6950494e+09 | DA13: 0 | DB13: 0 | DC13: 424480000 | DD13: 424480000 | DE13: 619399662 | DF13: 0 | DG13: 56000000 | DH13: 1 | DI13: 0 | DJ13: 619399662 | DK13: 0 | DL13: 675388462 | DM13: 0 | DN13: 0 | DO13: 0 | DP13: 56000000 | DQ13: 0 | DR13: 0 | DS13: 0 | DT13: 0 | DU13: 0 | DV13: 8.0969773e+08 | DW13: 0 | DX13: 0 | DY13: 0 | DZ13: 0 | EA13: 0 | EB13: 0 | EC13: 0 | ED13: 0 | EE13: 0 | EF13: 0 | EG13: 4350118 | EH13: 0 | EI13: 0 | EJ13: 0 | EK13: 0 | EL13: 12625385 | EM13: 0 | EN13: 0 | EO13: 0 | EP13: 4350118 | EQ13: 12625385 | ER13: 344 | EU13: ~2016 | EV13: 국내대출 | EW13: 0 | EX13: 4350118 | EY13: 0 | EZ13: 0 | FA13: 0 | FB13: 0 | FC13: 12625385 | FD13: 0 | FE13: 0 | FF13: 0 | FG13: 0 | FH13: 0 | FI13: 0 | FJ13: 0 | FK13: 0 | FL13: 0 | FM13: 0 | FN13: 0 | FO13: 0 | FP13: 0 | FQ13: TRUE | FR13: TRUE
A14: BS00000029 | B14: BS0000002901 | C14: 100001929 | D14: 푸른김해지키미 | E14: 푸른김해지키미 | F14: 인프라 | G14: BTL | H14: 하수관거 | I14: 국내 | J14: 아시아 | K14: 이머징 | L14: 한국 | M14: 해당없음 | N14: 출자 | O14: 지분 | P14: 주식형 | Q14: 프로젝트 | R14: KRW | S14: KRW | T14: 38825 | U14: 2958465 | V14: 2958465 | X14: PPP | Y14: Availability(정부) | Z14: 정부보증 | AA14: 정부가 임대료 지급 | AB14: IBK기업은행 | AC14: 해당없음 | AD14: 이건희 | AF14: 유재섭 | AG14: 정상 | AH14: 38833 | AI14: 기보유 | AJ14: 국내실물 | AK14: 인프라 | AL14: Equity | AM14: 인출 | AN14: 운영 | AO14: 0 | AP14: 1433765102 | AQ14: 0 | AR14: 0 | AS14: 0 | AT14: 0 | AU14: 0 | AV14: 0 | AW14: 0 | AX14: 0 | AY14: 0 | AZ14: 0 | BA14: 0 | BB14: 0 | BC14: 0 | BD14: 0 | BE14: 0 | BF14: 0 | BG14: 0 | BH14: 0 | BI14: 0 | BJ14: 0 | BK14: 0 | BL14: 0 | BM14: 0 | BN14: 0 | BO14: 0 | BP14: 0 | BQ14: 0 | BR14: 0 | BS14: 0 | BT14: 0 | BU14: 0 | BV14: 0 | BW14: 0 | BX14: 0 | BY14: 0 | BZ14: 0 | CA14: 1433765102 | CB14: 1433765102 | CC14: 1433765102 | CD14: 0 | CE14: 1411009704 | CF14: 1411009704 | CG14: 1411009704 | CH14: 1411009704 | CI14: 1411009704 | CJ14: 1411009704 | CK14: 0 | CL14: 0 | CM14: 2.9802322e-07 | CN14: 2.9802322e-07 | CO14: 0 | CP14: 420.51366 | CQ14: 420.51366 | CR14: 0 | CS14: 0 | CT14: 0 | CU14: 0 | CV14: 0 | CW14: 0 | CX14: 0 | CY14: 0 | CZ14: 0 | DA14: 0 | DB14: 0 | DC14: 0 | DD14: 0 | DE14: 0 | DF14: 0 | DG14: 0 | DH14: 0 | DI14: 1 | DJ14: 0 | DK14: 1411009704 | DL14: 0 | DM14: 1411009704 | DN14: 0 | DO14: 0 | DP14: 0 | DQ14: 0 | DR14: 0 | DS14: 0 | DT14: 0 | DU14: 0 | DV14: 989458535 | DW14: 0 | DX14: 0 | DY14: 197891707 | DZ14: 0 | EA14: 0 | EB14: 197891707 | EC14: 0.2 | ED14: 197891707 | EE14: 2.8220194e+08 | EF14: 0 | EG14: 0 | EH14: 0 | EI14: 0 | EJ14: 0 | EK14: 0 | EL14: 0 | EM14: 0 | EN14: 0 | EO14: 0 | EP14: 0 | EQ14: 0 | ER14: 450 | EU14: ~2016 | EV14: 국내출자 | EW14: 0 | EX14: 0 | EY14: 0 | EZ14: 0 | FA14: 0 | FB14: 0 | FC14: 0 | FD14: 0 | FE14: 0 | FF14: 0 | FG14: 0 | FH14: 0 | FI14: 0 | FJ14: 0 | FK14: 0 | FL14: 0 | FM14: 0 | FN14: 0 | FO14: 0 | FP14: 0 | FQ14: TRUE | FR14: TRUE
A15: BS00000030 | B15: 105370639100 | C15: 6000000000250 | D15: 청정상주 | E15: 청정상주주식회사 | F15: 인프라 | G15: BTL | H15: 하수관거 | I15: 국내 | J15: 아시아 | K15: 이머징 | L15: 한국 | M15: 해당없음 | N15: 대출 | O15: 선순위 | P15: 대출 | Q15: 프로젝트 | R15: KRW | S15: KRW | T15: 40239 | U15: 2958465 | V15: 2958465 | X15: PPP | Y15: Availability(정부) | Z15: 정부보증 | AA15: 정부가 임대료 지급 | AB15: IBK기업은행 | AC15: 해당없음 | AD15: 허강혁 | AF15: 유재섭 | AG15: 정상 | AH15: 38854 | AI15: 기보유 | AJ15: 국내실물 | AK15: 인프라 | AL15: Debt | AM15: 인출 | AN15: 운영 | AO15: 0 | AP15: 12481125000 | AQ15: 0 | AR15: 0 | AS15: 0 | AT15: 0 | AU15: 0 | AV15: 0 | AW15: 12481125000 | AX15: 210562500 | AY15: 210562500 | AZ15: 9576016638 | BA15: -210562500 | BB15: -210562500 | BC15: 2905108362 | BD15: 28276785 | BE15: 28276785 | BF15: 1740021585 | BG15: 0 | BH15: 28276785 | BI15: 0 | BJ15: 0 | BK15: 0 | BL15: 28255556 | BM15: 0 | BN15: 0 | BO15: 9764375 | BP15: 28297672 | BQ15: 9764375 | BR15: 28297672 | BS15: 0 | BT15: 0 | BU15: 0 | BV15: 9764375 | BW15: 28297672 | BX15: 0.32488502 | BY15: 0.94444582 | BZ15: 0 | CA15: 2905689500 | CB15: 3116252000 | CC15: 3116252000 | CD15: 0 | CE15: 2905108362 | CF15: 3115628750 | CG15: 3115628750 | CH15: 2905108362 | CI15: 3115628750 | CJ15: 3115628750 | CK15: 42112 | CL15: 0 | CM15: 0.31020152 | CN15: 3.7224182 | CO15: 3.7224182 | CP15: 9.0116902e+08 | CQ15: 1.0814028e+10 | CR15: 1.0814028e+10 | CS15: 1.1394122 | CT15: 3.310116e+09 | CU15: 3.68 | CV15: 0 | CW15: 0 | CX15: 3.68 | CY15: 3.68 | CZ15: 1.0690799e+10 | DA15: 0 | DB15: 0 | DC15: 774870000 | DD15: 774870000 | DE15: 2905108362 | DF15: 0 | DG15: 210562500 | DH15: 1 | DI15: 0 | DJ15: 2905108362 | DK15: 0 | DL15: 3115628750 | DM15: 0 | DN15: 0 | DO15: 0 | DP15: 210562500 | DQ15: 0 | DR15: 0 | DS15: 0 | DT15: 0 | DU15: 0 | DV15: 3.5993915e+09 | DW15: 0 | DX15: 0 | DY15: 0 | DZ15: 0 | EA15: 0 | EB15: 0 | EC15: 0 | ED15: 0 | EE15: 0 | EF15: 0 | EG15: 9764375 | EH15: 0 | EI15: 0 | EJ15: 0 | EK15: 0 | EL15: 28297672 | EM15: 0 | EN15: 0 | EO15: 0 | EP15: 9764375 | EQ15: 28297672 | ER15: 325 | EU15: ~2016 | EV15: 국내대출 | EW15: 0 | EX15: 9764375 | EY15: 0 | EZ15: 0 | FA15: 0 | FB15: 0 | FC15: 28297672 | FD15: 0 | FE15: 0 | FF15: 0 | FG15: 0 | FH15: 0 | FI15: 0 | FJ15: 0 | FK15: 0 | FL15: 0 | FM15: 0 | FN15: 0 | FO15: 0 | FP15: 0 | FQ15: TRUE | FR15: TRUE
A16: BS00000030 | B16: 105370639100 | C16: 6000000000251 | D16: 청정상주 | E16: 청정상주주식회사 | F16: 인프라 | G16: BTL | H16: 하수관거 | I16: 국내 | J16: 아시아 | K16: 이머징 | L16: 한국 | M16: 해당없음 | N16: 대출 | O16: 선순위 | P16: 대출 | Q16: 프로젝트 | R16: KRW | S16: KRW | T16: 40239 | U16: 2958465 | V16: 2958465 | X16: PPP | Y16: Availability(정부) | Z16: 정부보증 | AA16: 정부가 임대료 지급 | AB16: IBK기업은행 | AC16: 해당없음 | AD16: 허강혁 | AF16: 유재섭 | AG16: 정상 | AH16: 38854 | AI16: 기보유 | AJ16: 국내실물 | AK16: 인프라 | AL16: Debt | AM16: 인출 | AN16: 운영 | AO16: 0 | AP16: 2698875000 | AQ16: 0 | AR16: 0 | AS16: 0 | AT16: 0 | AU16: 0 | AV16: 0 | AW16: 2698875000 | AX16: 45562500 | AY16: 45562500 | AZ16: 2070497201 | BA16: -45562500 | BB16: -45562500 | BC16: 628377799 | BD16: 13296644 | BE16: 13296644 | BF16: 831348233 | BG16: 0 | BH16: 13296644 | BI16: 0 | BJ16: 0 | BK16: 0 | BL16: 13286658 | BM16: 0 | BN16: 0 | BO16: 4580826 | BP16: 13295772 | BQ16: 4580826 | BR16: 13295772 | BS16: 0 | BT16: 0 | BU16: 0 | BV16: 4580826 | BW16: 13295772 | BX16: 0.7059762 | BY16: 2.062938 | BZ16: 0 | CA16: 628503500 | CB16: 674066000 | CC16: 674066000 | CD16: 0 | CE16: 628377799 | CF16: 673931187 | CG16: 673931187 | CH16: 628377799 | CI16: 673931187 | CJ16: 673931187 | CK16: 9112 | CL16: 0 | CM16: 0.68519433 | CN16: 8.222332 | CO16: 8.222332 | CP16: 4.3056091e+08 | CQ16: 5.1667309e+09 | CR16: 5.1667309e+09 | CS16: 1.3080351 | CT16: 8.2194022e+08 | CU16: 8 | CV16: 0 | CW16: 0 | CX16: 8 | CY16: 8 | CZ16: 5027022392 | DA16: 0 | DB16: 0 | DC16: 364500000 | DD16: 364500000 | DE16: 628377799 | DF16: 0 | DG16: 45562500 | DH16: 1 | DI16: 0 | DJ16: 628377799 | DK16: 0 | DL16: 673931187 | DM16: 0 | DN16: 0 | DO16: 0 | DP16: 45562500 | DQ16: 0 | DR16: 0 | DS16: 0 | DT16: 0 | DU16: 0 | DV16: 8.2515357e+08 | DW16: 0 | DX16: 0 | DY16: 0 | DZ16: 0 | EA16: 0 | EB16: 0 | EC16: 0 | ED16: 0 | EE16: 0 | EF16: 0 | EG16: 4580826 | EH16: 0 | EI16: 0 | EJ16: 0 | EK16: 0 | EL16: 13295772 | EM16: 0 | EN16: 0 | EO16: 0 | EP16: 4580826 | EQ16: 13295772 | ER16: 342 | EU16: ~2016 | EV16: 국내대출 | EW16: 0 | EX16: 4580826 | EY16: 0 | EZ16: 0 | FA16: 0 | FB16: 0 | FC16: 13295772 | FD16: 0 | FE16: 0 | FF16: 0 | FG16: 0 | FH16: 0 | FI16: 0 | FJ16: 0 | FK16: 0 | FL16: 0 | FM16: 0 | FN16: 0 | FO16: 0 | FP16: 0 | FQ16: TRUE | FR16: TRUE
A17: BS00000030 | B17: BS0000003001 | C17: 100001937 | D17: 청정상주 | E17: 청정상주 | F17: 인프라 | G17: BTL | H17: 하수관거 | I17: 국내 | J17: 아시아 | K17: 이머징 | L17: 한국 | M17: 해당없음 | N17: 출자 | O17: 지분 | P17: 주식형 | Q17: 프로젝트 | R17: KRW | S17: KRW | T17: 38840 | U17: 2958465 | V17: 2958465 | X17: PPP | Y17: Availability(정부) | Z17: 정부보증 | AA17: 정부가 임대료 지급 | AB17: IBK기업은행 | AC17: 해당없음 | AD17: 허강혁 | AF17: 유재섭 | AG17: 정상 | AH17: 38854 | AI17: 기보유 | AJ17: 국내실물 | AK17: 인프라 | AL17: Equity | AM17: 인출 | AN17: 운영 | AO17: 0 | AP17: 1349000000 | AQ17: 0 | AR17: 0 | AS17: 0 | AT17: 0 | AU17: 0 | AV17: 0 | AW17: 0 | AX17: 0 | AY17: 0 | AZ17: 0 | BA17: 0 | BB17: 0 | BC17: 0 | BD17: 0 | BE17: 0 | BF17: 0 | BG17: 0 | BH17: 0 | BI17: 0 | BJ17: 0 | BK17: 0 | BL17: 0 | BM17: 0 | BN17: 0 | BO17: 0 | BP17: 0 | BQ17: 0 | BR17: 0 | BS17: 0 | BT17: 0 | BU17: 0 | BV17: 0 | BW17: 0 | BX17: 0 | BY17: 0 | BZ17: 0 | CA17: 1323372965 | CB17: 1323372965 | CC17: 1323372965 | CD17: 0 | CE17: 1323372965 | CF17: 1323372965 | CG17: 1323372965 | CH17: 1323372965 | CI17: 1323372965 | CJ17: 1323372965 | CK17: 0 | CL17: 0 | CM17: 2.9802322e-07 | CN17: 2.9802322e-07 | CO17: 0 | CP17: 394.39588 | CQ17: 394.39588 | CR17: 0 | CS17: 0 | CT17: 0 | CU17: 0 | CV17: 0 | CW17: 0 | CX17: 0 | CY17: 0 | CZ17: 0 | DA17: 0 | DB17: 0 | DC17: 0 | DD17: 0 | DE17: 0 | DF17: 0 | DG17: 0 | DH17: 0 | DI17: 1 | DJ17: 0 | DK17: 1323372965 | DL17: 0 | DM17: 1323372965 | DN17: 0 | DO17: 0 | DP17: 0 | DQ17: 0 | DR17: 0 | DS17: 0 | DT17: 0 | DU17: 0 | DV17: 881891163 | DW17: 0 | DX17: 0 | DY17: 1.7637823e+08 | DZ17: 0 | EA17: 0 | EB17: 1.7637823e+08 | EC17: 0.2 | ED17: 1.7637823e+08 | EE17: 2.6467459e+08 | EF17: 0 | EG17: 0 | EH17: 0 | EI17: 0 | EJ17: 0 | EK17: 0 | EL17: 0 | EM17: 0 | EN17: 0 | EO17: 0 | EP17: 0 | EQ17: 0 | ER17: 450 | EU17: ~2016 | EV17: 국내출자 | EW17: 0 | EX17: 0 | EY17: 0 | EZ17: 0 | FA17: 0 | FB17: 0 | FC17: 0 | FD17: 0 | FE17: 0 | FF17: 0 | FG17: 0 | FH17: 0 | FI17: 0 | FJ17: 0 | FK17: 0 | FL17: 0 | FM17: 0 | FN17: 0 | FO17: 0 | FP17: 0 | FQ17: TRUE | FR17: TRUE
A18: BS00000034 | B18: 305370641300 | C18: 6000000000127 | D18: 남양강진씨앤지 | E18: 남양강진씨앤지 | F18: 인프라 | G18: BTL | H18: 하수관거 | I18: 국내 | J18: 아시아 | K18: 이머징 | L18: 한국 | M18: 해당없음 | N18: 대출 | O18: 선순위 | P18: 대출 | Q18: 프로젝트 | R18: KRW | S18: KRW | T18: 40231 | U18: 2958465 | V18: 2958465 | X18: PPP | Y18: Availability(정부) | Z18: 정부보증 | AA18: 정부가 임대료 지급 | AB18: IBK기업은행 | AC18: 해당없음 | AD18: 허강혁 | AF18: 유재섭 | AG18: 정상 | AH18: 38882 | AI18: 기보유 | AJ18: 국내실물 | AK18: 인프라 | AL18: Debt | AM18: 인출 | AN18: 운영 | AO18: 0 | AP18: 5890000000 | AQ18: 0 | AR18: 0 | AS18: 0 | AT18: 0 | AU18: 0 | AV18: 0 | AW18: 5890000000 | AX18: 97000000 | AY18: 97000000 | AZ18: 4518274400 | BA18: -97000000 | BB18: -97000000 | BC18: 1371725600 | BD18: 13909216 | BE18: 13909216 | BF18: 859423238 | BG18: 0 | BH18: 13909216 | BI18: 0 | BJ18: 0 | BK18: 0 | BL18: 13899011 | BM18: 0 | BN18: 0 | BO18: 4801973 | BP18: 13918413 | BQ18: 4801973 | BR18: 13918413 | BS18: 0 | BT18: 0 | BU18: 0 | BV18: 4801973 | BW18: 13918413 | BX18: 0.33868828 | BY18: 0.98484678 | BZ18: 0 | CA18: 1372000000 | CB18: 1469000000 | CC18: 1469000000 | CD18: 0 | CE18: 1371725600 | CF18: 1468706200 | CG18: 1468706200 | CH18: 1371725600 | CI18: 1468706200 | CJ18: 1468706200 | CK18: 19400 | CL18: 0 | CM18: 0.32404124 | CN18: 3.8884949 | CO18: 3.8884949 | CP18: 4.4449567e+08 | CQ18: 5.333948e+09 | CR18: 5.333948e+09 | CS18: 1.1459123 | CT18: 1.5718772e+09 | CU18: 3.84 | CV18: 0 | CW18: 0 | CX18: 3.84 | CY18: 3.84 | CZ18: 5267426304 | DA18: 0 | DB18: 0 | DC18: 372480000 | DD18: 372480000 | DE18: 1371725600 | DF18: 0 | DG18: 97000000 | DH18: 1 | DI18: 0 | DJ18: 1371725600 | DK18: 0 | DL18: 1468706200 | DM18: 0 | DN18: 0 | DO18: 0 | DP18: 97000000 | DQ18: 0 | DR18: 0 | DS18: 0 | DT18: 0 | DU18: 0 | DV18: 1.7092378e+09 | DW18: 0 | DX18: 0 | DY18: 0 | DZ18: 0 | EA18: 0 | EB18: 0 | EC18: 0 | ED18: 0 | EE18: 0 | EF18: 0 | EG18: 4801973 | EH18: 0 | EI18: 0 | EJ18: 0 | EK18: 0 | EL18: 13918413 | EM18: 0 | EN18: 0 | EO18: 0 | EP18: 4801973 | EQ18: 13918413 | ER18: 341 | EU18: ~2016 | EV18: 국내대출 | EW18: 0 | EX18: 4801973 | EY18: 0 | EZ18: 0 | FA18: 0 | FB18: 0 | FC18: 13918413 | FD18: 0 | FE18: 0 | FF18: 0 | FG18: 0 | FH18: 0 | FI18: 0 | FJ18: 0 | FK18: 0 | FL18: 0 | FM18: 0 | FN18: 0 | FO18: 0 | FP18: 0 | FQ18: TRUE | FR18: TRUE
A19: BS00000034 | B19: 305370641300 | C19: 6000000000128 | D19: 남양강진씨앤지 | E19: 남양강진씨앤지 | F19: 인프라 | G19: BTL | H19: 하수관거 | I19: 국내 | J19: 아시아 | K19: 이머징 | L19: 한국 | M19: 해당없음 | N19: 대출 | O19: 선순위 | P19: 대출 | Q19: 프로젝트 | R19: KRW | S19: KRW | T19: 40231 | U19: 2958465 | V19: 2958465 | X19: PPP | Y19: Availability(정부) | Z19: 정부보증 | AA19: 정부가 임대료 지급 | AB19: IBK기업은행 | AC19: 해당없음 | AD19: 허강혁 | AF19: 유재섭 | AG19: 정상 | AH19: 38882 | AI19: 기보유 | AJ19: 국내실물 | AK19: 인프라 | AL19: Debt | AM19: 인출 | AN19: 운영 | AO19: 0 | AP19: 1059000000 | AQ19: 0 | AR19: 0 | AS19: 0 | AT19: 0 | AU19: 0 | AV19: 0 | AW19: 1059000000 | AX19: 18000000 | AY19: 18000000 | AZ19: 809050000 | BA19: -18000000 | BB19: -18000000 | BC19: 249950000 | BD19: 5180843 | BE19: 5180843 | BF19: 324472072 | BG19: 0 | BH19: 5180843 | BI19: 0 | BJ19: 0 | BK19: 0 | BL19: 5176977 | BM19: 0 | BN19: 0 | BO19: 1784927 | BP19: 5180578 | BQ19: 1784927 | BR19: 5180578 | BS19: 0 | BT19: 0 | BU19: 0 | BV19: 1784927 | BW19: 5180578 | BX19: 0.69168274 | BY19: 2.020838 | BZ19: 0 | CA19: 250000000 | CB19: 268000000 | CC19: 268000000 | CD19: 0 | CE19: 249950000 | CF19: 267946400 | CG19: 267946400 | CH19: 249950000 | CI19: 267946400 | CJ19: 267946400 | CK19: 3600 | CL19: 0 | CM19: 0.67140508 | CN19: 8.0568609 | CO19: 8.0568609 | CP19: 1.678177e+08 | CQ19: 2.0138124e+09 | CR19: 2.0138124e+09 | CS19: 1.3063948 | CT19: 3.2653338e+08 | CU19: 7.84 | CV19: 0 | CW19: 0 | CX19: 7.84 | CY19: 7.84 | CZ19: 1959608000 | DA19: 0 | DB19: 0 | DC19: 141120000 | DD19: 141120000 | DE19: 249950000 | DF19: 0 | DG19: 18000000 | DH19: 1 | DI19: 0 | DJ19: 249950000 | DK19: 0 | DL19: 267946400 | DM19: 0 | DN19: 0 | DO19: 0 | DP19: 18000000 | DQ19: 0 | DR19: 0 | DS19: 0 | DT19: 0 | DU19: 0 | DV19: 3.3883797e+08 | DW19: 0 | DX19: 0 | DY19: 0 | DZ19: 0 | EA19: 0 | EB19: 0 | EC19: 0 | ED19: 0 | EE19: 0 | EF19: 0 | EG19: 1784927 | EH19: 0 | EI19: 0 | EJ19: 0 | EK19: 0 | EL19: 5180578 | EM19: 0 | EN19: 0 | EO19: 0 | EP19: 1784927 | EQ19: 5180578 | ER19: 363 | EU19: ~2016 | EV19: 국내대출 | EW19: 0 | EX19: 1784927 | EY19: 0 | EZ19: 0 | FA19: 0 | FB19: 0 | FC19: 5180578 | FD19: 0 | FE19: 0 | FF19: 0 | FG19: 0 | FH19: 0 | FI19: 0 | FJ19: 0 | FK19: 0 | FL19: 0 | FM19: 0 | FN19: 0 | FO19: 0 | FP19: 0 | FQ19: TRUE | FR19: TRUE
A20: BS00000034 | B20: 305370641300 | C20: 6000000000129 | D20: 남양강진씨앤지 | E20: 남양강진씨앤지 | F20: 인프라 | G20: BTL | H20: 하수관거 | I20: 국내 | J20: 아시아 | K20: 이머징 | L20: 한국 | M20: 해당없음 | N20: 대출 | O20: 선순위 | P20: 대출 | Q20: 프로젝트 | R20: KRW | S20: KRW | T20: 40231 | U20: 2958465 | V20: 2958465 | X20: PPP | Y20: Availability(정부) | Z20: 정부보증 | AA20: 정부가 임대료 지급 | AB20: IBK기업은행 | AC20: 해당없음 | AD20: 허강혁 | AF20: 유재섭 | AG20: 정상 | AH20: 38882 | AI20: 기보유 | AJ20: 국내실물 | AK20: 인프라 | AL20: Debt | AM20: 인출 | AN20: 운영 | AO20: 0 | AP20: 683860000 | AQ20: 0 | AR20: 0 | AS20: 0 | AT20: 0 | AU20: 0 | AV20: 0 | AW20: 683860000 | AX20: 2900000 | AY20: 2900000 | AZ20: 644267920 | BA20: -2900000 | BB20: -2900000 | BC20: 39592080 | BD20: 465287 | BE20: 465287 | BF20: 28745039 | BG20: 0 | BH20: 465287 | BI20: 0 | BJ20: 0 | BK20: 0 | BL20: 464934 | BM20: 0 | BN20: 0 | BO20: 160554 | BP20: 465514 | BQ20: 160554 | BR20: 465514 | BS20: 0 | BT20: 0 | BU20: 0 | BV20: 160554 | BW20: 465514 | BX20: 0.39196306 | BY20: 1.1407131 | BZ20: 0 | CA20: 39600000 | CB20: 42500000 | CC20: 42500000 | CD20: 0 | CE20: 39592080 | CF20: 42491500 | CG20: 42491500 | CH20: 39592080 | CI20: 42491500 | CJ20: 42491500 | CK20: 580 | CL20: 0 | CM20: 0.3755044 | CN20: 4.5060528 | CO20: 4.5060528 | CP20: 14867000 | CQ20: 1.78404e+08 | CR20: 1.78404e+08 | CS20: 1.0420335 | CT20: 41256274 | CU20: 4.44 | CV20: 0 | CW20: 0 | CX20: 4.44 | CY20: 4.44 | CZ20: 1.7578884e+08 | DA20: 0 | DB20: 0 | DC20: 12876000 | DD20: 12876000 | DE20: 39592080 | DF20: 0 | DG20: 2900000 | DH20: 1 | DI20: 0 | DJ20: 39592080 | DK20: 0 | DL20: 42491500 | DM20: 0 | DN20: 0 | DO20: 0 | DP20: 2900000 | DQ20: 0 | DR20: 0 | DS20: 0 | DT20: 0 | DU20: 0 | DV20: 50218255 | DW20: 0 | DX20: 0 | DY20: 0 | DZ20: 0 | EA20: 0 | EB20: 0 | EC20: 0 | ED20: 0 | EE20: 0 | EF20: 0 | EG20: 160554 | EH20: 0 | EI20: 0 | EJ20: 0 | EK20: 0 | EL20: 465514 | EM20: 0 | EN20: 0 | EO20: 0 | EP20: 160554 | EQ20: 465514 | ER20: 398 | EU20: ~2016 | EV20: 국내대출 | EW20: 0 | EX20: 160554 | EY20: 0 | EZ20: 0 | FA20: 0 | FB20: 0 | FC20: 465514 | FD20: 0 | FE20: 0 | FF20: 0 | FG20: 0 | FH20: 0 | FI20: 0 | FJ20: 0 | FK20: 0 | FL20: 0 | FM20: 0 | FN20: 0 | FO20: 0 | FP20: 0 | FQ20: TRUE | FR20: TRUE
A21: BS00000034 | B21: BS0000003401 | C21: 100001924 | D21: 남양강진씨앤지 | E21: 남양강진씨앤지 | F21: 인프라 | G21: BTL | H21: 하수관거 | I21: 국내 | J21: 아시아 | K21: 이머징 | L21: 한국 | M21: 해당없음 | N21: 출자 | O21: 지분 | P21: 주식형 | Q21: 프로젝트 | R21: KRW | S21: KRW | T21: 38861 | U21: 2958465 | V21: 2958465 | X21: PPP | Y21: Availability(정부) | Z21: 정부보증 | AA21: 정부가 임대료 지급 | AB21: IBK기업은행 | AC21: 해당없음 | AD21: 허강혁 | AF21: 유재섭 | AG21: 정상 | AH21: 38882 | AI21: 기보유 | AJ21: 국내실물 | AK21: 인프라 | AL21: Equity | AM21: 인출 | AN21: 운영 | AO21: 0 | AP21: 520058700 | AQ21: 0 | AR21: 0 | AS21: 0 | AT21: 0 | AU21: 0 | AV21: 0 | AW21: 0 | AX21: 0 | AY21: 0 | AZ21: 0 | BA21: 0 | BB21: 0 | BC21: 0 | BD21: 0 | BE21: 0 | BF21: 0 | BG21: 0 | BH21: 0 | BI21: 0 | BJ21: 0 | BK21: 0 | BL21: 0 | BM21: 0 | BN21: 0 | BO21: 0 | BP21: 0 | BQ21: 0 | BR21: 0 | BS21: 0 | BT21: 0 | BU21: 0 | BV21: 0 | BW21: 0 | BX21: 0 | BY21: 0 | BZ21: 0 | CA21: 520058700 | CB21: 520058700 | CC21: 520058700 | CD21: 0 | CE21: 520058700 | CF21: 520058700 | CG21: 520058700 | CH21: 520058700 | CI21: 520058700 | CJ21: 520058700 | CK21: 0 | CL21: 0 | CM21: 2.9802322e-07 | CN21: 2.9802322e-07 | CO21: 0 | CP21: 154.98957 | CQ21: 154.98957 | CR21: 0 | CS21: 0 | CT21: 0 | CU21: 0 | CV21: 0 | CW21: 0 | CX21: 0 | CY21: 0 | CZ21: 0 | DA21: 0 | DB21: 0 | DC21: 0 | DD21: 0 | DE21: 0 | DF21: 0 | DG21: 0 | DH21: 0 | DI21: 1 | DJ21: 0 | DK21: 520058700 | DL21: 0 | DM21: 520058700 | DN21: 0 | DO21: 0 | DP21: 0 | DQ21: 0 | DR21: 0 | DS21: 0 | DT21: 0 | DU21: 0 | DV21: 336025930 | DW21: 0 | DX21: 0 | DY21: 67205186 | DZ21: 0 | EA21: 0 | EB21: 67205186 | EC21: 0.2 | ED21: 67205186 | EE21: 104011740 | EF21: 0 | EG21: 0 | EH21: 0 | EI21: 0 | EJ21: 0 | EK21: 0 | EL21: 0 | EM21: 0 | EN21: 0 | EO21: 0 | EP21: 0 | EQ21: 0 | ER21: 450 | EU21: ~2016 | EV21: 국내출자 | EW21: 0 | EX21: 0 | EY21: 0 | EZ21: 0 | FA21: 0 | FB21: 0 | FC21: 0 | FD21: 0 | FE21: 0 | FF21: 0 | FG21: 0 | FH21: 0 | FI21: 0 | FJ21: 0 | FK21: 0 | FL21: 0 | FM21: 0 | FN21: 0 | FO21: 0 | FP21: 0 | FQ21: TRUE | FR21: TRUE
A22: BS00000035 | B22: 405373691400 | C22: 6000000000139 | D22: 울산1지구 교육사업 | E22: 울산1지구교육사업(주) [울산 혜인학교 외 9개교] | F22: 인프라 | G22: BTL | H22: 교육시설 | I22: 국내 | J22: 아시아 | K22: 이머징 | L22: 한국 | M22: 해당없음 | N22: 대출 | O22: 선순위 | P22: 대출 | Q22: 프로젝트 | R22: KRW | S22: KRW | T22: 39668 | U22: 46310 | V22: 46310 | X22: PPP | Y22: Availability(정부) | Z22: 정부보증 | AA22: 정부가 임대료 지급 | AB22: IBK기업은행 | AC22: 해당없음 | AD22: 이건희 | AF22: 유재섭 | AG22: 정상 | AH22: 38876 | AI22: 기보유 | AJ22: 국내실물 | AK22: 인프라 | AL22: Debt | AM22: 인출 | AN22: 운영 | AO22: 0 | AP22: 3909000000 | AQ22: 0 | AR22: 0 | AS22: 0 | AT22: 0 | AU22: 0 | AV22: 0 | AW22: 3909000000 | AX22: 0 | AY22: 79416400 | AZ22: 3905351630 | BA22: 0 | BB22: -79416400 | BC22: 3648370 | BD22: 0 | BE22: 971479 | BF22: 2824131 | BG22: 0 | BH22: 971479 | BI22: 0 | BJ22: 0 | BK22: 0 | BL22: 183089 | BM22: 0 | BN22: 0 | BO22: 14377 | BP22: 199130 | BQ22: 14377 | BR22: 199130 | BS22: 0 | BT22: 0 | BU22: 0 | BV22: 14377 | BW22: 199130 | BX22: 0.39484437 | BY22: 0.46042615 | BZ22: 0 | CA22: 3649100 | CB22: 3649100 | CC22: 83065500 | CD22: 0 | CE22: 3648370 | CF22: 3648370 | CG22: 83048887 | CH22: 3648370 | CI22: 3648370 | CJ22: 83048887 | CK22: 15883 | CL22: 0 | CM22: 0.36537777 | CN22: 4.3845332 | CO22: 4.3845332 | CP22: 1333033.3 | CQ22: 15996399 | CR22: 15996399 | CS22: 1.0007225 | CT22: 3651005.8 | CU22: 4.64 | CV22: 0 | CW22: 0 | CX22: 0 | CY22: 4.64 | CZ22: 16928437 | DA22: 0 | DB22: 0 | DC22: 0 | DD22: 368492096 | DE22: 3648370 | DF22: 0 | DG22: 0 | DH22: 1 | DI22: 0 | DJ22: 3648370 | DK22: 0 | DL22: 83048887 | DM22: 0 | DN22: 0 | DO22: 0 | DP22: 79416400 | DQ22: 0 | DR22: 0 | DS22: 0 | DT22: 0 | DU22: 0 | DV22: 2.4329928e+08 | DW22: 0 | DX22: 0 | DY22: 0 | DZ22: 0 | EA22: 0 | EB22: 0 | EC22: 0 | ED22: 0 | EE22: 0 | EF22: 0 | EG22: 14377 | EH22: 0 | EI22: 0 | EJ22: 0 | EK22: 0 | EL22: 199130 | EM22: 0 | EN22: 0 | EO22: 0 | EP22: 14377 | EQ22: 199130 | ER22: 409 | EU22: ~2016 | EV22: 국내대출 | EW22: 0 | EX22: 14377 | EY22: 0 | EZ22: 0 | FA22: 0 | FB22: 0 | FC22: 199130 | FD22: 0 | FE22: 0 | FF22: 0 | FG22: 0 | FH22: 0 | FI22: 0 | FJ22: 0 | FK22: 0 | FL22: 0 | FM22: 0 | FN22: 0 | FO22: 0 | FP22: 0 | FQ22: TRUE | FR22: TRUE
A23: BS00000035 | B23: 405373691400 | C23: 6000000000140 | D23: 울산1지구 교육사업 | E23: 울산1지구교육사업(주) [울산 혜인학교 외 9개교] | F23: 인프라 | G23: BTL | H23: 교육시설 | I23: 국내 | J23: 아시아 | K23: 이머징 | L23: 한국 | M23: 해당없음 | N23: 대출 | O23: 선순위 | P23: 대출 | Q23: 프로젝트 | R23: KRW | S23: KRW | T23: 39668 | U23: 46310 | V23: 46310 | X23: PPP | Y23: Availability(정부) | Z23: 정부보증 | AA23: 정부가 임대료 지급 | AB23: IBK기업은행 | AC23: 해당없음 | AD23: 이건희 | AF23: 유재섭 | AG23: 정상 | AH23: 38876 | AI23: 기보유 | AJ23: 국내실물 | AK23: 인프라 | AL23: Debt | AM23: 인출 | AN23: 운영 | AO23: 0 | AP23: 665000000 | AQ23: 0 | AR23: 0 | AS23: 0 | AT23: 0 | AU23: 0 | AV23: 0 | AW23: 665000000 | AX23: 0 | AY23: 13526100 | AZ23: 664855129 | BA23: 0 | BB23: -13526100 | BC23: 144871 | BD23: 0 | BE23: 268775 | BF23: 189426 | BG23: 0 | BH23: 268775 | BI23: 0 | BJ23: 0 | BK23: 0 | BL23: 43254 | BM23: 0 | BN23: 0 | BO23: 960 | BP23: 46005 | BQ23: 960 | BR23: 46005 | BS23: 0 | BT23: 0 | BU23: 0 | BV23: 960 | BW23: 46005 | BX23: 0.66486138 | BY23: 0.66833092 | BZ23: 0 | CA23: 144900 | CB23: 144900 | CC23: 13671000 | CD23: 0 | CE23: 144871 | CF23: 144871 | CG23: 13668266 | CH23: 144871 | CI23: 144871 | CJ23: 13668266 | CK23: 2705 | CL23: 0 | CM23: 0.61718218 | CN23: 7.4061862 | CO23: 7.4061862 | CP23: 89411.8 | CQ23: 1072941.6 | CR23: 1072941.6 | CS23: 1.0002849 | CT23: 144912.27 | CU23: 7.8 | CV23: 0 | CW23: 0 | CX23: 0 | CY23: 7.8 | CZ23: 1129993.8 | DA23: 0 | DB23: 0 | DC23: 0 | DD23: 105503580 | DE23: 144871 | DF23: 0 | DG23: 0 | DH23: 1 | DI23: 0 | DJ23: 144871 | DK23: 0 | DL23: 13668266 | DM23: 0 | DN23: 0 | DO23: 0 | DP23: 13526100 | DQ23: 0 | DR23: 0 | DS23: 0 | DT23: 0 | DU23: 0 | DV23: 41004410 | DW23: 0 | DX23: 0 | DY23: 0 | DZ23: 0 | EA23: 0 | EB23: 0 | EC23: 0 | ED23: 0 | EE23: 0 | EF23: 0 | EG23: 960 | EH23: 0 | EI23: 0 | EJ23: 0 | EK23: 0 | EL23: 46005 | EM23: 0 | EN23: 0 | EO23: 0 | EP23: 960 | EQ23: 46005 | ER23: 426 | EU23: ~2016 | EV23: 국내대출 | EW23: 0 | EX23: 960 | EY23: 0 | EZ23: 0 | FA23: 0 | FB23: 0 | FC23: 46005 | FD23: 0 | FE23: 0 | FF23: 0 | FG23: 0 | FH23: 0 | FI23: 0 | FJ23: 0 | FK23: 0 | FL23: 0 | FM23: 0 | FN23: 0 | FO23: 0 | FP23: 0 | FQ23: TRUE | FR23: TRUE
A24: BS00000035 | B24: 405373691400 | C24: 6000000000141 | D24: 울산1지구 교육사업 | E24: 울산1지구교육사업(주) [울산 혜인학교 외 9개교] | F24: 인프라 | G24: BTL | H24: 교육시설 | I24: 국내 | J24: 아시아 | K24: 이머징 | L24: 한국 | M24: 해당없음 | N24: 대출 | O24: 선순위 | P24: 대출 | Q24: 프로젝트 | R24: KRW | S24: KRW | T24: 39668 | U24: 46310 | V24: 46310 | X24: PPP | Y24: Availability(정부) | Z24: 정부보증 | AA24: 정부가 임대료 지급 | AB24: IBK기업은행 | AC24: 해당없음 | AD24: 이건희 | AF24: 유재섭 | AG24: 정상 | AH24: 38876 | AI24: 기보유 | AJ24: 국내실물 | AK24: 인프라 | AL24: Debt | AM24: 인출 | AN24: 운영 | AO24: 0 | AP24: 3287000000 | AQ24: 0 | AR24: 0 | AS24: 0 | AT24: 0 | AU24: 0 | AV24: 0 | AW24: 3287000000 | AX24: 0 | AY24: 66918600 | AZ24: 3283402120 | BA24: 0 | BB24: -66918600 | BC24: 3597880 | BD24: 0 | BE24: 618542 | BF24: 2084497 | BG24: 0 | BH24: 618542 | BI24: 0 | BJ24: 0 | BK24: 0 | BL24: 120201 | BM24: 0 | BN24: 0 | BO24: 10634 | BP24: 133684 | BQ24: 10634 | BR24: 133684 | BS24: 0 | BT24: 0 | BU24: 0 | BV24: 10634 | BW24: 133684 | BX24: 0.29600038 | BY24: 0.36146787 | BZ24: 0 | CA24: 3598600 | CB24: 3598600 | CC24: 70517200 | CD24: 0 | CE24: 3597880 | CF24: 3597880 | CG24: 70503097 | CH24: 3597880 | CI24: 3597880 | CJ24: 70503097 | CK24: 13383 | CL24: 0 | CM24: 0.27347058 | CN24: 3.281647 | CO24: 3.281647 | CP24: 983914.34 | CQ24: 11806972 | CR24: 11806972 | CS24: 1.0006342 | CT24: 3600161.6 | CU24: 3.48 | CV24: 0 | CW24: 0 | CX24: 0 | CY24: 3.48 | CZ24: 12520622 | DA24: 0 | DB24: 0 | DC24: 0 | DD24: 232876728 | DE24: 3597880 | DF24: 0 | DG24: 0 | DH24: 1 | DI24: 0 | DJ24: 3597880 | DK24: 0 | DL24: 70503097 | DM24: 0 | DN24: 0 | DO24: 0 | DP24: 66918600 | DQ24: 0 | DR24: 0 | DS24: 0 | DT24: 0 | DU24: 0 | DV24: 2.0477651e+08 | DW24: 0 | DX24: 0 | DY24: 0 | DZ24: 0 | EA24: 0 | EB24: 0 | EC24: 0 | ED24: 0 | EE24: 0 | EF24: 0 | EG24: 10634 | EH24: 0 | EI24: 0 | EJ24: 0 | EK24: 0 | EL24: 133684 | EM24: 0 | EN24: 0 | EO24: 0 | EP24: 10634 | EQ24: 133684 | ER24: 411 | EU24: ~2016 | EV24: 국내대출 | EW24: 0 | EX24: 10634 | EY24: 0 | EZ24: 0 | FA24: 0 | FB24: 0 | FC24: 133684 | FD24: 0 | FE24: 0 | FF24: 0 | FG24: 0 | FH24: 0 | FI24: 0 | FJ24: 0 | FK24: 0 | FL24: 0 | FM24: 0 | FN24: 0 | FO24: 0 | FP24: 0 | FQ24: TRUE | FR24: TRUE
A25: BS00000035 | B25: 405373691400 | C25: 6000000000142 | D25: 울산1지구 교육사업 | E25: 울산1지구교육사업(주) [울산 혜인학교 외 9개교] | F25: 인프라 | G25: BTL | H25: 교육시설 | I25: 국내 | J25: 아시아 | K25: 이머징 | L25: 한국 | M25: 해당없음 | N25: 대출 | O25: 선순위 | P25: 대출 | Q25: 프로젝트 | R25: KRW | S25: KRW | T25: 39668 | U25: 46310 | V25: 46310 | X25: PPP | Y25: Availability(정부) | Z25: 정부보증 | AA25: 정부가 임대료 지급 | AB25: IBK기업은행 | AC25: 해당없음 | AD25: 이건희 | AF25: 유재섭 | AG25: 정상 | AH25: 38876 | AI25: 기보유 | AJ25: 국내실물 | AK25: 인프라 | AL25: Debt | AM25: 인출 | AN25: 운영 | AO25: 0 | AP25: 559000000 | AQ25: 0 | AR25: 0 | AS25: 0 | AT25: 0 | AU25: 0 | AV25: 0 | AW25: 559000000 | AX25: 0 | AY25: 11390400 | AZ25: 558813637 | BA25: 0 | BB25: -11390400 | BC25: 186363 | BD25: 0 | BE25: 193754 | BF25: 206801 | BG25: 0 | BH25: 193754 | BI25: 0 | BJ25: 0 | BK25: 0 | BL25: 32060 | BM25: 0 | BN25: 0 | BO25: 1049 | BP25: 34370 | BQ25: 1049 | BR25: 34370 | BS25: 0 | BT25: 0 | BU25: 0 | BV25: 1049 | BW25: 34370 | BX25: 0.56446861 | BY25: 0.58619476 | BZ25: 0 | CA25: 186400 | CB25: 186400 | CC25: 11576800 | CD25: 0 | CE25: 186363 | CF25: 186363 | CG25: 11574485 | CH25: 186363 | CI25: 186363 | CJ25: 11574485 | CK25: 2278 | CL25: 0 | CM25: 0.52378088 | CN25: 6.2853706 | CO25: 6.2853706 | CP25: 97613.377 | CQ25: 1171360.5 | CR25: 1171360.5 | CS25: 1.0003699 | CT25: 186431.94 | CU25: 6.64 | CV25: 0 | CW25: 0 | CX25: 0 | CY25: 6.64 | CZ25: 1237450.3 | DA25: 0 | DB25: 0 | DC25: 0 | DD25: 75632256 | DE25: 186363 | DF25: 0 | DG25: 0 | DH25: 1 | DI25: 0 | DJ25: 186363 | DK25: 0 | DL25: 11574485 | DM25: 0 | DN25: 0 | DO25: 0 | DP25: 11390400 | DQ25: 0 | DR25: 0 | DS25: 0 | DT25: 0 | DU25: 0 | DV25: 34445172 | DW25: 0 | DX25: 0 | DY25: 0 | DZ25: 0 | EA25: 0 | EB25: 0 | EC25: 0 | ED25: 0 | EE25: 0 | EF25: 0 | EG25: 1049 | EH25: 0 | EI25: 0 | EJ25: 0 | EK25: 0 | EL25: 34370 | EM25: 0 | EN25: 0 | EO25: 0 | EP25: 1049 | EQ25: 34370 | ER25: 430 | EU25: ~2016 | EV25: 국내대출 | EW25: 0 | EX25: 1049 | EY25: 0 | EZ25: 0 | FA25: 0 | FB25: 0 | FC25: 34370 | FD25: 0 | FE25: 0 | FF25: 0 | FG25: 0 | FH25: 0 | FI25: 0 | FJ25: 0 | FK25: 0 | FL25: 0 | FM25: 0 | FN25: 0 | FO25: 0 | FP25: 0 | FQ25: TRUE | FR25: TRUE
A26: BS00000035 | B26: 405373691400 | C26: 6000000000143 | D26: 울산1지구 교육사업 | E26: 울산1지구교육사업(주) [울산 혜인학교 외 9개교] | F26: 인프라 | G26: BTL | H26: 교육시설 | I26: 국내 | J26: 아시아 | K26: 이머징 | L26: 한국 | M26: 해당없음 | N26: 대출 | O26: 선순위 | P26: 대출 | Q26: 프로젝트 | R26: KRW | S26: KRW | T26: 39668 | U26: 46310 | V26: 46310 | X26: PPP | Y26: Availability(정부) | Z26: 정부보증 | AA26: 정부가 임대료 지급 | AB26: IBK기업은행 | AC26: 해당없음 | AD26: 이건희 | AF26: 유재섭 | AG26: 정상 | AH26: 38876 | AI26: 기보유 | AJ26: 국내실물 | AK26: 인프라 | AL26: Debt | AM26: 인출 | AN26: 운영 | AO26: 0 | AP26: 366000000 | AQ26: 0 | AR26: 0 | AS26: 0 | AT26: 0 | AU26: 0 | AV26: 0 | AW26: 366000000 | AX26: 0 | AY26: 7435400 | AZ26: 364945361 | BA26: 0 | BB26: -7435400 | BC26: 1054639 | BD26: 0 | BE26: 64414 | BF26: 528226 | BG26: 0 | BH26: 64414 | BI26: 0 | BJ26: 0 | BK26: 0 | BL26: 16413 | BM26: 0 | BN26: 0 | BO26: 2696 | BP26: 17910 | BQ26: 2696 | BR26: 17910 | BS26: 0 | BT26: 0 | BU26: 0 | BV26: 2696 | BW26: 17910 | BX26: 0.25595965 | BY26: 0.3760519 | BZ26: 0 | CA26: 1054850 | CB26: 1054850 | CC26: 8490250 | CD26: 0 | CE26: 1054639 | CF26: 1054639 | CG26: 8488552 | CH26: 1054639 | CI26: 1054639 | CJ26: 8488552 | CK26: 1487 | CL26: 0 | CM26: 0.23641353 | CN26: 2.8369623 | CO26: 2.8369623 | CP26: 249330.92 | CQ26: 2991971.1 | CR26: 2991971.1 | CS26: 1.0014432 | CT26: 1056161.1 | CU26: 3.01 | CV26: 0 | CW26: 0 | CX26: 0 | CY26: 3.01 | CZ26: 3174463.4 | DA26: 0 | DB26: 0 | DC26: 0 | DD26: 22380554 | DE26: 1054639 | DF26: 0 | DG26: 0 | DH26: 1 | DI26: 0 | DJ26: 1054639 | DK26: 0 | DL26: 8488552 | DM26: 0 | DN26: 0 | DO26: 0 | DP26: 7435400 | DQ26: 0 | DR26: 0 | DS26: 0 | DT26: 0 | DU26: 0 | DV26: 23344498 | DW26: 0 | DX26: 0 | DY26: 0 | DZ26: 0 | EA26: 0 | EB26: 0 | EC26: 0 | ED26: 0 | EE26: 0 | EF26: 0 | EG26: 2696 | EH26: 0 | EI26: 0 | EJ26: 0 | EK26: 0 | EL26: 17910 | EM26: 0 | EN26: 0 | EO26: 0 | EP26: 2696 | EQ26: 17910 | ER26: 439 | EU26: ~2016 | EV26: 국내대출 | EW26: 0 | EX26: 2696 | EY26: 0 | EZ26: 0 | FA26: 0 | FB26: 0 | FC26: 17910 | FD26: 0 | FE26: 0 | FF26: 0 | FG26: 0 | FH26: 0 | FI26: 0 | FJ26: 0 | FK26: 0 | FL26: 0 | FM26: 0 | FN26: 0 | FO26: 0 | FP26: 0 | FQ26: TRUE | FR26: TRUE
A27: BS00000035 | B27: 405373691400 | C27: 6000000000144 | D27: 울산1지구 교육사업 | E27: 울산1지구교육사업(주) [울산 혜인학교 외 9개교] | F27: 인프라 | G27: BTL | H27: 교육시설 | I27: 국내 | J27: 아시아 | K27: 이머징 | L27: 한국 | M27: 해당없음 | N27: 대출 | O27: 선순위 | P27: 대출 | Q27: 프로젝트 | R27: KRW | S27: KRW | T27: 39668 | U27: 46310 | V27: 46310 | X27: PPP | Y27: Availability(정부) | Z27: 정부보증 | AA27: 정부가 임대료 지급 | AB27: IBK기업은행 | AC27: 해당없음 | AD27: 이건희 | AF27: 유재섭 | AG27: 정상 | AH27: 38876 | AI27: 기보유 | AJ27: 국내실물 | AK27: 인프라 | AL27: Debt | AM27: 인출 | AN27: 운영 | AO27: 0 | AP27: 62000000 | AQ27: 0 | AR27: 0 | AS27: 0 | AT27: 0 | AU27: 0 | AV27: 0 | AW27: 0 | AX27: 0 | AY27: 1058750 | AZ27: 0 | BA27: 0 | BB27: -1058750 | BC27: 0 | BD27: 0 | BE27: 16465 | BF27: 0 | BG27: 0 | BH27: 16465 | BI27: 0 | BJ27: 0 | BK27: 0 | BL27: 2506 | BM27: 0 | BN27: 0 | BO27: 0 | BP27: 2721 | BQ27: 0 | BR27: 2721 | BS27: 0 | BT27: 0 | BU27: 0 | BV27: 0 | BW27: 2721 | BX27: 0 | BY27: 0.51543023 | BZ27: 0 | CA27: 0 | CB27: 0 | CC27: 1058750 | CD27: 0 | CE27: 0 | CF27: 0 | CG27: 1058538 | CH27: 0 | CI27: 0 | CJ27: 1058538 | CK27: 212 | CL27: 0 | CM27: 0 | CN27: 0 | CO27: 0 | CP27: 0 | CQ27: 0 | CR27: 0 | CS27: 0 | CT27: 0 | CU27: 0 | CV27: 0 | CW27: 0 | CX27: 0 | CY27: 9.01 | CZ27: 0 | DA27: 0 | DB27: 0 | DC27: 0 | DD27: 9539337.5 | DE27: 0 | DF27: 0 | DG27: 0 | DH27: 1 | DI27: 0 | DJ27: 0 | DK27: 0 | DL27: 1058538 | DM27: 0 | DN27: 0 | DO27: 0 | DP27: 1058750 | DQ27: 0 | DR27: 0 | DS27: 0 | DT27: 0 | DU27: 0 | DV27: 3590213.9 | DW27: 0 | DX27: 0 | DY27: 0 | DZ27: 0 | EA27: 0 | EB27: 0 | EC27: 0 | ED27: 0 | EE27: 0 | EF27: 0 | EG27: 0 | EH27: 0 | EI27: 0 | EJ27: 0 | EK27: 0 | EL27: 2721 | EM27: 0 | EN27: 0 | EO27: 0 | EP27: 0 | EQ27: 2721 | ER27: 448 | EU27: ~2016 | EV27: 국내대출 | EW27: 0 | EX27: 0 | EY27: 0 | EZ27: 0 | FA27: 0 | FB27: 0 | FC27: 2721 | FD27: 0 | FE27: 0 | FF27: 0 | FG27: 0 | FH27: 0 | FI27: 0 | FJ27: 0 | FK27: 0 | FL27: 0 | FM27: 0 | FN27: 0 | FO27: 0 | FP27: 0 | FQ27: TRUE | FR27: TRUE
A28: BS00000035 | B28: 405373691400 | C28: 6000000000145 | D28: 울산1지구 교육사업 | E28: 울산1지구교육사업(주) [울산 혜인학교 외 9개교] | F28: 인프라 | G28: BTL | H28: 교육시설 | I28: 국내 | J28: 아시아 | K28: 이머징 | L28: 한국 | M28: 해당없음 | N28: 대출 | O28: 선순위 | P28: 대출 | Q28: 프로젝트 | R28: KRW | S28: KRW | T28: 39668 | U28: 46310 | V28: 46310 | X28: PPP | Y28: Availability(정부) | Z28: 정부보증 | AA28: 정부가 임대료 지급 | AB28: IBK기업은행 | AC28: 해당없음 | AD28: 이건희 | AF28: 유재섭 | AG28: 정상 | AH28: 38876 | AI28: 기보유 | AJ28: 국내실물 | AK28: 인프라 | AL28: Debt | AM28: 인출 | AN28: 운영 | AO28: 0 | AP28: 4668000000 | AQ28: 0 | AR28: 0 | AS28: 0 | AT28: 0 | AU28: 0 | AV28: 0 | AW28: 4668000000 | AX28: 0 | AY28: 94959550 | AZ28: 4662698161 | BA28: 0 | BB28: -94959550 | BC28: 5301839 | BD28: 0 | BE28: 1101843 | BF28: 3855201 | BG28: 0 | BH28: 1101843 | BI28: 0 | BJ28: 0 | BK28: 0 | BL28: 215813 | BM28: 0 | BN28: 0 | BO28: 19632 | BP28: 234981 | BQ28: 19632 | BR28: 234981 | BS28: 0 | BT28: 0 | BU28: 0 | BV28: 19632 | BW28: 234981 | BX28: 0.37097344 | BY28: 0.44626846 | BZ28: 0 | CA28: 5302900 | CB28: 5302900 | CC28: dsd | CD28: 0 | CE28: 5301839 | CF28: 5301839 | CG28: 100242398 | CH28: 5301839 | CI28: 5301839 | CJ28: 100242398 | CK28: 18991 | CL28: 0 | CM28: 0.34322312 | CN28: 4.1186774 | CO28: 4.1186774 | CP28: 1819713.7 | CQ28: 21836564 | CR28: 21836564 | CS28: 1.0008259 | CT28: 5306217.7 | CU28: 4.36 | CV28: 0 | CW28: 0 | CX28: 0 | CY28: 4.36 | CZ28: 23116018 | DA28: 0 | DB28: 0 | DC28: 0 | DD28: 4.1402364e+08 | DE28: 5301839 | DF28: 0 | DG28: 0 | DH28: 1 | DI28: 0 | DJ28: 5301839 | DK28: 0 | DL28: 100242398 | DM28: 0 | DN28: 0 | DO28: 0 | DP28: 94959550 | DQ28: 0 | DR28: 0 | DS28: 0 | DT28: 0 | DU28: 0 | DV28: 2.9154687e+08 | DW28: 0 | DX28: 0 | DY28: 0 | DZ28: 0 | EA28: 0 | EB28: 0 | EC28: 0 | ED28: 0 | EE28: 0 | EF28: 0 | EG28: 19632 | EH28: 0 | EI28: 0 | EJ28: 0 | EK28: 0 | EL28: 234981 | EM28: 0 | EN28: 0 | EO28: 0 | EP28: 19632 | EQ28: 234981 | ER28: 404 | EU28: ~2016 | EV28: 국내대출 | EW28: 0 | EX28: 19632 | EY28: 0 | EZ28: 0 | FA28: 0 | FB28: 0 | FC28: 234981 | FD28: 0 | FE28: 0 | FF28: 0 | FG28: 0 | FH28: 0 | FI28: 0 | FJ28: 0 | FK28: 0 | FL28: 0 | FM28: 0 | FN28: 0 | FO28: 0 | FP28: 0 | FQ28: TRUE | FR28: TRUE
A29: BS00000035 | B29: 405373691400 | C29: 6000000000146 | D29: 울산1지구 교육사업 | E29: 울산1지구교육사업(주) [울산 혜인학교 외 9개교] | F29: 인프라 | G29: BTL | H29: 교육시설 | I29: 국내 | J29: 아시아 | K29: 이머징 | L29: 한국 | M29: 해당없음 | N29: 대출 | O29: 선순위 | P29: 대출 | Q29: 프로젝트 | R29: KRW | S29: KRW | T29: 39668 | U29: 46310 | V29: 46310 | X29: PPP | Y29: Availability(정부) | Z29: 정부보증 | AA29: 정부가 임대료 지급 | AB29: IBK기업은행 | AC29: 해당없음 | AD29: 이건희 | AF29: 유재섭 | AG29: 정상 | AH29: 38876 | AI29: 기보유 | AJ29: 국내실물 | AK29: 인프라 | AL29: Debt | AM29: 인출 | AN29: 운영 | AO29: 0 | AP29: 794000000 | AQ29: 0 | AR29: 0 | AS29: 0 | AT29: 0 | AU29: 0 | AV29: 0 | AW29: 794000000 | AX29: 0 | AY29: 16175950 | AZ29: 793864927 | BA29: 0 | BB29: -16175950 | BC29: 135073 | BD29: 0 | BE29: 309168 | BF29: 170062 | BG29: 0 | BH29: 309168 | BI29: 0 | BJ29: 0 | BK29: 0 | BL29: 49162 | BM29: 0 | BN29: 0 | BO29: 862 | BP29: 52449 | BQ29: 862 | BR29: 52449 | BS29: 0 | BT29: 0 | BU29: 0 | BV29: 862 | BW29: 52449 | BX29: 0.64021628 | BY29: 0.63999611 | BZ29: 0 | CA29: 135100 | CB29: 135100 | CC29: 16311050 | CD29: 0 | CE29: 135073 | CF29: 135073 | CG29: 16307788 | CH29: 135073 | CI29: 135073 | CJ29: 16307788 | CK29: 3235 | CL29: 0 | CM29: 0.5942848 | CN29: 7.1314176 | CO29: 7.1314176 | CP29: 80271.831 | CQ29: 963261.97 | CR29: 963261.97 | CS29: 1.0002142 | CT29: 135101.93 | CU29: 7.52 | CV29: 0 | CW29: 0 | CX29: 0 | CY29: 7.52 | CZ29: 1015749 | DA29: 0 | DB29: 0 | DC29: 0 | DD29: 121643144 | DE29: 135073 | DF29: 0 | DG29: 0 | DH29: 1 | DI29: 0 | DJ29: 135073 | DK29: 0 | DL29: 16307788 | DM29: 0 | DN29: 0 | DO29: 0 | DP29: 16175950 | DQ29: 0 | DR29: 0 | DS29: 0 | DT29: 0 | DU29: 0 | DV29: 48944575 | DW29: 0 | DX29: 0 | DY29: 0 | DZ29: 0 | EA29: 0 | EB29: 0 | EC29: 0 | ED29: 0 | EE29: 0 | EF29: 0 | EG29: 862 | EH29: 0 | EI29: 0 | EJ29: 0 | EK29: 0 | EL29: 52449 | EM29: 0 | EN29: 0 | EO29: 0 | EP29: 862 | EQ29: 52449 | ER29: 424 | EU29: ~2016 | EV29: 국내대출 | EW29: 0 | EX29: 862 | EY29: 0 | EZ29: 0 | FA29: 0 | FB29: 0 | FC29: 52449 | FD29: 0 | FE29: 0 | FF29: 0 | FG29: 0 | FH29: 0 | FI29: 0 | FJ29: 0 | FK29: 0 | FL29: 0 | FM29: 0 | FN29: 0 | FO29: 0 | FP29: 0 | FQ29: TRUE | FR29: TRUE
A30: BS00000035 | B30: 405373691400 | C30: 6000000000147 | D30: 울산1지구 교육사업 | E30: 울산1지구교육사업(주) [울산 혜인학교 외 9개교] | F30: 인프라 | G30: BTL | H30: 교육시설 | I30: 국내 | J30: 아시아 | K30: 이머징 | L30: 한국 | M30: 해당없음 | N30: 대출 | O30: 선순위 | P30: 대출 | Q30: 프로젝트 | R30: KRW | S30: KRW | T30: 39668 | U30: 46310 | V30: 46310 | X30: PPP | Y30: Availability(정부) | Z30: 정부보증 | AA30: 정부가 임대료 지급 | AB30: IBK기업은행 | AC30: 해당없음 | AD30: 이건희 | AF30: 유재섭 | AG30: 정상 | AH30: 38876 | AI30: 기보유 | AJ30: 국내실물 | AK30: 인프라 | AL30: Debt | AM30: 인출 | AN30: 운영 | AO30: 0 | AP30: 1944000000 | AQ30: 0 | AR30: 0 | AS30: 0 | AT30: 0 | AU30: 0 | AV30: 0 | AW30: 1944000000 | AX30: 0 | AY30: 39550000 | AZ30: 1942185113 | BA30: 0 | BB30: -39550000 | BC30: 1814887 | BD30: 0 | BE30: 569276 | BF30: 1655617 | BG30: 0 | BH30: 569276 | BI30: 0 | BJ30: 0 | BK30: 0 | BL30: 107266 | BM30: 0 | BN30: 0 | BO30: 8416 | BP30: 115269 | BQ30: 8416 | BR30: 115269 | BS30: 0 | BT30: 0 | BU30: 0 | BV30: 8416 | BW30: 115269 | BX30: 0.46479801 | BY30: 0.53543017 | BZ30: 0 | CA30: 1815250 | CB30: 1815250 | CC30: 41365250 | CD30: 0 | CE30: 1814887 | CF30: 1814887 | CG30: 41356977 | CH30: 1814887 | CI30: 1814887 | CJ30: 41356977 | CK30: 7910 | CL30: 0 | CM30: 0.43059229 | CN30: 5.1671075 | CO30: 5.1671075 | CP30: 781476.35 | CQ30: 9377716.2 | CR30: 9377716.2 | CS30: 1.0008517 | CT30: 1816432.7 | CU30: 5.46 | CV30: 0 | CW30: 0 | CX30: 0 | CY30: 5.46 | CZ30: 9909283 | DA30: 0 | DB30: 0 | DC30: 0 | DD30: 215943000 | DE30: 1814887 | DF30: 0 | DG30: 0 | DH30: 1 | DI30: 0 | DJ30: 1814887 | DK30: 0 | DL30: 41356977 | DM30: 0 | DN30: 0 | DO30: 0 | DP30: 39550000 | DQ30: 0 | DR30: 0 | DS30: 0 | DT30: 0 | DU30: 0 | DV30: 1.2137431e+08 | DW30: 0 | DX30: 0 | DY30: 0 | DZ30: 0 | EA30: 0 | EB30: 0 | EC30: 0 | ED30: 0 | EE30: 0 | EF30: 0 | EG30: 8416 | EH30: 0 | EI30: 0 | EJ30: 0 | EK30: 0 | EL30: 115269 | EM30: 0 | EN30: 0 | EO30: 0 | EP30: 8416 | EQ30: 115269 | ER30: 414 | EU30: ~2016 | EV30: 국내대출 | EW30: 0 | EX30: 8416 | EY30: 0 | EZ30: 0 | FA30: 0 | FB30: 0 | FC30: 115269 | FD30: 0 | FE30: 0 | FF30: 0 | FG30: 0 | FH30: 0 | FI30: 0 | FJ30: 0 | FK30: 0 | FL30: 0 | FM30: 0 | FN30: 0 | FO30: 0 | FP30: 0 | FQ30: TRUE | FR30: TRUE
A31: BS00000035 | B31: 405373691400 | C31: 6000000000148 | D31: 울산1지구 교육사업 | E31: 울산1지구교육사업(주) [울산 혜인학교 외 9개교] | F31: 인프라 | G31: BTL | H31: 교육시설 | I31: 국내 | J31: 아시아 | K31: 이머징 | L31: 한국 | M31: 해당없음 | N31: 대출 | O31: 선순위 | P31: 대출 | Q31: 프로젝트 | R31: KRW | S31: KRW | T31: 39668 | U31: 46310 | V31: 46310 | X31: PPP | Y31: Availability(정부) | Z31: 정부보증 | AA31: 정부가 임대료 지급 | AB31: IBK기업은행 | AC31: 해당없음 | AD31: 이건희 | AF31: 유재섭 | AG31: 정상 | AH31: 38876 | AI31: 기보유 | AJ31: 국내실물 | AK31: 인프라 | AL31: Debt | AM31: 인출 | AN31: 운영 | AO31: 0 | AP31: 330000000 | AQ31: 0 | AR31: 0 | AS31: 0 | AT31: 0 | AU31: 0 | AV31: 0 | AW31: 0 | AX31: 0 | AY31: 5964026 | AZ31: 0 | BA31: 0 | BB31: -5964026 | BC31: 0 | BD31: 0 | BE31: 129581 | BF31: 0 | BG31: 0 | BH31: 129581 | BI31: 0 | BJ31: 0 | BK31: 0 | BL31: 19719 | BM31: 0 | BN31: 0 | BO31: 0 | BP31: 20934 | BQ31: 0 | BR31: 20934 | BS31: 0 | BT31: 0 | BU31: 0 | BV31: 0 | BW31: 20934 | BX31: 0 | BY31: 0.70462322 | BZ31: 0 | CA31: 0 | CB31: 0 | CC31: 5964026 | CD31: 0 | CE31: 0 | CF31: 0 | CG31: 5962833 | CH31: 0 | CI31: 0 | CJ31: 5962833 | CK31: 1193 | CL31: 0 | CM31: 0 | CN31: 0 | CO31: 0 | CP31: 0 | CQ31: 0 | CR31: 0 | CS31: 0 | CT31: 0 | CU31: 0 | CV31: 0 | CW31: 0 | CX31: 0 | CY31: 9.57 | CZ31: 0 | DA31: 0 | DB31: 0 | DC31: 0 | DD31: 57075729 | DE31: 0 | DF31: 0 | DG31: 0 | DH31: 1 | DI31: 0 | DJ31: 0 | DK31: 0 | DL31: 5962833 | DM31: 0 | DN31: 0 | DO31: 0 | DP31: 5964026 | DQ31: 0 | DR31: 0 | DS31: 0 | DT31: 0 | DU31: 0 | DV31: 19594689 | DW31: 0 | DX31: 0 | DY31: 0 | DZ31: 0 | EA31: 0 | EB31: 0 | EC31: 0 | ED31: 0 | EE31: 0 | EF31: 0 | EG31: 0 | EH31: 0 | EI31: 0 | EJ31: 0 | EK31: 0 | EL31: 20934 | EM31: 0 | EN31: 0 | EO31: 0 | EP31: 0 | EQ31: 20934 | ER31: 436 | EU31: ~2016 | EV31: 국내대출 | EW31: 0 | EX31: 0 | EY31: 0 | EZ31: 0 | FA31: 0 | FB31: 0 | FC31: 20934 | FD31: 0 | FE31: 0 | FF31: 0 | FG31: 0 | FH31: 0 | FI31: 0 | FJ31: 0 | FK31: 0 | FL31: 0 | FM31: 0 | FN31: 0 | FO31: 0 | FP31: 0 | FQ31: TRUE | FR31: TRUE
A32: BS00000036 | B32: 205373352200 | C32: 6000000000112 | D32: 울산2지구 교육사업 | E32: 울산2지구교육사업(주) [울산 구영초 외 8개교] | F32: 인프라 | G32: BTL | H32: 교육시설 | I32: 국내 | J32: 아시아 | K32: 이머징 | L32: 한국 | M32: 해당없음 | N32: 대출 | O32: 선순위 | P32: 대출 | Q32: 프로젝트 | R32: KRW | S32: KRW | T32: 39668 | U32: 46037 | V32: 46037 | X32: PPP | Y32: Availability(정부) | Z32: 정부보증 | AA32: 정부가 임대료 지급 | AB32: IBK기업은행 | AC32: 해당없음 | AD32: 이건희 | AF32: 유재섭 | AG32: 정상 | AH32: 38876 | AI32: 기보유 | AJ32: 국내실물 | AK32: 인프라 | AL32: Debt | AM32: 인출 | AN32: 운영 | AO32: 0 | AP32: 362000000 | AQ32: 0 | AR32: 0 | AS32: 0 | AT32: 0 | AU32: 0 | AV32: 0 | AW32: 0 | AX32: 0 | AY32: 5271750 | AZ32: 0 | BA32: 0 | BB32: -5271750 | BC32: 0 | BD32: 0 | BE32: 39995 | BF32: 0 | BG32: 0 | BH32: 39995 | BI32: 0 | BJ32: 0 | BK32: 0 | BL32: 6086 | BM32: 0 | BN32: 0 | BO32: 0 | BP32: 7147 | BQ32: 0 | BR32: 7147 | BS32: 0 | BT32: 0 | BU32: 0 | BV32: 0 | BW32: 7147 | BX32: 0 | BY32: 0.27156582 | BZ32: 0 | CA32: 0 | CB32: 0 | CC32: 5271750 | CD32: 0 | CE32: 0 | CF32: 0 | CG32: 5270696 | CH32: 0 | CI32: 0 | CJ32: 5270696 | CK32: 1054 | CL32: 0 | CM32: 0 | CN32: 0 | CO32: 0 | CP32: 0 | CQ32: 0 | CR32: 0 | CS32: 0 | CT32: 0 | CU32: 0 | CV32: 0 | CW32: 0 | CX32: 0 | CY32: 5.85 | CZ32: 0 | DA32: 0 | DB32: 0 | DC32: 0 | DD32: 30839737 | DE32: 0 | DF32: 0 | DG32: 0 | DH32: 1 | DI32: 0 | DJ32: 0 | DK32: 0 | DL32: 5270696 | DM32: 0 | DN32: 0 | DO32: 0 | DP32: 5271750 | DQ32: 0 | DR32: 0 | DS32: 0 | DT32: 0 | DU32: 0 | DV32: 20125934 | DW32: 0 | DX32: 0 | DY32: 0 | DZ32: 0 | EA32: 0 | EB32: 0 | EC32: 0 | ED32: 0 | EE32: 0 | EF32: 0 | EG32: 0 | EH32: 0 | EI32: 0 | EJ32: 0 | EK32: 0 | EL32: 7147 | EM32: 0 | EN32: 0 | EO32: 0 | EP32: 0 | EQ32: 7147 | ER32: 446 | EU32: ~2016 | EV32: 국내대출 | EW32: 0 | EX32: 0 | EY32: 0 | EZ32: 0 | FA32: 0 | FB32: 0 | FC32: 7147 | FD32: 0 | FE32: 0 | FF32: 0 | FG32: 0 | FH32: 0 | FI32: 0 | FJ32: 0 | FK32: 0 | FL32: 0 | FM32: 0 | FN32: 0 | FO32: 0 | FP32: 0 | FQ32: TRUE | FR32: TRUE
A33: BS00000036 | B33: 205373352200 | C33: 6000000000113 | D33: 울산2지구 교육사업 | E33: 울산2지구교육사업(주) [울산 구영초 외 8개교] | F33: 인프라 | G33: BTL | H33: 교육시설 | I33: 국내 | J33: 아시아 | K33: 이머징 | L33: 한국 | M33: 해당없음 | N33: 대출 | O33: 선순위 | P33: 대출 | Q33: 프로젝트 | R33: KRW | S33: KRW | T33: 39668 | U33: 46037 | V33: 46037 | X33: PPP | Y33: Availability(정부) | Z33: 정부보증 | AA33: 정부가 임대료 지급 | AB33: IBK기업은행 | AC33: 해당없음 | AD33: 이건희 | AF33: 유재섭 | AG33: 정상 | AH33: 38876 | AI33: 기보유 | AJ33: 국내실물 | AK33: 인프라 | AL33: Debt | AM33: 인출 | AN33: 운영 | AO33: 0 | AP33: 61000000 | AQ33: 0 | AR33: 0 | AS33: 0 | AT33: 0 | AU33: 0 | AV33: 0 | AW33: 0 | AX33: 0 | AY33: 994643 | AZ33: 0 | BA33: 0 | BB33: -994643 | BC33: 0 | BD33: 0 | BE33: 16772 | BF33: 0 | BG33: 0 | BH33: 16772 | BI33: 0 | BJ33: 0 | BK33: 0 | BL33: 2552 | BM33: 0 | BN33: 0 | BO33: 0 | BP33: 2754 | BQ33: 0 | BR33: 2754 | BS33: 0 | BT33: 0 | BU33: 0 | BV33: 0 | BW33: 2754 | BX33: 0 | BY33: 0.5554155 | BZ33: 0 | CA33: 0 | CB33: 0 | CC33: 994643 | CD33: 0 | CE33: 0 | CF33: 0 | CG33: 994444 | CH33: 0 | CI33: 0 | CJ33: 994444 | CK33: 199 | CL33: 0 | CM33: 0 | CN33: 0 | CO33: 0 | CP33: 0 | CQ33: 0 | CR33: 0 | CS33: 0 | CT33: 0 | CU33: 0 | CV33: 0 | CW33: 0 | CX33: 0 | CY33: 9.53 | CZ33: 0 | DA33: 0 | DB33: 0 | DC33: 0 | DD33: 9478947.8 | DE33: 0 | DF33: 0 | DG33: 0 | DH33: 1 | DI33: 0 | DJ33: 0 | DK33: 0 | DL33: 994444 | DM33: 0 | DN33: 0 | DO33: 0 | DP33: 994643 | DQ33: 0 | DR33: 0 | DS33: 0 | DT33: 0 | DU33: 0 | DV33: 3537975.3 | DW33: 0 | DX33: 0 | DY33: 0 | DZ33: 0 | EA33: 0 | EB33: 0 | EC33: 0 | ED33: 0 | EE33: 0 | EF33: 0 | EG33: 0 | EH33: 0 | EI33: 0 | EJ33: 0 | EK33: 0 | EL33: 2754 | EM33: 0 | EN33: 0 | EO33: 0 | EP33: 0 | EQ33: 2754 | ER33: 447 | EU33: ~2016 | EV33: 국내대출 | EW33: 0 | EX33: 0 | EY33: 0 | EZ33: 0 | FA33: 0 | FB33: 0 | FC33: 2754 | FD33: 0 | FE33: 0 | FF33: 0 | FG33: 0 | FH33: 0 | FI33: 0 | FJ33: 0 | FK33: 0 | FL33: 0 | FM33: 0 | FN33: 0 | FO33: 0 | FP33: 0 | FQ33: TRUE | FR33: TRUE
A34: BS00000036 | B34: 205373352200 | C34: 6000000000114 | D34: 울산2지구 교육사업 | E34: 울산2지구교육사업(주) [울산 구영초 외 8개교] | F34: 인프라 | G34: BTL | H34: 교육시설 | I34: 국내 | J34: 아시아 | K34: 이머징 | L34: 한국 | M34: 해당없음 | N34: 대출 | O34: 선순위 | P34: 대출 | Q34: 프로젝트 | R34: KRW | S34: KRW | T34: 39668 | U34: 46037 | V34: 46037 | X34: PPP | Y34: Availability(정부) | Z34: 정부보증 | AA34: 정부가 임대료 지급 | AB34: IBK기업은행 | AC34: 해당없음 | AD34: 이건희 | AF34: 유재섭 | AG34: 정상 | AH34: 38876 | AI34: 기보유 | AJ34: 국내실물 | AK34: 인프라 | AL34: Debt | AM34: 인출 | AN34: 운영 | AO34: 0 | AP34: 1465000000 | AQ34: 0 | AR34: 0 | AS34: 0 | AT34: 0 | AU34: 0 | AV34: 0 | AW34: 0 | AX34: 0 | AY34: 22106515 | AZ34: 0 | BA34: 0 | BB34: -22106515 | BC34: 0 | BD34: 0 | BE34: 196136 | BF34: 0 | BG34: 0 | BH34: 196136 | BI34: 0 | BJ34: 0 | BK34: 0 | BL34: 29847 | BM34: 0 | BN34: 0 | BO34: 0 | BP34: 34301 | BQ34: 0 | BR34: 34301 | BS34: 0 | BT34: 0 | BU34: 0 | BV34: 0 | BW34: 34301 | BX34: 0 | BY34: 0.31086933 | BZ34: 0 | CA34: 0 | CB34: 0 | CC34: 22106515 | CD34: 0 | CE34: 0 | CF34: 0 | CG34: 22102094 | CH34: 0 | CI34: 0 | CJ34: 22102094 | CK34: 4421 | CL34: 0 | CM34: 0 | CN34: 0 | CO34: 0 | CP34: 0 | CQ34: 0 | CR34: 0 | CS34: 0 | CT34: 0 | CU34: 0 | CV34: 0 | CW34: 0 | CX34: 0 | CY34: 5.91 | CZ34: 0 | DA34: 0 | DB34: 0 | DC34: 0 | DD34: 1.306495e+08 | DE34: 0 | DF34: 0 | DG34: 0 | DH34: 1 | DI34: 0 | DJ34: 0 | DK34: 0 | DL34: 22102094 | DM34: 0 | DN34: 0 | DO34: 0 | DP34: 22106515 | DQ34: 0 | DR34: 0 | DS34: 0 | DT34: 0 | DU34: 0 | DV34: 82042749 | DW34: 0 | DX34: 0 | DY34: 0 | DZ34: 0 | EA34: 0 | EB34: 0 | EC34: 0 | ED34: 0 | EE34: 0 | EF34: 0 | EG34: 0 | EH34: 0 | EI34: 0 | EJ34: 0 | EK34: 0 | EL34: 34301 | EM34: 0 | EN34: 0 | EO34: 0 | EP34: 0 | EQ34: 34301 | ER34: 431 | EU34: ~2016 | EV34: 국내대출 | EW34: 0 | EX34: 0 | EY34: 0 | EZ34: 0 | FA34: 0 | FB34: 0 | FC34: 34301 | FD34: 0 | FE34: 0 | FF34: 0 | FG34: 0 | FH34: 0 | FI34: 0 | FJ34: 0 | FK34: 0 | FL34: 0 | FM34: 0 | FN34: 0 | FO34: 0 | FP34: 0 | FQ34: TRUE | FR34: TRUE
A35: BS00000036 | B35: 205373352200 | C35: 6000000000115 | D35: 울산2지구 교육사업 | E35: 울산2지구교육사업(주) [울산 구영초 외 8개교] | F35: 인프라 | G35: BTL | H35: 교육시설 | I35: 국내 | J35: 아시아 | K35: 이머징 | L35: 한국 | M35: 해당없음 | N35: 대출 | O35: 선순위 | P35: 대출 | Q35: 프로젝트 | R35: KRW | S35: KRW | T35: 39668 | U35: 46037 | V35: 46037 | X35: PPP | Y35: Availability(정부) | Z35: 정부보증 | AA35: 정부가 임대료 지급 | AB35: IBK기업은행 | AC35: 해당없음 | AD35: 이건희 | AF35: 유재섭 | AG35: 정상 | AH35: 38876 | AI35: 기보유 | AJ35: 국내실물 | AK35: 인프라 | AL35: Debt | AM35: 인출 | AN35: 운영 | AO35: 0 | AP35: 246000000 | AQ35: 0 | AR35: 0 | AS35: 0 | AT35: 0 | AU35: 0 | AV35: 0 | AW35: 0 | AX35: 0 | AY35: 3708728 | AZ35: 0 | BA35: 0 | BB35: -3708728 | BC35: 0 | BD35: 0 | BE35: 67305 | BF35: 0 | BG35: 0 | BH35: 67305 | BI35: 0 | BJ35: 0 | BK35: 0 | BL35: 10242 | BM35: 0 | BN35: 0 | BO35: 0 | BP35: 10995 | BQ35: 0 | BR35: 10995 | BS35: 0 | BT35: 0 | BU35: 0 | BV35: 0 | BW35: 10995 | BX35: 0 | BY35: 0.59480805 | BZ35: 0 | CA35: 0 | CB35: 0 | CC35: 3708728 | CD35: 0 | CE35: 0 | CF35: 0 | CG35: 3707986 | CH35: 0 | CI35: 0 | CJ35: 3707986 | CK35: 742 | CL35: 0 | CM35: 0 | CN35: 0 | CO35: 0 | CP35: 0 | CQ35: 0 | CR35: 0 | CS35: 0 | CT35: 0 | CU35: 0 | CV35: 0 | CW35: 0 | CX35: 0 | CY35: 9.59 | CZ35: 0 | DA35: 0 | DB35: 0 | DC35: 0 | DD35: 35566702 | DE35: 0 | DF35: 0 | DG35: 0 | DH35: 1 | DI35: 0 | DJ35: 0 | DK35: 0 | DL35: 3707986 | DM35: 0 | DN35: 0 | DO35: 0 | DP35: 3708728 | DQ35: 0 | DR35: 0 | DS35: 0 | DT35: 0 | DU35: 0 | DV35: 13853645 | DW35: 0 | DX35: 0 | DY35: 0 | DZ35: 0 | EA35: 0 | EB35: 0 | EC35: 0 | ED35: 0 | EE35: 0 | EF35: 0 | EG35: 0 | EH35: 0 | EI35: 0 | EJ35: 0 | EK35: 0 | EL35: 10995 | EM35: 0 | EN35: 0 | EO35: 0 | EP35: 0 | EQ35: 10995 | ER35: 443 | EU35: ~2016 | EV35: 국내대출 | EW35: 0 | EX35: 0 | EY35: 0 | EZ35: 0 | FA35: 0 | FB35: 0 | FC35: 10995 | FD35: 0 | FE35: 0 | FF35: 0 | FG35: 0 | FH35: 0 | FI35: 0 | FJ35: 0 | FK35: 0 | FL35: 0 | FM35: 0 | FN35: 0 | FO35: 0 | FP35: 0 | FQ35: TRUE | FR35: TRUE
A36: BS00000036 | B36: 205373352200 | C36: 6000000000116 | D36: 울산2지구 교육사업 | E36: 울산2지구교육사업(주) [울산 구영초 외 8개교] | F36: 인프라 | G36: BTL | H36: 교육시설 | I36: 국내 | J36: 아시아 | K36: 이머징 | L36: 한국 | M36: 해당없음 | N36: 대출 | O36: 선순위 | P36: 대출 | Q36: 프로젝트 | R36: KRW | S36: KRW | T36: 39668 | U36: 46037 | V36: 46037 | X36: PPP | Y36: Availability(정부) | Z36: 정부보증 | AA36: 정부가 임대료 지급 | AB36: IBK기업은행 | AC36: 해당없음 | AD36: 이건희 | AF36: 유재섭 | AG36: 정상 | AH36: 38876 | AI36: 기보유 | AJ36: 국내실물 | AK36: 인프라 | AL36: Debt | AM36: 인출 | AN36: 운영 | AO36: 0 | AP36: 5832000000 | AQ36: 0 | AR36: 0 | AS36: 0 | AT36: 0 | AU36: 0 | AV36: 0 | AW36: 0 | AX36: 0 | AY36: 86026971 | AZ36: 0 | BA36: 0 | BB36: -86026971 | BC36: 0 | BD36: 0 | BE36: 763259 | BF36: 0 | BG36: 0 | BH36: 763259 | BI36: 0 | BJ36: 0 | BK36: 0 | BL36: 116148 | BM36: 0 | BN36: 0 | BO36: 0 | BP36: 133482 | BQ36: 0 | BR36: 133482 | BS36: 0 | BT36: 0 | BU36: 0 | BV36: 0 | BW36: 133482 | BX36: 0 | BY36: 0.31087046 | BZ36: 0 | CA36: 0 | CB36: 0 | CC36: 86026971 | CD36: 0 | CE36: 0 | CF36: 0 | CG36: 86009766 | CH36: 0 | CI36: 0 | CJ36: 86009766 | CK36: 17205 | CL36: 0 | CM36: 0 | CN36: 0 | CO36: 0 | CP36: 0 | CQ36: 0 | CR36: 0 | CS36: 0 | CT36: 0 | CU36: 0 | CV36: 0 | CW36: 0 | CX36: 0 | CY36: 5.89 | CZ36: 0 | DA36: 0 | DB36: 0 | DC36: 0 | DD36: 5.0669886e+08 | DE36: 0 | DF36: 0 | DG36: 0 | DH36: 1 | DI36: 0 | DJ36: 0 | DK36: 0 | DL36: 86009766 | DM36: 0 | DN36: 0 | DO36: 0 | DP36: 86026971 | DQ36: 0 | DR36: 0 | DS36: 0 | DT36: 0 | DU36: 0 | DV36: 3.2414404e+08 | DW36: 0 | DX36: 0 | DY36: 0 | DZ36: 0 | EA36: 0 | EB36: 0 | EC36: 0 | ED36: 0 | EE36: 0 | EF36: 0 | EG36: 0 | EH36: 0 | EI36: 0 | EJ36: 0 | EK36: 0 | EL36: 133482 | EM36: 0 | EN36: 0 | EO36: 0 | EP36: 0 | EQ36: 133482 | ER36: 412 | EU36: ~2016 | EV36: 국내대출 | EW36: 0 | EX36: 0 | EY36: 0 | EZ36: 0 | FA36: 0 | FB36: 0 | FC36: 133482 | FD36: 0 | FE36: 0 | FF36: 0 | FG36: 0 | FH36: 0 | FI36: 0 | FJ36: 0 | FK36: 0 | FL36: 0 | FM36: 0 | FN36: 0 | FO36: 0 | FP36: 0 | FQ36: TRUE | FR36: TRUE
A37: BS00000036 | B37: 205373352200 | C37: 6000000000117 | D37: 울산2지구 교육사업 | E37: 울산2지구교육사업(주) [울산 구영초 외 8개교] | F37: 인프라 | G37: BTL | H37: 교육시설 | I37: 국내 | J37: 아시아 | K37: 이머징 | L37: 한국 | M37: 해당없음 | N37: 대출 | O37: 선순위 | P37: 대출 | Q37: 프로젝트 | R37: KRW | S37: KRW | T37: 39668 | U37: 46037 | V37: 46037 | X37: PPP | Y37: Availability(정부) | Z37: 정부보증 | AA37: 정부가 임대료 지급 | AB37: IBK기업은행 | AC37: 해당없음 | AD37: 이건희 | AF37: 유재섭 | AG37: 정상 | AH37: 38876 | AI37: 기보유 | AJ37: 국내실물 | AK37: 인프라 | AL37: Debt | AM37: 인출 | AN37: 운영 | AO37: 0 | AP37: 979000000 | AQ37: 0 | AR37: 0 | AS37: 0 | AT37: 0 | AU37: 0 | AV37: 0 | AW37: 0 | AX37: 0 | AY37: 15055609 | AZ37: 0 | BA37: 0 | BB37: -15055609 | BC37: 0 | BD37: 0 | BE37: 273228 | BF37: 0 | BG37: 0 | BH37: 273228 | BI37: 0 | BJ37: 0 | BK37: 0 | BL37: 41578 | BM37: 0 | BN37: 0 | BO37: 0 | BP37: 44635 | BQ37: 0 | BR37: 44635 | BS37: 0 | BT37: 0 | BU37: 0 | BV37: 0 | BW37: 44635 | BX37: 0 | BY37: 0.59481756 | BZ37: 0 | CA37: 0 | CB37: 0 | CC37: 15055609 | CD37: 0 | CE37: 0 | CF37: 0 | CG37: 15052598 | CH37: 0 | CI37: 0 | CJ37: 15052598 | CK37: 3011 | CL37: 0 | CM37: 0 | CN37: 0 | CO37: 0 | CP37: 0 | CQ37: 0 | CR37: 0 | CS37: 0 | CT37: 0 | CU37: 0 | CV37: 0 | CW37: 0 | CX37: 0 | CY37: 9.57 | CZ37: 0 | DA37: 0 | DB37: 0 | DC37: 0 | DD37: 1.4408218e+08 | DE37: 0 | DF37: 0 | DG37: 0 | DH37: 1 | DI37: 0 | DJ37: 0 | DK37: 0 | DL37: 15052598 | DM37: 0 | DN37: 0 | DO37: 0 | DP37: 15055609 | DQ37: 0 | DR37: 0 | DS37: 0 | DT37: 0 | DU37: 0 | DV37: 55282223 | DW37: 0 | DX37: 0 | DY37: 0 | DZ37: 0 | EA37: 0 | EB37: 0 | EC37: 0 | ED37: 0 | EE37: 0 | EF37: 0 | EG37: 0 | EH37: 0 | EI37: 0 | EJ37: 0 | EK37: 0 | EL37: 44635 | EM37: 0 | EN37: 0 | EO37: 0 | EP37: 0 | EQ37: 44635 | ER37: 427 | EU37: ~2016 | EV37: 국내대출 | EW37: 0 | EX37: 0 | EY37: 0 | EZ37: 0 | FA37: 0 | FB37: 0 | FC37: 44635 | FD37: 0 | FE37: 0 | FF37: 0 | FG37: 0 | FH37: 0 | FI37: 0 | FJ37: 0 | FK37: 0 | FL37: 0 | FM37: 0 | FN37: 0 | FO37: 0 | FP37: 0 | FQ37: TRUE | FR37: TRUE
A38: BS00000036 | B38: 205373352200 | C38: 6000000000118 | D38: 울산2지구 교육사업 | E38: 울산2지구교육사업(주) [울산 구영초 외 8개교] | F38: 인프라 | G38: BTL | H38: 교육시설 | I38: 국내 | J38: 아시아 | K38: 이머징 | L38: 한국 | M38: 해당없음 | N38: 대출 | O38: 선순위 | P38: 대출 | Q38: 프로젝트 | R38: KRW | S38: KRW | T38: 39668 | U38: 46037 | V38: 46037 | X38: PPP | Y38: Availability(정부) | Z38: 정부보증 | AA38: 정부가 임대료 지급 | AB38: IBK기업은행 | AC38: 해당없음 | AD38: 이건희 | AF38: 유재섭 | AG38: 정상 | AH38: 38876 | AI38: 기보유 | AJ38: 국내실물 | AK38: 인프라 | AL38: Debt | AM38: 인출 | AN38: 운영 | AO38: 0 | AP38: 938000000 | AQ38: 0 | AR38: 0 | AS38: 0 | AT38: 0 | AU38: 0 | AV38: 0 | AW38: 0 | AX38: 0 | AY38: 12982619 | AZ38: 0 | BA38: 0 | BB38: -12982619 | BC38: 0 | BD38: 0 | BE38: 114531 | BF38: 0 | BG38: 0 | BH38: 114531 | BI38: 0 | BJ38: 0 | BK38: 0 | BL38: 17429 | BM38: 0 | BN38: 0 | BO38: 0 | BP38: 20045 | BQ38: 0 | BR38: 20045 | BS38: 0 | BT38: 0 | BU38: 0 | BV38: 0 | BW38: 20045 | BX38: 0 | BY38: 0.30933697 | BZ38: 0 | CA38: 0 | CB38: 0 | CC38: 12982619 | CD38: 0 | CE38: 0 | CF38: 0 | CG38: 12980022 | CH38: 0 | CI38: 0 | CJ38: 12980022 | CK38: 2597 | CL38: 0 | CM38: 0 | CN38: 0 | CO38: 0 | CP38: 0 | CQ38: 0 | CR38: 0 | CS38: 0 | CT38: 0 | CU38: 0 | CV38: 0 | CW38: 0 | CX38: 0 | CY38: 5.89 | CZ38: 0 | DA38: 0 | DB38: 0 | DC38: 0 | DD38: 76467626 | DE38: 0 | DF38: 0 | DG38: 0 | DH38: 1 | DI38: 0 | DJ38: 0 | DK38: 0 | DL38: 12980022 | DM38: 0 | DN38: 0 | DO38: 0 | DP38: 12982619 | DQ38: 0 | DR38: 0 | DS38: 0 | DT38: 0 | DU38: 0 | DV38: 51233750 | DW38: 0 | DX38: 0 | DY38: 0 | DZ38: 0 | EA38: 0 | EB38: 0 | EC38: 0 | ED38: 0 | EE38: 0 | EF38: 0 | EG38: 0 | EH38: 0 | EI38: 0 | EJ38: 0 | EK38: 0 | EL38: 20045 | EM38: 0 | EN38: 0 | EO38: 0 | EP38: 0 | EQ38: 20045 | ER38: 437 | EU38: ~2016 | EV38: 국내대출 | EW38: 0 | EX38: 0 | EY38: 0 | EZ38: 0 | FA38: 0 | FB38: 0 | FC38: 20045 | FD38: 0 | FE38: 0 | FF38: 0 | FG38: 0 | FH38: 0 | FI38: 0 | FJ38: 0 | FK38: 0 | FL38: 0 | FM38: 0 | FN38: 0 | FO38: 0 | FP38: 0 | FQ38: TRUE | FR38: TRUE
A39: BS00000036 | B39: 205373352200 | C39: 6000000000119 | D39: 울산2지구 교육사업 | E39: 울산2지구교육사업(주) [울산 구영초 외 8개교] | F39: 인프라 | G39: BTL | H39: 교육시설 | I39: 국내 | J39: 아시아 | K39: 이머징 | L39: 한국 | M39: 해당없음 | N39: 대출 | O39: 선순위 | P39: 대출 | Q39: 프로젝트 | R39: KRW | S39: KRW | T39: 39668 | U39: 46037 | V39: 46037 | X39: PPP | Y39: Availability(정부) | Z39: 정부보증 | AA39: 정부가 임대료 지급 | AB39: IBK기업은행 | AC39: 해당없음 | AD39: 이건희 | AF39: 유재섭 | AG39: 정상 | AH39: 38876 | AI39: 기보유 | AJ39: 국내실물 | AK39: 인프라 | AL39: Debt | AM39: 인출 | AN39: 운영 | AO39: 0 | AP39: 158000000 | AQ39: 0 | AR39: 0 | AS39: 0 | AT39: 0 | AU39: 0 | AV39: 0 | AW39: 0 | AX39: 0 | AY39: 2830302 | AZ39: 0 | BA39: 0 | BB39: -2830302 | BC39: 0 | BD39: 0 | BE39: 51221 | BF39: 0 | BG39: 0 | BH39: 51221 | BI39: 0 | BJ39: 0 | BK39: 0 | BL39: 7794 | BM39: 0 | BN39: 0 | BO39: 0 | BP39: 8369 | BQ39: 0 | BR39: 8369 | BS39: 0 | BT39: 0 | BU39: 0 | BV39: 0 | BW39: 8369 | BX39: 0 | BY39: 0.59325852 | BZ39: 0 | CA39: 0 | CB39: 0 | CC39: 2830302 | CD39: 0 | CE39: 0 | CF39: 0 | CG39: 2829736 | CH39: 0 | CI39: 0 | CJ39: 2829736 | CK39: 566 | CL39: 0 | CM39: 0 | CN39: 0 | CO39: 0 | CP39: 0 | CQ39: 0 | CR39: 0 | CS39: 0 | CT39: 0 | CU39: 0 | CV39: 0 | CW39: 0 | CX39: 0 | CY39: 9.57 | CZ39: 0 | DA39: 0 | DB39: 0 | DC39: 0 | DD39: 27085990 | DE39: 0 | DF39: 0 | DG39: 0 | DH39: 1 | DI39: 0 | DJ39: 0 | DK39: 0 | DL39: 2829736 | DM39: 0 | DN39: 0 | DO39: 0 | DP39: 2830302 | DQ39: 0 | DR39: 0 | DS39: 0 | DT39: 0 | DU39: 0 | DV39: 9321069 | DW39: 0 | DX39: 0 | DY39: 0 | DZ39: 0 | EA39: 0 | EB39: 0 | EC39: 0 | ED39: 0 | EE39: 0 | EF39: 0 | EG39: 0 | EH39: 0 | EI39: 0 | EJ39: 0 | EK39: 0 | EL39: 8369 | EM39: 0 | EN39: 0 | EO39: 0 | EP39: 0 | EQ39: 8369 | ER39: 444 | EU39: ~2016 | EV39: 국내대출 | EW39: 0 | EX39: 0 | EY39: 0 | EZ39: 0 | FA39: 0 | FB39: 0 | FC39: 8369 | FD39: 0 | FE39: 0 | FF39: 0 | FG39: 0 | FH39: 0 | FI39: 0 | FJ39: 0 | FK39: 0 | FL39: 0 | FM39: 0 | FN39: 0 | FO39: 0 | FP39: 0 | FQ39: TRUE | FR39: TRUE
A40: BS00000036 | B40: 205373352200 | C40: 6000000000120 | D40: 울산2지구 교육사업 | E40: 울산2지구교육사업(주) [울산 구영초 외 8개교] | F40: 인프라 | G40: BTL | H40: 교육시설 | I40: 국내 | J40: 아시아 | K40: 이머징 | L40: 한국 | M40: 해당없음 | N40: 대출 | O40: 선순위 | P40: 대출 | Q40: 프로젝트 | R40: KRW | S40: KRW | T40: 39668 | U40: 46037 | V40: 46037 | X40: PPP | Y40: Availability(정부) | Z40: 정부보증 | AA40: 정부가 임대료 지급 | AB40: IBK기업은행 | AC40: 해당없음 | AD40: 이건희 | AF40: 유재섭 | AG40: 정상 | AH40: 38876 | AI40: 기보유 | AJ40: 국내실물 | AK40: 인프라 | AL40: Debt | AM40: 인출 | AN40: 운영 | AO40: 0 | AP40: 4193000000 | AQ40: 0 | AR40: 0 | AS40: 0 | AT40: 0 | AU40: 0 | AV40: 0 | AW40: 0 | AX40: 0 | AY40: 61175657 | AZ40: 0 | BA40: 0 | BB40: -61175657 | BC40: 0 | BD40: 0 | BE40: 536602 | BF40: 0 | BG40: 0 | BH40: 536602 | BI40: 0 | BJ40: 0 | BK40: 0 | BL40: 81657 | BM40: 0 | BN40: 0 | BO40: 0 | BP40: 93983 | BQ40: 0 | BR40: 93983 | BS40: 0 | BT40: 0 | BU40: 0 | BV40: 0 | BW40: 93983 | BX40: 0 | BY40: 0.30779061 | BZ40: 0 | CA40: 0 | CB40: 0 | CC40: 61175657 | CD40: 0 | CE40: 0 | CF40: 0 | CG40: 61163422 | CH40: 0 | CI40: 0 | CJ40: 61163422 | CK40: 12235 | CL40: 0 | CM40: 0 | CN40: 0 | CO40: 0 | CP40: 0 | CQ40: 0 | CR40: 0 | CS40: 0 | CT40: 0 | CU40: 0 | CV40: 0 | CW40: 0 | CX40: 0 | CY40: 5.88 | CZ40: 0 | DA40: 0 | DB40: 0 | DC40: 0 | DD40: 3.5971286e+08 | DE40: 0 | DF40: 0 | DG40: 0 | DH40: 1 | DI40: 0 | DJ40: 0 | DK40: 0 | DL40: 61163422 | DM40: 0 | DN40: 0 | DO40: 0 | DP40: 61175657 | DQ40: 0 | DR40: 0 | DS40: 0 | DT40: 0 | DU40: 0 | DV40: 2.3257227e+08 | DW40: 0 | DX40: 0 | DY40: 0 | DZ40: 0 | EA40: 0 | EB40: 0 | EC40: 0 | ED40: 0 | EE40: 0 | EF40: 0 | EG40: 0 | EH40: 0 | EI40: 0 | EJ40: 0 | EK40: 0 | EL40: 93983 | EM40: 0 | EN40: 0 | EO40: 0 | EP40: 0 | EQ40: 93983 | ER40: 419 | EU40: ~2016 | EV40: 국내대출 | EW40: 0 | EX40: 0 | EY40: 0 | EZ40: 0 | FA40: 0 | FB40: 0 | FC40: 93983 | FD40: 0 | FE40: 0 | FF40: 0 | FG40: 0 | FH40: 0 | FI40: 0 | FJ40: 0 | FK40: 0 | FL40: 0 | FM40: 0 | FN40: 0 | FO40: 0 | FP40: 0 | FQ40: TRUE | FR40: TRUE
... A69: BS00000040 | B69: 205376176200 | C69: 6000000000353 | D69: 푸른아산지키미 | E69: 푸른아산지키미(주) [충남 아산시 하수관거] | F69: 인프라 | G69: BTL | H69: 하수관거 | I69: 국내 | J69: 아시아 | K69: 이머징 | L69: 한국 | M69: 해당없음 | N69: 대출 | O69: 선순위 | P69: 대출 | Q69: 프로젝트 | R69: KRW | S69: KRW | T69: 40345 | U69: 2958465 | V69: 2958465 | X69: PPP | Y69: Availability(정부) | Z69: 정부보증 | AA69: 정부가 임대료 지급 | AB69: IBK기업은행 | AC69: 해당없음 | AD69: 이건희 | AF69: 유재섭 | AG69: 정상 | AH69: 38877 | AI69: 기보유 | AJ69: 국내실물 | AK69: 인프라 | AL69: Debt | AM69: 인출 | AN69: 운영 | AO69: 0 | AP69: 2856000000 | AQ69: 0 | AR69: 0 | AS69: 0 | AT69: 0 | AU69: 0 | AV69: 0 | AW69: 2856000000 | AX69: 55971000 | AY69: 55971000 | AZ69: 2218780469 | BA69: -55971000 | BB69: -55971000 | BC69: 637219531 | BD69: 12582297 | BE69: 12582297 | BF69: 759670711 | BG69: 0 | BH69: 12582297 | BI69: 0 | BJ69: 0 | BK69: 0 | BL69: 12571011 | BM69: 0 | BN69: 0 | BO69: 4335463 | BP69: 12582208 | BQ69: 4335463 | BR69: 12582208 | BS69: 0 | BT69: 0 | BU69: 0 | BV69: 4335463 | BW69: 12582208 | BX69: 0.65388472 | BY69: 1.9095536 | BZ69: 0 | CA69: 637347000 | CB69: 693318000 | CC69: 693318000 | CD69: 0 | CE69: 637219531 | CF69: 693179336 | CG69: 693179336 | CH69: 637219531 | CI69: 693179336 | CJ69: 693179336 | CK69: 11195 | CL69: 0 | CM69: 0.62877892 | CN69: 7.545347 | CO69: 7.545347 | CP69: 4.0067021e+08 | CQ69: 4.8080425e+09 | CR69: 4.8080425e+09 | CS69: 1.2659911 | CT69: 8.0671428e+08 | CU69: 7.36 | CV69: 0 | CW69: 0 | CX69: 7.36 | CY69: 7.36 | CZ69: 4.6899357e+09 | DA69: 0 | DB69: 0 | DC69: 411946560 | DD69: 411946560 | DE69: 637219531 | DF69: 0 | DG69: 55971000 | DH69: 1 | DI69: 0 | DJ69: 637219531 | DK69: 0 | DL69: 693179336 | DM69: 0 | DN69: 0 | DO69: 0 | DP69: 55971000 | DQ69: 0 | DR69: 0 | DS69: 0 | DT69: 0 | DU69: 0 | DV69: 8.4520199e+08 | DW69: 0 | DX69: 0 | DY69: 0 | DZ69: 0 | EA69: 0 | EB69: 0 | EC69: 0 | ED69: 0 | EE69: 0 | EF69: 0 | EG69: 4335463 | EH69: 0 | EI69: 0 | EJ69: 0 | EK69: 0 | EL69: 12582208 | EM69: 0 | EN69: 0 | EO69: 0 | EP69: 4335463 | EQ69: 12582208 | ER69: 345 | EU69: ~2016 | EV69: 국내대출 | EW69: 0 | EX69: 4335463 | EY69: 0 | EZ69: 0 | FA69: 0 | FB69: 0 | FC69: 12582208 | FD69: 0 | FE69: 0 | FF69: 0 | FG69: 0 | FH69: 0 | FI69: 0 | FJ69: 0 | FK69: 0 | FL69: 0 | FM69: 0 | FN69: 0 | FO69: 0 | FP69: 0 | FQ69: TRUE | FR69: TRUE
A70: BS00000040 | B70: BS0000004001 | C70: 100001914 | D70: 푸른아산지키미 | E70: 푸른아산지키미 | F70: 인프라 | G70: BTL | H70: 하수관거 | I70: 국내 | J70: 아시아 | K70: 이머징 | L70: 한국 | M70: 해당없음 | N70: 출자 | O70: 지분 | P70: 주식형 | Q70: 프로젝트 | R70: KRW | S70: KRW | T70: 38869 | U70: 2958465 | V70: 2958465 | X70: PPP | Y70: Availability(정부) | Z70: 정부보증 | AA70: 정부가 임대료 지급 | AB70: IBK기업은행 | AC70: 해당없음 | AD70: 이건희 | AF70: 유재섭 | AG70: 정상 | AH70: 38877 | AI70: 기보유 | AJ70: 국내실물 | AK70: 인프라 | AL70: Equity | AM70: 인출 | AN70: 운영 | AO70: 0 | AP70: 1533000000 | AQ70: 0 | AR70: 0 | AS70: 0 | AT70: 0 | AU70: 0 | AV70: 0 | AW70: 0 | AX70: 0 | AY70: 0 | AZ70: 0 | BA70: 0 | BB70: 0 | BC70: 0 | BD70: 0 | BE70: 0 | BF70: 0 | BG70: 0 | BH70: 0 | BI70: 0 | BJ70: 0 | BK70: 0 | BL70: 0 | BM70: 0 | BN70: 0 | BO70: 0 | BP70: 0 | BQ70: 0 | BR70: 0 | BS70: 0 | BT70: 0 | BU70: 0 | BV70: 0 | BW70: 0 | BX70: 0 | BY70: 0 | BZ70: 0 | CA70: 1407112033 | CB70: 1407112033 | CC70: 1407112033 | CD70: 0 | CE70: 1407112033 | CF70: 1407112033 | CG70: 1407112033 | CH70: 1407112033 | CI70: 1407112033 | CJ70: 1407112033 | CK70: 0 | CL70: 0 | CM70: 2.9802322e-07 | CN70: 2.9802322e-07 | CO70: 0 | CP70: 419.35206 | CQ70: 419.35206 | CR70: 0 | CS70: 0 | CT70: 0 | CU70: 0 | CV70: 0 | CW70: 0 | CX70: 0 | CY70: 0 | CZ70: 0 | DA70: 0 | DB70: 0 | DC70: 0 | DD70: 0 | DE70: 0 | DF70: 0 | DG70: 0 | DH70: 0 | DI70: 1 | DJ70: 0 | DK70: 1407112033 | DL70: 0 | DM70: 1407112033 | DN70: 0 | DO70: 0 | DP70: 0 | DQ70: 0 | DR70: 0 | DS70: 0 | DT70: 0 | DU70: 0 | DV70: 1063826871 | DW70: 0 | DX70: 0 | DY70: 2.1276537e+08 | DZ70: 0 | EA70: 0 | EB70: 2.1276537e+08 | EC70: 0.2 | ED70: 2.1276537e+08 | EE70: 2.8142241e+08 | EF70: 0 | EG70: 0 | EH70: 0 | EI70: 0 | EJ70: 0 | EK70: 0 | EL70: 0 | EM70: 0 | EN70: 0 | EO70: 0 | EP70: 0 | EQ70: 0 | ER70: 450 | EU70: ~2016 | EV70: 국내출자 | EW70: 0 | EX70: 0 | EY70: 0 | EZ70: 0 | FA70: 0 | FB70: 0 | FC70: 0 | FD70: 0 | FE70: 0 | FF70: 0 | FG70: 0 | FH70: 0 | FI70: 0 | FJ70: 0 | FK70: 0 | FL70: 0 | FM70: 0 | FN70: 0 | FO70: 0 | FP70: 0 | FQ70: TRUE | FR70: TRUE
A71: BS00000041 | B71: 505376177500 | C71: 6000000000151 | D71: 푸른여수지키미 | E71: 푸른여수지키미(주) [전남 여수시 하수관거] | F71: 인프라 | G71: BTL | H71: 하수관거 | I71: 국내 | J71: 아시아 | K71: 이머징 | L71: 한국 | M71: 해당없음 | N71: 대출 | O71: 선순위 | P71: 대출 | Q71: 프로젝트 | R71: KRW | S71: KRW | T71: 40267 | U71: 2958465 | V71: 2958465 | X71: PPP | Y71: Availability(정부) | Z71: 정부보증 | AA71: 정부가 임대료 지급 | AB71: IBK기업은행 | AC71: 해당없음 | AD71: 이건희 | AF71: 유재섭 | AG71: 정상 | AH71: 38877 | AI71: 기보유 | AJ71: 국내실물 | AK71: 인프라 | AL71: Debt | AM71: 인출 | AN71: 운영 | AO71: 0 | AP71: 828240000 | AQ71: 0 | AR71: 0 | AS71: 0 | AT71: 0 | AU71: 0 | AV71: 0 | AW71: 394400000 | AX71: 3956000 | AY71: 3956000 | AZ71: 342500382 | BA71: -3956000 | BB71: -3956000 | BC71: 51899618 | BD71: 566159 | BE71: 566159 | BF71: 34628522 | BG71: 0 | BH71: 566159 | BI71: 0 | BJ71: 0 | BK71: 0 | BL71: 565713 | BM71: 0 | BN71: 0 | BO71: 195430 | BP71: 566504 | BQ71: 195430 | BR71: 566504 | BS71: 0 | BT71: 0 | BU71: 0 | BV71: 195430 | BW71: 566504 | BX71: 0.3633912 | BY71: 1.0570294 | BZ71: 0 | CA71: 51910000 | CB71: 55866000 | CC71: 55866000 | CD71: 0 | CE71: 51899618 | CF71: 55854827 | CG71: 55854827 | CH71: 51899618 | CI71: 55854827 | CJ71: 55854827 | CK71: 791 | CL71: 0 | CM71: 0.34721373 | CN71: 4.1665648 | CO71: 4.1665648 | CP71: 18020260 | CQ71: 2.1624312e+08 | CR71: 2.1624312e+08 | CS71: 1.0878005 | CT71: 56456431 | CU71: 4.11 | CV71: 0 | CW71: 0 | CX71: 4.11 | CY71: 4.11 | CZ71: 2.1330743e+08 | DA71: 0 | DB71: 0 | DC71: 16259160 | DD71: 16259160 | DE71: 51899618 | DF71: 0 | DG71: 3956000 | DH71: 1 | DI71: 0 | DJ71: 51899618 | DK71: 0 | DL71: 55854827 | DM71: 0 | DN71: 0 | DO71: 0 | DP71: 3956000 | DQ71: 0 | DR71: 0 | DS71: 0 | DT71: 0 | DU71: 0 | DV71: 64273877 | DW71: 0 | DX71: 0 | DY71: 0 | DZ71: 0 | EA71: 0 | EB71: 0 | EC71: 0 | ED71: 0 | EE71: 0 | EF71: 0 | EG71: 195430 | EH71: 0 | EI71: 0 | EJ71: 0 | EK71: 0 | EL71: 566504 | EM71: 0 | EN71: 0 | EO71: 0 | EP71: 195430 | EQ71: 566504 | ER71: 394 | EU71: ~2016 | EV71: 국내대출 | EW71: 0 | EX71: 195430 | EY71: 0 | EZ71: 0 | FA71: 0 | FB71: 0 | FC71: 566504 | FD71: 0 | FE71: 0 | FF71: 0 | FG71: 0 | FH71: 0 | FI71: 0 | FJ71: 0 | FK71: 0 | FL71: 0 | FM71: 0 | FN71: 0 | FO71: 0 | FP71: 0 | FQ71: TRUE | FR71: TRUE
A72: BS00000041 | B72: 505376177500 | C72: 6000000000227 | D72: 푸른여수지키미 | E72: 푸른여수지키미(주) [전남 여수시 하수관거] | F72: 인프라 | G72: BTL | H72: 하수관거 | I72: 국내 | J72: 아시아 | K72: 이머징 | L72: 한국 | M72: 해당없음 | N72: 대출 | O72: 선순위 | P72: 대출 | Q72: 프로젝트 | R72: KRW | S72: KRW | T72: 40267 | U72: 2958465 | V72: 2958465 | X72: PPP | Y72: Availability(정부) | Z72: 정부보증 | AA72: 정부가 임대료 지급 | AB72: IBK기업은행 | AC72: 해당없음 | AD72: 이건희 | AF72: 유재섭 | AG72: 정상 | AH72: 38877 | AI72: 기보유 | AJ72: 국내실물 | AK72: 인프라 | AL72: Debt | AM72: 인출 | AN72: 운영 | AO72: 0 | AP72: 8341560000 | AQ72: 0 | AR72: 0 | AS72: 0 | AT72: 0 | AU72: 0 | AV72: 0 | AW72: 7020320000 | AX72: 139471000 | AY72: 139471000 | AZ72: 5195460045 | BA72: -139471000 | BB72: -139471000 | BC72: 1824859955 | BD72: 17924486 | BE72: 17924486 | BF72: 1094461492 | BG72: 0 | BH72: 17924486 | BI72: 0 | BJ72: 0 | BK72: 0 | BL72: 17910348 | BM72: 0 | BN72: 0 | BO72: 6190099 | BP72: 17938245 | BQ72: 6190099 | BR72: 17938245 | BS72: 0 | BT72: 0 | BU72: 0 | BV72: 6190099 | BW72: 17938245 | BX72: 0.32726108 | BY72: 0.95132198 | BZ72: 0 | CA72: 1825225000 | CB72: 1964696000 | CC72: 1964696000 | CD72: 0 | CE72: 1824859955 | CF72: 1964303061 | CG72: 1964303061 | CH72: 1824859955 | CI72: 1964303061 | CJ72: 1964303061 | CK72: 27894 | CL72: 0 | CM72: 0.31210308 | CN72: 3.7452369 | CO72: 3.7452369 | CP72: 5.695444e+08 | CQ72: 6.8345328e+09 | CR72: 6.8345328e+09 | CS72: 1.1558991 | CT72: 2.109354e+09 | CU72: 3.7 | CV72: 0 | CW72: 0 | CX72: 3.7 | CY72: 3.7 | CZ72: 6.7519818e+09 | DA72: 0 | DB72: 0 | DC72: 516042700 | DD72: 516042700 | DE72: 1824859955 | DF72: 0 | DG72: 139471000 | DH72: 1 | DI72: 0 | DJ72: 1824859955 | DK72: 0 | DL72: 1964303061 | DM72: 0 | DN72: 0 | DO72: 0 | DP72: 139471000 | DQ72: 0 | DR72: 0 | DS72: 0 | DT72: 0 | DU72: 0 | DV72: 2.2469821e+09 | DW72: 0 | DX72: 0 | DY72: 0 | DZ72: 0 | EA72: 0 | EB72: 0 | EC72: 0 | ED72: 0 | EE72: 0 | EF72: 0 | EG72: 6190099 | EH72: 0 | EI72: 0 | EJ72: 0 | EK72: 0 | EL72: 17938245 | EM72: 0 | EN72: 0 | EO72: 0 | EP72: 6190099 | EQ72: 17938245 | ER72: 338 | EU72: ~2016 | EV72: 국내대출 | EW72: 0 | EX72: 6190099 | EY72: 0 | EZ72: 0 | FA72: 0 | FB72: 0 | FC72: 17938245 | FD72: 0 | FE72: 0 | FF72: 0 | FG72: 0 | FH72: 0 | FI72: 0 | FJ72: 0 | FK72: 0 | FL72: 0 | FM72: 0 | FN72: 0 | FO72: 0 | FP72: 0 | FQ72: TRUE | FR72: TRUE
A73: BS00000041 | B73: 505376177500 | C73: 6000000000352 | D73: 푸른여수지키미 | E73: 푸른여수지키미(주) [전남 여수시 하수관거] | F73: 인프라 | G73: BTL | H73: 하수관거 | I73: 국내 | J73: 아시아 | K73: 이머징 | L73: 한국 | M73: 해당없음 | N73: 대출 | O73: 선순위 | P73: 대출 | Q73: 프로젝트 | R73: KRW | S73: KRW | T73: 40267 | U73: 2958465 | V73: 2958465 | X73: PPP | Y73: Availability(정부) | Z73: 정부보증 | AA73: 정부가 임대료 지급 | AB73: IBK기업은행 | AC73: 해당없음 | AD73: 이건희 | AF73: 유재섭 | AG73: 정상 | AH73: 38877 | AI73: 기보유 | AJ73: 국내실물 | AK73: 인프라 | AL73: Debt | AM73: 인출 | AN73: 운영 | AO73: 0 | AP73: 1321240000 | AQ73: 0 | AR73: 0 | AS73: 0 | AT73: 0 | AU73: 0 | AV73: 0 | AW73: 1321240000 | AX73: 26288000 | AY73: 26288000 | AZ73: 977249812 | BA73: -26288000 | BB73: -26288000 | BC73: 343990188 | BD73: 5743929 | BE73: 5743929 | BF73: 354091328 | BG73: 0 | BH73: 5743929 | BI73: 0 | BJ73: 0 | BK73: 0 | BL73: 5739399 | BM73: 0 | BN73: 0 | BO73: 1979945 | BP73: 5744657 | BQ73: 1979945 | BR73: 5744657 | BS73: 0 | BT73: 0 | BU73: 0 | BV73: 1979945 | BW73: 5744657 | BX73: 0.55594322 | BY73: 1.621597 | BZ73: 0 | CA73: 344059000 | CB73: 370347000 | CC73: 370347000 | CD73: 0 | CE73: 343990188 | CF73: 370272931 | CG73: 370272931 | CH73: 343990188 | CI73: 370272931 | CJ73: 370272931 | CK73: 5257 | CL73: 0 | CM73: 0.53566878 | CN73: 6.4280254 | CO73: 6.4280254 | CP73: 1.8426481e+08 | CQ73: 2.2111777e+09 | CR73: 2.2111777e+09 | CS73: 1.2679992 | CT73: 4.361793e+08 | CU73: 6.29 | CV73: 0 | CW73: 0 | CX73: 6.29 | CY73: 6.29 | CZ73: 2.1636983e+09 | DA73: 0 | DB73: 0 | DC73: 165351520 | DD73: 165351520 | DE73: 343990188 | DF73: 0 | DG73: 26288000 | DH73: 1 | DI73: 0 | DJ73: 343990188 | DK73: 0 | DL73: 370272931 | DM73: 0 | DN73: 0 | DO73: 0 | DP73: 26288000 | DQ73: 0 | DR73: 0 | DS73: 0 | DT73: 0 | DU73: 0 | DV73: 4.4708058e+08 | DW73: 0 | DX73: 0 | DY73: 0 | DZ73: 0 | EA73: 0 | EB73: 0 | EC73: 0 | ED73: 0 | EE73: 0 | EF73: 0 | EG73: 1979945 | EH73: 0 | EI73: 0 | EJ73: 0 | EK73: 0 | EL73: 5744657 | EM73: 0 | EN73: 0 | EO73: 0 | EP73: 1979945 | EQ73: 5744657 | ER73: 359 | EU73: ~2016 | EV73: 국내대출 | EW73: 0 | EX73: 1979945 | EY73: 0 | EZ73: 0 | FA73: 0 | FB73: 0 | FC73: 5744657 | FD73: 0 | FE73: 0 | FF73: 0 | FG73: 0 | FH73: 0 | FI73: 0 | FJ73: 0 | FK73: 0 | FL73: 0 | FM73: 0 | FN73: 0 | FO73: 0 | FP73: 0 | FQ73: TRUE | FR73: TRUE
A74: BS00000041 | B74: BS0000004101 | C74: 100001934 | D74: 푸른여수지키미 | E74: 푸른여수지키미 | F74: 인프라 | G74: BTL | H74: 하수관거 | I74: 국내 | J74: 아시아 | K74: 이머징 | L74: 한국 | M74: 해당없음 | N74: 출자 | O74: 지분 | P74: 주식형 | Q74: 프로젝트 | R74: KRW | S74: KRW | T74: 38869 | U74: 2958465 | V74: 2958465 | X74: PPP | Y74: Availability(정부) | Z74: 정부보증 | AA74: 정부가 임대료 지급 | AB74: IBK기업은행 | AC74: 해당없음 | AD74: 이건희 | AF74: 유재섭 | AG74: 정상 | AH74: 38877 | AI74: 기보유 | AJ74: 국내실물 | AK74: 인프라 | AL74: Equity | AM74: 인출 | AN74: 운영 | AO74: 0 | AP74: 658290175 | AQ74: 0 | AR74: 0 | AS74: 0 | AT74: 0 | AU74: 0 | AV74: 0 | AW74: 0 | AX74: 0 | AY74: 0 | AZ74: 0 | BA74: 0 | BB74: 0 | BC74: 0 | BD74: 0 | BE74: 0 | BF74: 0 | BG74: 0 | BH74: 0 | BI74: 0 | BJ74: 0 | BK74: 0 | BL74: 0 | BM74: 0 | BN74: 0 | BO74: 0 | BP74: 0 | BQ74: 0 | BR74: 0 | BS74: 0 | BT74: 0 | BU74: 0 | BV74: 0 | BW74: 0 | BX74: 0 | BY74: 0 | BZ74: 0 | CA74: 658290175 | CB74: 658290175 | CC74: 658290175 | CD74: 0 | CE74: 658290175 | CF74: 658290175 | CG74: 658290175 | CH74: 658290175 | CI74: 658290175 | CJ74: 658290175 | CK74: 0 | CL74: 0 | CM74: 2.9802322e-07 | CN74: 2.9802322e-07 | CO74: 0 | CP74: 196.18576 | CQ74: 196.18576 | CR74: 0 | CS74: 0 | CT74: 0 | CU74: 0 | CV74: 0 | CW74: 0 | CX74: 0 | CY74: 0 | CZ74: 0 | DA74: 0 | DB74: 0 | DC74: 0 | DD74: 0 | DE74: 0 | DF74: 0 | DG74: 0 | DH74: 0 | DI74: 1 | DJ74: 0 | DK74: 658290175 | DL74: 0 | DM74: 658290175 | DN74: 0 | DO74: 0 | DP74: 0 | DQ74: 0 | DR74: 0 | DS74: 0 | DT74: 0 | DU74: 0 | DV74: 185512898 | DW74: 0 | DX74: 0 | DY74: 37102580 | DZ74: 0 | EA74: 0 | EB74: 37102580 | EC74: 0.2 | ED74: 37102580 | EE74: 131658035 | EF74: 0 | EG74: 0 | EH74: 0 | EI74: 0 | EJ74: 0 | EK74: 0 | EL74: 0 | EM74: 0 | EN74: 0 | EO74: 0 | EP74: 0 | EQ74: 0 | ER74: 450 | EU74: ~2016 | EV74: 국내출자 | EW74: 0 | EX74: 0 | EY74: 0 | EZ74: 0 | FA74: 0 | FB74: 0 | FC74: 0 | FD74: 0 | FE74: 0 | FF74: 0 | FG74: 0 | FH74: 0 | FI74: 0 | FJ74: 0 | FK74: 0 | FL74: 0 | FM74: 0 | FN74: 0 | FO74: 0 | FP74: 0 | FQ74: TRUE | FR74: TRUE
A75: BS00000043 | B75: 705379090700 | C75: 6000000000259 | D75: 기능대 BTL | E75: 기능대비티엘(주) [한국폴리텍대학 기숙사 및 공학관] | F75: 인프라 | G75: BTL | H75: 교육시설 | I75: 국내 | J75: 아시아 | K75: 이머징 | L75: 한국 | M75: 해당없음 | N75: 대출 | O75: 선순위 | P75: 대출 | Q75: 프로젝트 | R75: KRW | S75: KRW | T75: 39496 | U75: 2958465 | V75: 2958465 | X75: PPP | Y75: Availability(정부) | Z75: 정부보증 | AA75: 정부가 임대료 지급 | AB75: IBK기업은행 | AC75: 해당없음 | AD75: 이다인 | AF75: 유재섭 | AG75: 정상 | AH75: 38919 | AI75: 기보유 | AJ75: 국내실물 | AK75: 인프라 | AL75: Debt | AM75: 인출 | AN75: 운영 | AO75: 0 | AP75: 6281000000 | AQ75: 0 | AR75: 0 | AS75: 0 | AT75: 0 | AU75: 0 | AV75: 0 | AW75: 6281000000 | AX75: 0 | AY75: 126198000 | AZ75: 5931178467 | BA75: 0 | BB75: -126198000 | BC75: 349821533 | BD75: 0 | BE75: 5568323 | BF75: 299333171 | BG75: 0 | BH75: 5568323 | BI75: 0 | BJ75: 0 | BK75: 0 | BL75: 4466991 | BM75: 0 | BN75: 0 | BO75: 1379209 | BP75: 4492451 | BQ75: 1379209 | BR75: 4492451 | BS75: 0 | BT75: 0 | BU75: 0 | BV75: 1379209 | BW75: 4492451 | BX75: 0.39503116 | BY75: 1.0939727 | BZ75: 0 | CA75: 350017000 | CB75: 350017000 | CC75: 476215000 | CD75: 0 | CE75: 349821533 | CF75: 349836263 | CG75: 475980425 | CH75: 349821533 | CI75: 349836263 | CJ75: 475980425 | CK75: 39108 | CL75: 0 | CM75: 0.39339101 | CN75: 4.7206921 | CO75: 4.7206921 | CP75: 1.3761665e+08 | CQ75: 1.6513997e+09 | CR75: 1.6513997e+09 | CS75: 1.0476569 | CT75: 3.6649295e+08 | CU75: 4.69 | CV75: 0 | CW75: 0 | CX75: 0 | CY75: 4.69 | CZ75: 1.640663e+09 | DA75: 0 | DB75: 0 | DC75: 0 | DD75: 591868620 | DE75: 349821533 | DF75: 0 | DG75: 0 | DH75: 1 | DI75: 0 | DJ75: 349821533 | DK75: 0 | DL75: 475980425 | DM75: 0 | DN75: 0 | DO75: 0 | DP75: 126198000 | DQ75: 0 | DR75: 0 | DS75: 0 | DT75: 0 | DU75: 0 | DV75: 7.2408802e+08 | DW75: 0 | DX75: 0 | DY75: 0 | DZ75: 0 | EA75: 0 | EB75: 0 | EC75: 0 | ED75: 0 | EE75: 0 | EF75: 0 | EG75: 1379209 | EH75: 0 | EI75: 0 | EJ75: 0 | EK75: 0 | EL75: 4492451 | EM75: 0 | EN75: 0 | EO75: 0 | EP75: 1379209 | EQ75: 4492451 | ER75: 367 | EU75: ~2016 | EV75: 국내대출 | EW75: 0 | EX75: 1379209 | EY75: 0 | EZ75: 0 | FA75: 0 | FB75: 0 | FC75: 4492451 | FD75: 0 | FE75: 0 | FF75: 0 | FG75: 0 | FH75: 0 | FI75: 0 | FJ75: 0 | FK75: 0 | FL75: 0 | FM75: 0 | FN75: 0 | FO75: 0 | FP75: 0 | FQ75: TRUE | FR75: TRUE
A76: BS00000043 | B76: 705379090700 | C76: 6000000000260 | D76: 기능대 BTL | E76: 기능대비티엘(주) [한국폴리텍대학 기숙사 및 공학관] | F76: 인프라 | G76: BTL | H76: 교육시설 | I76: 국내 | J76: 아시아 | K76: 이머징 | L76: 한국 | M76: 해당없음 | N76: 대출 | O76: 선순위 | P76: 대출 | Q76: 프로젝트 | R76: KRW | S76: KRW | T76: 39496 | U76: 2958465 | V76: 2958465 | X76: PPP | Y76: Availability(정부) | Z76: 정부보증 | AA76: 정부가 임대료 지급 | AB76: IBK기업은행 | AC76: 해당없음 | AD76: 이다인 | AF76: 유재섭 | AG76: 정상 | AH76: 38919 | AI76: 기보유 | AJ76: 국내실물 | AK76: 인프라 | AL76: Debt | AM76: 인출 | AN76: 운영 | AO76: 0 | AP76: 918000000 | AQ76: 0 | AR76: 0 | AS76: 0 | AT76: 0 | AU76: 0 | AV76: 0 | AW76: 918000000 | AX76: 0 | AY76: 18550000 | AZ76: 866591886 | BA76: 0 | BB76: -18550000 | BC76: 51408114 | BD76: 0 | BE76: 1555066 | BF76: 84788344 | BG76: 0 | BH76: 1555066 | BI76: 0 | BJ76: 0 | BK76: 0 | BL76: 1245734 | BM76: 0 | BN76: 0 | BO76: 384856 | BP76: 1249506 | BQ76: 384856 | BR76: 1249506 | BS76: 0 | BT76: 0 | BU76: 0 | BV76: 384856 | BW76: 1249506 | BX76: 0.7514091 | BY76: 2.0805868 | BZ76: 0 | CA76: 51454000 | CB76: 51454000 | CC76: 70004000 | CD76: 0 | CE76: 51408114 | CF76: 51412552 | CG76: 69952313 | CH76: 51408114 | CI76: 51412552 | CJ76: 69952313 | CK76: 5801 | CL76: 0 | CM76: 0.75826429 | CN76: 9.0991715 | CO76: 9.0991715 | CP76: 38980937 | CQ76: 4.6777125e+08 | CR76: 4.6777125e+08 | CS76: 1.092362 | CT76: 56156272 | CU76: 8.91 | CV76: 0 | CW76: 0 | CX76: 0 | CY76: 8.91 | CZ76: 4.580463e+08 | DA76: 0 | DB76: 0 | DC76: 0 | DD76: 165280500 | DE76: 51408114 | DF76: 0 | DG76: 0 | DH76: 1 | DI76: 0 | DJ76: 51408114 | DK76: 0 | DL76: 69952313 | DM76: 0 | DN76: 0 | DO76: 0 | DP76: 18550000 | DQ76: 0 | DR76: 0 | DS76: 0 | DT76: 0 | DU76: 0 | DV76: 1.0717151e+08 | DW76: 0 | DX76: 0 | DY76: 0 | DZ76: 0 | EA76: 0 | EB76: 0 | EC76: 0 | ED76: 0 | EE76: 0 | EF76: 0 | EG76: 384856 | EH76: 0 | EI76: 0 | EJ76: 0 | EK76: 0 | EL76: 1249506 | EM76: 0 | EN76: 0 | EO76: 0 | EP76: 384856 | EQ76: 1249506 | ER76: 387 | EU76: ~2016 | EV76: 국내대출 | EW76: 0 | EX76: 384856 | EY76: 0 | EZ76: 0 | FA76: 0 | FB76: 0 | FC76: 1249506 | FD76: 0 | FE76: 0 | FF76: 0 | FG76: 0 | FH76: 0 | FI76: 0 | FJ76: 0 | FK76: 0 | FL76: 0 | FM76: 0 | FN76: 0 | FO76: 0 | FP76: 0 | FQ76: TRUE | FR76: TRUE
A77: BS00000043 | B77: BS0000004301 | C77: 100001915 | D77: 기능대 BTL | E77: 기능대비티엘 | F77: 인프라 | G77: BTL | H77: 교육시설 | I77: 국내 | J77: 아시아 | K77: 이머징 | L77: 한국 | M77: 해당없음 | N77: 출자 | O77: 지분 | P77: 주식형 | Q77: 프로젝트 | R77: KRW | S77: KRW | T77: 38923 | U77: 2958465 | V77: 2958465 | X77: PPP | Y77: Availability(정부) | Z77: 정부보증 | AA77: 정부가 임대료 지급 | AB77: IBK기업은행 | AC77: 해당없음 | AD77: 이다인 | AF77: 유재섭 | AG77: 정상 | AI77: 기보유 | AJ77: 국내실물 | AK77: 인프라 | AL77: Equity | AM77: 인출 | AN77: 운영 | AO77: 0 | AP77: 475345936 | AQ77: 0 | AR77: 0 | AS77: 0 | AT77: 0 | AU77: 0 | AV77: 0 | AW77: 0 | AX77: 0 | AY77: 0 | AZ77: 0 | BA77: 0 | BB77: 0 | BC77: 0 | BD77: 0 | BE77: 0 | BF77: 0 | BG77: 0 | BH77: 0 | BI77: 0 | BJ77: 0 | BK77: 0 | BL77: 0 | BM77: 0 | BN77: 0 | BO77: 0 | BP77: 0 | BQ77: 0 | BR77: 0 | BS77: 0 | BT77: 0 | BU77: 0 | BV77: 0 | BW77: 0 | BX77: 0 | BY77: 0 | BZ77: 0 | CA77: 475345936 | CB77: 475345936 | CC77: 475345936 | CD77: 0 | CE77: 475345936 | CF77: 475345936 | CG77: 475345936 | CH77: 475345936 | CI77: 475345936 | CJ77: 475345936 | CK77: 0 | CL77: 0 | CM77: 2.9802322e-07 | CN77: 2.9802322e-07 | CO77: 0 | CP77: 141.66413 | CQ77: 141.66413 | CR77: 0 | CS77: 0 | CT77: 0 | CU77: 0 | CV77: 0 | CW77: 0 | CX77: 0 | CY77: 0 | CZ77: 0 | DA77: 0 | DB77: 0 | DC77: 0 | DD77: 0 | DE77: 0 | DF77: 0 | DG77: 0 | DH77: 0 | DI77: 1 | DJ77: 0 | DK77: 475345936 | DL77: 0 | DM77: 475345936 | DN77: 0 | DO77: 0 | DP77: 0 | DQ77: 0 | DR77: 0 | DS77: 0 | DT77: 0 | DU77: 0 | DV77: 574474851 | DW77: 0 | DX77: 0 | DY77: 1.1489497e+08 | DZ77: 0 | EA77: 0 | EB77: 1.1489497e+08 | EC77: 0.2 | ED77: 1.1489497e+08 | EE77: 95069187 | EF77: 0 | EG77: 0 | EH77: 0 | EI77: 0 | EJ77: 0 | EK77: 0 | EL77: 0 | EM77: 0 | EN77: 0 | EO77: 0 | EP77: 0 | EQ77: 0 | ER77: 450 | EU77: ~2016 | EV77: 국내출자 | EW77: 0 | EX77: 0 | EY77: 0 | EZ77: 0 | FA77: 0 | FB77: 0 | FC77: 0 | FD77: 0 | FE77: 0 | FF77: 0 | FG77: 0 | FH77: 0 | FI77: 0 | FJ77: 0 | FK77: 0 | FL77: 0 | FM77: 0 | FN77: 0 | FO77: 0 | FP77: 0 | FQ77: TRUE | FR77: TRUE
A78: BS00000044 | B78: BS0000004401 | C78: 200000296 | D78: 동북아 인프라 사모특별자산투자신탁 1호 | E78: 동북아인프라특별자산1호 | F78: 인프라 | G78: BTL | H78: 혼합 | I78: 국내 | J78: 아시아 | K78: 이머징 | L78: 한국 | M78: 해당없음 | N78: 수익증권 | O78: 선순위 | P78: 채권형 | Q78: 블라인드 | R78: KRW | S78: KRW | T78: 38959 | U78: 48090 | V78: 48090 | X78: PPP | Y78: Availability(정부) | Z78: 정부보증 | AA78: 정부가 임대료 지급 | AB78: 키움투자자산운용 | AC78: 해당없음 | AD78: 배상원 | AF78: 유재섭 | AG78: 정상 | AI78: 기보유 | AJ78: 국내실물 | AK78: 인프라 | AL78: Debt | AM78: 인출 | AN78: 운영 | AO78: 0 | AP78: 100000000000 | AQ78: 0 | AR78: 0 | AS78: 0 | AT78: 0 | AU78: 0 | AV78: 0 | AW78: 98570024397 | AX78: 0 | AY78: 2161043510 | AZ78: 54211054425 | BA78: 0 | BB78: -2161043510 | BC78: 44358969972 | BD78: 0 | BE78: 344189910 | BF78: 52844919855 | BG78: 344189910 | BH78: 0 | BI78: 0 | BJ78: -10027150 | BK78: 344189910 | BL78: 0 | BM78: 121005071 | BN78: 110977920 | BO78: 0 | BP78: 344189910 | BQ78: 121005071 | BR78: 455167830 | BS78: 0 | BT78: 0 | BU78: 0 | BV78: 121005071 | BW78: 455167830 | BX78: 0.28055471 | BY78: 1.0333191 | BZ78: 0 | CA78: 43195507410 | CB78: 43195507410 | CC78: 45369842748 | CD78: 0 | CE78: 43251656161 | CF78: 43130651090 | CG78: 45301721751 | CH78: 43251656161 | CI78: 43130651090 | CJ78: 45301721751 | CK78: 110977920 | CL78: 897723306 | CM78: 3.3536902 | CN78: 4.2900571 | CO78: 4.227995 | CP78: 1.4505266e+11 | CQ78: 1.8555208e+11 | CR78: 1.8286779e+11 | CS78: 1.5248817 | CT78: 6.5953661e+10 | CU78: 0 | CV78: 0 | CW78: 0 | CX78: 0 | CY78: 0 | CZ78: 0 | DA78: 0 | DB78: 0 | DC78: 0 | DD78: 0 | DE78: 0 | DF78: 0 | DG78: 0 | DH78: 0.761072 | DI78: 0.238928 | DJ78: 3.2917624e+10 | DK78: 1.0334032e+10 | DL78: 3.4477872e+10 | DM78: 1.082385e+10 | DN78: 0 | DO78: 0 | DP78: 1.6447097e+09 | DQ78: 5.1633381e+08 | DR78: 0 | DS78: 0 | DT78: 0 | DU78: 0 | DV78: 50232239967 | DW78: 1.0704406e+09 | DX78: 0 | DY78: 2.1433516e+09 | DZ78: 0 | EA78: 0 | EB78: 3.2137921e+09 | EC78: 0.063978674 | ED78: 3.2137921e+09 | EE78: 2.7671836e+09 | EF78: 0 | EG78: 0 | EH78: 0 | EI78: 0 | EJ78: 121005071 | EK78: 0 | EL78: 344189910 | EM78: -10027150 | EN78: 0 | EO78: 121005070 | EP78: 121005071 | EQ78: 455167830 | ER78: 194 | EU78: ~2016 | EV78: 국내간접투자 | EW78: 0 | EX78: 0 | EY78: 0 | EZ78: 0 | FA78: 92093571 | FB78: 0 | FC78: 2.619533e+08 | FD78: -7631383.1 | FE78: 0 | FF78: 92093570 | FG78: 0 | FH78: 0 | FI78: 0 | FJ78: 0 | FK78: 28911500 | FL78: 0 | FM78: 82236607 | FN78: -2395766.9 | FO78: 0 | FP78: 28911500 | FQ78: TRUE | FR78: TRUE
A79: BS00000045 | B79: BS0000004501 | C79: 200000297 | D79: 동북아 인프라 사모특별자산투자신탁 2호 | E79: 키움동북아인프라 일반 사모특별자산투자신탁제2호 | F79: 인프라 | G79: BTL | H79: 혼합 | I79: 국내 | J79: 아시아 | K79: 이머징 | L79: 한국 | M79: 해당없음 | N79: 수익증권 | O79: 지분 | P79: 채권형 | Q79: 블라인드 | R79: KRW | S79: KRW | T79: 39268 | U79: 48400 | V79: 48400 | X79: PPP | Y79: Availability(정부) | Z79: 정부보증 | AA79: 정부가 임대료 지급 | AB79: 키움투자자산운용 | AC79: 해당없음 | AD79: 배상원 | AF79: 유재섭 | AG79: 정상 | AI79: 기보유 | AJ79: 국내실물 | AK79: 인프라 | AL79: Debt | AM79: 인출 | AN79: 운영 | AO79: 0 | AP79: 100000000000 | AQ79: 0 | AR79: 0 | AS79: 0 | AT79: 0 | AU79: 0 | AV79: 0 | AW79: 98257031010 | AX79: 0 | AY79: 2076235509 | AZ79: 47985945802 | BA79: 0 | BB79: -2076235509 | BC79: 50271085208 | BD79: 0 | BE79: 384365553 | BF79: 57396283090 | BG79: 384365553 | BH79: 0 | BI79: 0 | BJ79: -8545195 | BK79: 384365553 | BL79: 0 | BM79: 89308505 | BN79: 80763309 | BO79: 0 | BP79: 384365553 | BQ79: 89308505 | BR79: 465128862 | BS79: 0 | BT79: 0 | BU79: 0 | BV79: 89308505 | BW79: 465128862 | BX79: 0.17674227 | BY79: 0.90518694 | BZ79: 0 | CA79: 49618854988 | CB79: 49618854988 | CC79: 51666028835 | CD79: 0 | CE79: 50619668492 | CF79: 50530359987 | CG79: 52615140692 | CH79: 50619668492 | CI79: 50530359987 | CJ79: 52615140692 | CK79: 80763309 | CL79: 1111901314 | CM79: 2.1009257 | CN79: 3.7461767 | CO79: 4.592829 | CP79: 1.0634816e+11 | CQ79: 1.8963022e+11 | CR79: 2.3248748e+11 | CS79: 1.587692 | CT79: 8.036844e+10 | CU79: 0 | CV79: 0 | CW79: 0 | CX79: 0 | CY79: 0 | CZ79: 0 | DA79: 0 | DB79: 0 | DC79: 0 | DD79: 0 | DE79: 0 | DF79: 0 | DG79: 0 | DH79: 0.6361219 | DI79: 0.3638781 | DJ79: 3.2200279e+10 | DK79: 1.8419389e+10 | DL79: 3.3469643e+10 | DM79: 1.9145498e+10 | DN79: 0 | DO79: 0 | DP79: 1.3207389e+09 | DQ79: 7.5549664e+08 | DR79: 0 | DS79: 0 | DT79: 0 | DU79: 0 | DV79: 56890408173 | DW79: 9.8018834e+08 | DX79: 0 | DY79: 3.7322254e+09 | DZ79: 0 | EA79: 0 | EB79: 4.7124137e+09 | EC79: 0.082833186 | ED79: 4.7124137e+09 | EE79: 4.1929884e+09 | EF79: 0 | EG79: 0 | EH79: 0 | EI79: 0 | EJ79: 89308505 | EK79: 0 | EL79: 384365553 | EM79: -8545195 | EN79: 0 | EO79: 89308504 | EP79: 89308505 | EQ79: 465128862 | ER79: 191 | EU79: ~2016 | EV79: 국내간접투자 | EW79: 0 | EX79: 0 | EY79: 0 | EZ79: 0 | FA79: 56811096 | FB79: 0 | FC79: 2.4450334e+08 | FD79: -5435785.6 | FE79: 0 | FF79: 56811095 | FG79: 0 | FH79: 0 | FI79: 0 | FJ79: 0 | FK79: 32497409 | FL79: 0 | FM79: 1.3986221e+08 | FN79: -3109409.4 | FO79: 0 | FP79: 32497409 | FQ79: TRUE | FR79: TRUE
A80: BS00000046 | B80: BS0000004601 | C80: 200000298 | D80: 동북아 인프라 사모특별자산투자신탁 3호 | E80: 동북아인프라특별자산3호 | F80: 인프라 | G80: BTL | H80: 혼합 | I80: 국내 | J80: 아시아 | K80: 이머징 | L80: 한국 | M80: 해당없음 | N80: 수익증권 | O80: 혼합 | P80: 채권형 | Q80: 블라인드 | R80: KRW | S80: KRW | T80: 39556 | U80: 48687 | V80: 48687 | X80: PPP | Y80: Availability(정부) | Z80: 정부보증 | AA80: 정부가 임대료 지급 | AB80: 키움투자자산운용 | AC80: 해당없음 | AD80: 배상원 | AF80: 유재섭 | AG80: 정상 | AI80: 기보유 | AJ80: 국내실물 | AK80: 인프라 | AL80: Debt | AM80: 인출 | AN80: 운영 | AO80: 0 | AP80: 50000000000 | AQ80: 0 | AR80: 0 | AS80: 0 | AT80: 0 | AU80: 0 | AV80: 0 | AW80: 49986001490 | AX80: 0 | AY80: 561555083 | AZ80: 13980608743 | BA80: 0 | BB80: -561555083 | BC80: 36005392747 | BD80: 0 | BE80: 258455996 | BF80: 37050080192 | BG80: 258455996 | BH80: 0 | BI80: 0 | BJ80: -2409237 | BK80: 258455996 | BL80: 0 | BM80: 56966136 | BN80: 54556899 | BO80: 0 | BP80: 258455996 | BQ80: 56966136 | BR80: 313012895 | BS80: 0 | BT80: 0 | BU80: 0 | BV80: 56966136 | BW80: 313012895 | BX80: 0.16077745 | BY80: 0.87960479 | BZ80: 0 | CA80: 35449544581 | CB80: 35449544581 | CC80: 36013793409 | CD80: 0 | CE80: 35488636220 | CF80: 35431670084 | CG80: 35995634404 | CH80: 35488636220 | CI80: 35431670084 | CJ80: 35995634404 | CK80: 54556899 | CL80: 495443721 | CM80: 1.9095072 | CN80: 3.6267206 | CO80: 5.7087716 | CP80: 6.7765807e+10 | CQ80: 1.2870737e+11 | CR80: 2.0259652e+11 | CS80: 1.7308711 | CT80: 6.1426255e+10 | CU80: 0 | CV80: 0 | CW80: 0 | CX80: 0 | CY80: 0 | CZ80: 0 | DA80: 0 | DB80: 0 | DC80: 0 | DD80: 0 | DE80: 0 | DF80: 0 | DG80: 0 | DH80: 0.61567767 | DI80: 0.38432233 | DJ80: 2.1849561e+10 | DK80: 1.3639075e+10 | DL80: 2.2161708e+10 | DM80: 1.3833926e+10 | DN80: 0 | DO80: 0 | DP80: 3.4573693e+08 | DQ80: 2.1581816e+08 | DR80: 0 | DS80: 0 | DT80: 0 | DU80: 0 | DV80: 37194254622 | DW80: 5.7962467e+08 | DX80: 0 | DY80: 2.7213845e+09 | DZ80: 0 | EA80: 0 | EB80: 3.3010091e+09 | EC80: 0.088750512 | ED80: 3.3010091e+09 | EE80: 3.1496346e+09 | EF80: 0 | EG80: 0 | EH80: 0 | EI80: 0 | EJ80: 56966136 | EK80: 0 | EL80: 258455996 | EM80: -2409237 | EN80: 0 | EO80: 56966136 | EP80: 56966136 | EQ80: 313012895 | ER80: 219 | EU80: ~2016 | EV80: 국내간접투자 | EW80: 0 | EX80: 0 | EY80: 0 | EZ80: 0 | FA80: 35072778 | FB80: 0 | FC80: 1.5912559e+08 | FD80: -1483313.4 | FE80: 0 | FF80: 35072778 | FG80: 0 | FH80: 0 | FI80: 0 | FJ80: 0 | FK80: 21893358 | FL80: 0 | FM80: 99330410 | FN80: -925923.57 | FO80: 0 | FP80: 21893358 | FQ80: TRUE | FR80: TRUE
A81: BS00000048 | B81: 805409765800 | C81: 6000000000183 | D81: 일산에듀피아 | E81: 일산에듀피아(주) | F81: 인프라 | G81: BTL | H81: 교육시설 | I81: 국내 | J81: 아시아 | K81: 이머징 | L81: 한국 | M81: 해당없음 | N81: 대출 | O81: 선순위 | P81: 대출 | Q81: 프로젝트 | R81: KRW | S81: KRW | T81: 39302 | U81: 45107 | V81: 45107 | W81: 45747 | X81: PPP | Y81: Availability(정부) | Z81: 정부보증 | AA81: 정부가 임대료 지급 | AB81: IBK기업은행 | AC81: 해당없음 | AD81: 이다인 | AF81: 유재섭 | AG81: 정상 | AI81: 기보유 | AJ81: 국내실물 | AK81: 인프라 | AL81: Debt | AM81: 인출 | AN81: 상환 | AO81: 0 | AP81: 2397000000 | AQ81: 0 | AR81: 0 | AS81: 0 | AT81: 0 | AU81: 0 | AV81: 0 | AW81: 0 | AX81: 0 | AY81: 0 | AZ81: 0 | BA81: 0 | BB81: 0 | BC81: 0 | BD81: 0 | BE81: 0 | BF81: 0 | BG81: 0 | BH81: 0 | BI81: 0 | BJ81: 0 | BK81: 0 | BL81: 0 | BM81: 0 | BN81: 0 | BO81: 0 | BP81: 0 | BQ81: 0 | BR81: 0 | BS81: 0 | BT81: 0 | BU81: 0 | BV81: 0 | BW81: 0 | BX81: 0 | BY81: 0 | BZ81: 0 | CA81: 0 | CB81: 0 | CC81: 0 | CD81: 0 | CE81: 0 | CF81: 0 | CG81: 0 | CH81: 0 | CI81: 0 | CJ81: 0 | CK81: 0 | CL81: 0 | CM81: 0 | CN81: 0 | CO81: 0 | CP81: 0 | CQ81: 0 | CR81: 0 | CS81: 0 | CT81: 0 | CU81: 0 | CV81: 0 | CW81: 0 | CX81: 0 | CY81: 0 | CZ81: 0 | DA81: 0 | DB81: 0 | DC81: 0 | DD81: 0 | DE81: 0 | DF81: 0 | DG81: 0 | DH81: 1 | DI81: 0 | DJ81: 0 | DK81: 0 | DL81: 0 | DM81: 0 | DN81: 0 | DO81: 0 | DP81: 0 | DQ81: 0 | DR81: 0 | DS81: 0 | DT81: 0 | DU81: 0 | DV81: 0 | DW81: 0 | DX81: 0 | DY81: 0 | DZ81: 0 | EA81: 0 | EB81: 0 | EC81: 0 | ED81: 0 | EE81: 0 | EF81: 0 | EG81: 0 | EH81: 0 | EI81: 0 | EJ81: 0 | EK81: 0 | EL81: 0 | EM81: 0 | EN81: 0 | EO81: 0 | EP81: 0 | EQ81: 0 | ER81: 450 | EU81: ~2016 | EV81: 국내대출 | EW81: 0 | EX81: 0 | EY81: 0 | EZ81: 0 | FA81: 0 | FB81: 0 | FC81: 0 | FD81: 0 | FE81: 0 | FF81: 0 | FG81: 0 | FH81: 0 | FI81: 0 | FJ81: 0 | FK81: 0 | FL81: 0 | FM81: 0 | FN81: 0 | FO81: 0 | FP81: 0 | FQ81: TRUE | FR81: TRUE
A82: BS00000048 | B82: 805409765800 | C82: 6000000000184 | D82: 일산에듀피아 | E82: 일산에듀피아(주) | F82: 인프라 | G82: BTL | H82: 교육시설 | I82: 국내 | J82: 아시아 | K82: 이머징 | L82: 한국 | M82: 해당없음 | N82: 대출 | O82: 선순위 | P82: 대출 | Q82: 프로젝트 | R82: KRW | S82: KRW | T82: 39302 | U82: 45107 | V82: 45107 | W82: 45747 | X82: PPP | Y82: Availability(정부) | Z82: 정부보증 | AA82: 정부가 임대료 지급 | AB82: IBK기업은행 | AC82: 해당없음 | AD82: 이다인 | AF82: 유재섭 | AG82: 정상 | AI82: 기보유 | AJ82: 국내실물 | AK82: 인프라 | AL82: Debt | AM82: 인출 | AN82: 상환 | AO82: 0 | AP82: 2241000000 | AQ82: 0 | AR82: 0 | AS82: 0 | AT82: 0 | AU82: 0 | AV82: 0 | AW82: 0 | AX82: 0 | AY82: 0 | AZ82: 0 | BA82: 0 | BB82: 0 | BC82: 0 | BD82: 0 | BE82: 0 | BF82: 0 | BG82: 0 | BH82: 0 | BI82: 0 | BJ82: 0 | BK82: 0 | BL82: 0 | BM82: 0 | BN82: 0 | BO82: 0 | BP82: 0 | BQ82: 0 | BR82: 0 | BS82: 0 | BT82: 0 | BU82: 0 | BV82: 0 | BW82: 0 | BX82: 0 | BY82: 0 | BZ82: 0 | CA82: 0 | CB82: 0 | CC82: 0 | CD82: 0 | CE82: 0 | CF82: 0 | CG82: 0 | CH82: 0 | CI82: 0 | CJ82: 0 | CK82: 0 | CL82: 0 | CM82: 0 | CN82: 0 | CO82: 0 | CP82: 0 | CQ82: 0 | CR82: 0 | CS82: 0 | CT82: 0 | CU82: 0 | CV82: 0 | CW82: 0 | CX82: 0 | CY82: 0 | CZ82: 0 | DA82: 0 | DB82: 0 | DC82: 0 | DD82: 0 | DE82: 0 | DF82: 0 | DG82: 0 | DH82: 1 | DI82: 0 | DJ82: 0 | DK82: 0 | DL82: 0 | DM82: 0 | DN82: 0 | DO82: 0 | DP82: 0 | DQ82: 0 | DR82: 0 | DS82: 0 | DT82: 0 | DU82: 0 | DV82: 0 | DW82: 0 | DX82: 0 | DY82: 0 | DZ82: 0 | EA82: 0 | EB82: 0 | EC82: 0 | ED82: 0 | EE82: 0 | EF82: 0 | EG82: 0 | EH82: 0 | EI82: 0 | EJ82: 0 | EK82: 0 | EL82: 0 | EM82: 0 | EN82: 0 | EO82: 0 | EP82: 0 | EQ82: 0 | ER82: 450 | EU82: ~2016 | EV82: 국내대출 | EW82: 0 | EX82: 0 | EY82: 0 | EZ82: 0 | FA82: 0 | FB82: 0 | FC82: 0 | FD82: 0 | FE82: 0 | FF82: 0 | FG82: 0 | FH82: 0 | FI82: 0 | FJ82: 0 | FK82: 0 | FL82: 0 | FM82: 0 | FN82: 0 | FO82: 0 | FP82: 0 | FQ82: TRUE | FR82: TRUE
A83: BS00000048 | B83: 805409765800 | C83: 6000000000185 | D83: 일산에듀피아 | E83: 일산에듀피아(주) | F83: 인프라 | G83: BTL | H83: 교육시설 | I83: 국내 | J83: 아시아 | K83: 이머징 | L83: 한국 | M83: 해당없음 | N83: 대출 | O83: 선순위 | P83: 대출 | Q83: 프로젝트 | R83: KRW | S83: KRW | T83: 39302 | U83: 45107 | V83: 45107 | W83: 45747 | X83: PPP | Y83: Availability(정부) | Z83: 정부보증 | AA83: 정부가 임대료 지급 | AB83: IBK기업은행 | AC83: 해당없음 | AD83: 이다인 | AF83: 유재섭 | AG83: 정상 | AI83: 기보유 | AJ83: 국내실물 | AK83: 인프라 | AL83: Debt | AM83: 인출 | AN83: 상환 | AO83: 0 | AP83: 1212000000 | AQ83: 0 | AR83: 0 | AS83: 0 | AT83: 0 | AU83: 0 | AV83: 0 | AW83: 0 | AX83: 0 | AY83: 0 | AZ83: 0 | BA83: 0 | BB83: 0 | BC83: 0 | BD83: 0 | BE83: 0 | BF83: 0 | BG83: 0 | BH83: 0 | BI83: 0 | BJ83: 0 | BK83: 0 | BL83: 0 | BM83: 0 | BN83: 0 | BO83: 0 | BP83: 0 | BQ83: 0 | BR83: 0 | BS83: 0 | BT83: 0 | BU83: 0 | BV83: 0 | BW83: 0 | BX83: 0 | BY83: 0 | BZ83: 0 | CA83: 0 | CB83: 0 | CC83: 0 | CD83: 0 | CE83: 0 | CF83: 0 | CG83: 0 | CH83: 0 | CI83: 0 | CJ83: 0 | CK83: 0 | CL83: 0 | CM83: 0 | CN83: 0 | CO83: 0 | CP83: 0 | CQ83: 0 | CR83: 0 | CS83: 0 | CT83: 0 | CU83: 0 | CV83: 0 | CW83: 0 | CX83: 0 | CY83: 0 | CZ83: 0 | DA83: 0 | DB83: 0 | DC83: 0 | DD83: 0 | DE83: 0 | DF83: 0 | DG83: 0 | DH83: 1 | DI83: 0 | DJ83: 0 | DK83: 0 | DL83: 0 | DM83: 0 | DN83: 0 | DO83: 0 | DP83: 0 | DQ83: 0 | DR83: 0 | DS83: 0 | DT83: 0 | DU83: 0 | DV83: 0 | DW83: 0 | DX83: 0 | DY83: 0 | DZ83: 0 | EA83: 0 | EB83: 0 | EC83: 0 | ED83: 0 | EE83: 0 | EF83: 0 | EG83: 0 | EH83: 0 | EI83: 0 | EJ83: 0 | EK83: 0 | EL83: 0 | EM83: 0 | EN83: 0 | EO83: 0 | EP83: 0 | EQ83: 0 | ER83: 450 | EU83: ~2016 | EV83: 국내대출 | EW83: 0 | EX83: 0 | EY83: 0 | EZ83: 0 | FA83: 0 | FB83: 0 | FC83: 0 | FD83: 0 | FE83: 0 | FF83: 0 | FG83: 0 | FH83: 0 | FI83: 0 | FJ83: 0 | FK83: 0 | FL83: 0 | FM83: 0 | FN83: 0 | FO83: 0 | FP83: 0 | FQ83: TRUE | FR83: TRUE
A84: BS00000048 | B84: 805409765800 | C84: 6000000000230 | D84: 일산에듀피아 | E84: 일산에듀피아(주) | F84: 인프라 | G84: BTL | H84: 교육시설 | I84: 국내 | J84: 아시아 | K84: 이머징 | L84: 한국 | M84: 해당없음 | N84: 대출 | O84: 선순위 | P84: 대출 | Q84: 프로젝트 | R84: KRW | S84: KRW | T84: 39302 | U84: 45107 | V84: 45107 | W84: 45747 | X84: PPP | Y84: Availability(정부) | Z84: 정부보증 | AA84: 정부가 임대료 지급 | AB84: IBK기업은행 | AC84: 해당없음 | AD84: 이다인 | AF84: 유재섭 | AG84: 정상 | AI84: 기보유 | AJ84: 국내실물 | AK84: 인프라 | AL84: Debt | AM84: 인출 | AN84: 상환 | AO84: 0 | AP84: 3426000000 | AQ84: 0 | AR84: 0 | AS84: 0 | AT84: 0 | AU84: 0 | AV84: 0 | AW84: 0 | AX84: 0 | AY84: 0 | AZ84: 0 | BA84: 0 | BB84: 0 | BC84: 0 | BD84: 0 | BE84: 0 | BF84: 0 | BG84: 0 | BH84: 0 | BI84: 0 | BJ84: 0 | BK84: 0 | BL84: 0 | BM84: 0 | BN84: 0 | BO84: 0 | BP84: 0 | BQ84: 0 | BR84: 0 | BS84: 0 | BT84: 0 | BU84: 0 | BV84: 0 | BW84: 0 | BX84: 0 | BY84: 0 | BZ84: 0 | CA84: 0 | CB84: 0 | CC84: 0 | CD84: 0 | CE84: 0 | CF84: 0 | CG84: 0 | CH84: 0 | CI84: 0 | CJ84: 0 | CK84: 0 | CL84: 0 | CM84: 0 | CN84: 0 | CO84: 0 | CP84: 0 | CQ84: 0 | CR84: 0 | CS84: 0 | CT84: 0 | CU84: 0 | CV84: 0 | CW84: 0 | CX84: 0 | CY84: 0 | CZ84: 0 | DA84: 0 | DB84: 0 | DC84: 0 | DD84: 0 | DE84: 0 | DF84: 0 | DG84: 0 | DH84: 1 | DI84: 0 | DJ84: 0 | DK84: 0 | DL84: 0 | DM84: 0 | DN84: 0 | DO84: 0 | DP84: 0 | DQ84: 0 | DR84: 0 | DS84: 0 | DT84: 0 | DU84: 0 | DV84: 0 | DW84: 0 | DX84: 0 | DY84: 0 | DZ84: 0 | EA84: 0 | EB84: 0 | EC84: 0 | ED84: 0 | EE84: 0 | EF84: 0 | EG84: 0 | EH84: 0 | EI84: 0 | EJ84: 0 | EK84: 0 | EL84: 0 | EM84: 0 | EN84: 0 | EO84: 0 | EP84: 0 | EQ84: 0 | ER84: 450 | EU84: ~2016 | EV84: 국내대출 | EW84: 0 | EX84: 0 | EY84: 0 | EZ84: 0 | FA84: 0 | FB84: 0 | FC84: 0 | FD84: 0 | FE84: 0 | FF84: 0 | FG84: 0 | FH84: 0 | FI84: 0 | FJ84: 0 | FK84: 0 | FL84: 0 | FM84: 0 | FN84: 0 | FO84: 0 | FP84: 0 | FQ84: TRUE | FR84: TRUE
A85: BS00000049 | B85: 905409747900 | C85: 6000000000211 | D85: 안산에듀피아 | E85: 안산에듀피아(주) [경기 광덕중 외 4개교] | F85: 인프라 | G85: BTL | H85: 교육시설 | I85: 국내 | J85: 아시아 | K85: 이머징 | L85: 한국 | M85: 해당없음 | N85: 대출 | O85: 선순위 | P85: 대출 | Q85: 프로젝트 | R85: KRW | S85: KRW | T85: 39510 | U85: 45841 | V85: 45841 | W85: 45838 | X85: PPP | Y85: Availability(정부) | Z85: 정부보증 | AA85: 정부가 임대료 지급 | AB85: IBK기업은행 | AC85: 해당없음 | AD85: 이다인 | AF85: 유재섭 | AG85: 정상 | AI85: 기보유 | AJ85: 국내실물 | AK85: 인프라 | AL85: Debt | AM85: 인출 | AN85: 상환 | AO85: 0 | AP85: 6334000000 | AQ85: 0 | AR85: 0 | AS85: 0 | AT85: 0 | AU85: 0 | AV85: 0 | AW85: 0 | AX85: 0 | AY85: 0 | AZ85: 0 | BA85: 0 | BB85: 0 | BC85: 0 | BD85: 0 | BE85: 0 | BF85: 0 | BG85: 0 | BH85: 0 | BI85: 0 | BJ85: 0 | BK85: 0 | BL85: 0 | BM85: 0 | BN85: 0 | BO85: 0 | BP85: 0 | BQ85: 0 | BR85: 0 | BS85: 0 | BT85: 0 | BU85: 0 | BV85: 0 | BW85: 0 | BX85: 0 | BY85: 0 | BZ85: 0 | CA85: 0 | CB85: 0 | CC85: 0 | CD85: 0 | CE85: 0 | CF85: 0 | CG85: 0 | CH85: 0 | CI85: 0 | CJ85: 0 | CK85: 0 | CL85: 0 | CM85: 0 | CN85: 0 | CO85: 0 | CP85: 0 | CQ85: 0 | CR85: 0 | CS85: 0 | CT85: 0 | CU85: 0 | CV85: 0 | CW85: 0 | CX85: 0 | CY85: 0 | CZ85: 0 | DA85: 0 | DB85: 0 | DC85: 0 | DD85: 0 | DE85: 0 | DF85: 0 | DG85: 0 | DH85: 1 | DI85: 0 | DJ85: 0 | DK85: 0 | DL85: 0 | DM85: 0 | DN85: 0 | DO85: 0 | DP85: 0 | DQ85: 0 | DR85: 0 | DS85: 0 | DT85: 0 | DU85: 0 | DV85: 0 | DW85: 0 | DX85: 0 | DY85: 0 | DZ85: 0 | EA85: 0 | EB85: 0 | EC85: 0 | ED85: 0 | EE85: 0 | EF85: 0 | EG85: 0 | EH85: 0 | EI85: 0 | EJ85: 0 | EK85: 0 | EL85: 0 | EM85: 0 | EN85: 0 | EO85: 0 | EP85: 0 | EQ85: 0 | ER85: 450 | EU85: ~2016 | EV85: 국내대출 | EW85: 0 | EX85: 0 | EY85: 0 | EZ85: 0 | FA85: 0 | FB85: 0 | FC85: 0 | FD85: 0 | FE85: 0 | FF85: 0 | FG85: 0 | FH85: 0 | FI85: 0 | FJ85: 0 | FK85: 0 | FL85: 0 | FM85: 0 | FN85: 0 | FO85: 0 | FP85: 0 | FQ85: TRUE | FR85: TRUE
A86: BS00000049 | B86: 905409747900 | C86: 6000000000212 | D86: 안산에듀피아 | E86: 안산에듀피아(주) [경기 광덕중 외 4개교] | F86: 인프라 | G86: BTL | H86: 교육시설 | I86: 국내 | J86: 아시아 | K86: 이머징 | L86: 한국 | M86: 해당없음 | N86: 대출 | O86: 선순위 | P86: 대출 | Q86: 프로젝트 | R86: KRW | S86: KRW | T86: 39510 | U86: 45841 | V86: 45841 | W86: 45568 | X86: PPP | Y86: Availability(정부) | Z86: 정부보증 | AA86: 정부가 임대료 지급 | AB86: IBK기업은행 | AC86: 해당없음 | AD86: 이다인 | AF86: 유재섭 | AG86: 정상 | AI86: 기보유 | AJ86: 국내실물 | AK86: 인프라 | AL86: Debt | AM86: 인출 | AN86: 상환 | AO86: 0 | AP86: 3584000000 | AQ86: 0 | AR86: 0 | AS86: 0 | AT86: 0 | AU86: 0 | AV86: 0 | AW86: 0 | AX86: 0 | AY86: 0 | AZ86: 0 | BA86: 0 | BB86: 0 | BC86: 0 | BD86: 0 | BE86: 0 | BF86: 0 | BG86: 0 | BH86: 0 | BI86: 0 | BJ86: 0 | BK86: 0 | BL86: 0 | BM86: 0 | BN86: 0 | BO86: 0 | BP86: 0 | BQ86: 0 | BR86: 0 | BS86: 0 | BT86: 0 | BU86: 0 | BV86: 0 | BW86: 0 | BX86: 0 | BY86: 0 | BZ86: 0 | CA86: 0 | CB86: 0 | CC86: 0 | CD86: 0 | CE86: 0 | CF86: 0 | CG86: 0 | CH86: 0 | CI86: 0 | CJ86: 0 | CK86: 0 | CL86: 0 | CM86: 0 | CN86: 0 | CO86: 0 | CP86: 0 | CQ86: 0 | CR86: 0 | CS86: 0 | CT86: 0 | CU86: 0 | CV86: 0 | CW86: 0 | CX86: 0 | CY86: 0 | CZ86: 0 | DA86: 0 | DB86: 0 | DC86: 0 | DD86: 0 | DE86: 0 | DF86: 0 | DG86: 0 | DH86: 1 | DI86: 0 | DJ86: 0 | DK86: 0 | DL86: 0 | DM86: 0 | DN86: 0 | DO86: 0 | DP86: 0 | DQ86: 0 | DR86: 0 | DS86: 0 | DT86: 0 | DU86: 0 | DV86: 0 | DW86: 0 | DX86: 0 | DY86: 0 | DZ86: 0 | EA86: 0 | EB86: 0 | EC86: 0 | ED86: 0 | EE86: 0 | EF86: 0 | EG86: 0 | EH86: 0 | EI86: 0 | EJ86: 0 | EK86: 0 | EL86: 0 | EM86: 0 | EN86: 0 | EO86: 0 | EP86: 0 | EQ86: 0 | ER86: 450 | EU86: ~2016 | EV86: 국내대출 | EW86: 0 | EX86: 0 | EY86: 0 | EZ86: 0 | FA86: 0 | FB86: 0 | FC86: 0 | FD86: 0 | FE86: 0 | FF86: 0 | FG86: 0 | FH86: 0 | FI86: 0 | FJ86: 0 | FK86: 0 | FL86: 0 | FM86: 0 | FN86: 0 | FO86: 0 | FP86: 0 | FQ86: TRUE | FR86: TRUE
A87: BS00000050 | B87: 305409768300 | C87: 6000000000130 | D87: 안매초 외 3교 BTL (신한민자) | E87: 신한민자(주) [경기 안매초 외 3개교] | F87: 인프라 | G87: BTL | H87: 교육시설 | I87: 국내 | J87: 아시아 | K87: 이머징 | L87: 한국 | M87: 해당없음 | N87: 대출 | O87: 선순위 | P87: 대출 | Q87: 프로젝트 | R87: KRW | S87: KRW | T87: 39447 | U87: 45473 | V87: 45473 | W87: 45473 | X87: PPP | Y87: Availability(정부) | Z87: 정부보증 | AA87: 정부가 임대료 지급 | AB87: IBK기업은행 | AC87: 해당없음 | AD87: 상환/확인필요 | AF87: 유재섭 | AG87: 정상 | AI87: 기보유 | AJ87: 국내실물 | AK87: 인프라 | AL87: Debt | AM87: 인출 | AN87: 상환 | AO87: 0 | AP87: 8817000000 | AQ87: 0 | AR87: 0 | AS87: 0 | AT87: 0 | AU87: 0 | AV87: 0 | AW87: 0 | AX87: 0 | AY87: 0 | AZ87: 0 | BA87: 0 | BB87: 0 | BC87: 0 | BD87: 0 | BE87: 0 | BF87: 0 | BG87: 0 | BH87: 0 | BI87: 0 | BJ87: 0 | BK87: 0 | BL87: 0 | BM87: 0 | BN87: 0 | BO87: 0 | BP87: 0 | BQ87: 0 | BR87: 0 | BS87: 0 | BT87: 0 | BU87: 0 | BV87: 0 | BW87: 0 | BX87: 0 | BY87: 0 | BZ87: 0 | CA87: 0 | CB87: 0 | CC87: 0 | CD87: 0 | CE87: 0 | CF87: 0 | CG87: 0 | CH87: 0 | CI87: 0 | CJ87: 0 | CK87: 0 | CL87: 0 | CM87: 0 | CN87: 0 | CO87: 0 | CP87: 0 | CQ87: 0 | CR87: 0 | CS87: 0 | CT87: 0 | CU87: 0 | CV87: 0 | CW87: 0 | CX87: 0 | CY87: 0 | CZ87: 0 | DA87: 0 | DB87: 0 | DC87: 0 | DD87: 0 | DE87: 0 | DF87: 0 | DG87: 0 | DH87: 1 | DI87: 0 | DJ87: 0 | DK87: 0 | DL87: 0 | DM87: 0 | DN87: 0 | DO87: 0 | DP87: 0 | DQ87: 0 | DR87: 0 | DS87: 0 | DT87: 0 | DU87: 0 | DV87: 0 | DW87: 0 | DX87: 0 | DY87: 0 | DZ87: 0 | EA87: 0 | EB87: 0 | EC87: 0 | ED87: 0 | EE87: 0 | EF87: 0 | EG87: 0 | EH87: 0 | EI87: 0 | EJ87: 0 | EK87: 0 | EL87: 0 | EM87: 0 | EN87: 0 | EO87: 0 | EP87: 0 | EQ87: 0 | ER87: 450 | EU87: ~2016 | EV87: 국내대출 | EW87: 0 | EX87: 0 | EY87: 0 | EZ87: 0 | FA87: 0 | FB87: 0 | FC87: 0 | FD87: 0 | FE87: 0 | FF87: 0 | FG87: 0 | FH87: 0 | FI87: 0 | FJ87: 0 | FK87: 0 | FL87: 0 | FM87: 0 | FN87: 0 | FO87: 0 | FP87: 0 | FQ87: TRUE | FR87: TRUE
A88: BS00000051 | B88: BS0000005101 | C88: 100001966 | D88: 맥쿼리코리아오퍼튜니티즈 사모투자전문회사 (MKOF) | E88: MKOF | F88: 인프라 | G88: 혼합 | H88: 혼합 | I88: 국내 | J88: 아시아 | K88: 이머징 | L88: 한국 | M88: 해당없음 | N88: 출자 | O88: 지분 | P88: 주식형 | Q88: 프로젝트 | R88: KRW | S88: KRW | T88: 38799 | U88: 2958465 | V88: 2958465 | X88: 비규제자산 | Y88: Merchant(정부) | Z88: 무보증 | AA88: 무보증 | AB88: 맥쿼리코리아오퍼튜니티즈 | AC88: 해당없음 | AD88: 전희배 | AF88: 유재섭 | AG88: 관심 | AI88: 기보유 | AJ88: 국내실물 | AK88: 인프라 | AL88: Equity | AM88: 인출 | AN88: 운영 | AO88: 0 | AP88: 80000000000 | AQ88: 0 | AR88: 0 | AS88: 0 | AT88: 0 | AU88: 0 | AV88: 0 | AW88: 103499000000 | AX88: 0 | AY88: 0 | AZ88: 74636000000 | BA88: 0 | BB88: 0 | BC88: 28863000000 | BD88: 0 | BE88: 0 | BF88: 31372000000 | BG88: 0 | BH88: 0 | BI88: 0 | BJ88: 0 | BK88: 0 | BL88: 0 | BM88: 0 | BN88: 0 | BO88: 0 | BP88: 0 | BQ88: 0 | BR88: 0 | BS88: 0 | BT88: 0 | BU88: 0 | BV88: 0 | BW88: 0 | BX88: 0 | BY88: 0 | BZ88: 0 | CA88: 28863000000 | CB88: 28863000000 | CC88: 28863000000 | CD88: 0 | CE88: 69306349 | CF88: 69306349 | CG88: 69306349 | CH88: 69306349 | CI88: 69306349 | CJ88: 69306349 | CK88: 0 | CL88: 28902731708 | CM88: 2.9802322e-07 | CN88: 2.9802322e-07 | CO88: 0.76571137 | CP88: 20.654902 | CQ88: 20.654902 | CR88: 53068659 | CS88: 1.0249114 | CT88: 71032868 | CU88: 0 | CV88: 0 | CW88: 0 | CX88: 0 | CY88: 0 | CZ88: 0 | DA88: 0 | DB88: 0 | DC88: 0 | DD88: 0 | DE88: 0 | DF88: 0 | DG88: 0 | DH88: 0 | DI88: 1 | DJ88: 0 | DK88: 69306349 | DL88: 0 | DM88: 69306349 | DN88: 0 | DO88: 0 | DP88: 0 | DQ88: 0 | DR88: 0 | DS88: 0 | DT88: 0 | DU88: 0 | DV88: 69306349 | DW88: 0 | DX88: 0 | DY88: 33960111 | DZ88: 0 | EA88: 0 | EB88: 33960111 | EC88: 0.49 | ED88: 33960111 | EE88: 33960111 | EF88: 0 | EG88: 0 | EH88: 0 | EI88: 0 | EJ88: 0 | EK88: 0 | EL88: 0 | EM88: 0 | EN88: 0 | EO88: 0 | EP88: 0 | EQ88: 0 | ER88: 450 | EU88: ~2016 | EV88: 국내출자 | EW88: 0 | EX88: 0 | EY88: 0 | EZ88: 0 | FA88: 0 | FB88: 0 | FC88: 0 | FD88: 0 | FE88: 0 | FF88: 0 | FG88: 0 | FH88: 0 | FI88: 0 | FJ88: 0 | FK88: 0 | FL88: 0 | FM88: 0 | FN88: 0 | FO88: 0 | FP88: 0 | FQ88: TRUE | FR88: TRUE
A89: BS00000056 | B89: 605461108600 | C89: 6000000000330 | D89: 경남지역대학교 생활관건설 | E89: 경남지역대학교생활관건설(주) [경상대 및 창원대 생활관] | F89: 인프라 | G89: BTL | H89: 교육시설 | I89: 국내 | J89: 아시아 | K89: 이머징 | L89: 한국 | M89: 해당없음 | N89: 대출 | O89: 선순위 | P89: 대출 | Q89: 프로젝트 | R89: KRW | S89: KRW | T89: 39902 | U89: 46568 | V89: 46568 | X89: PPP | Y89: Availability(정부) | Z89: 정부보증 | AA89: 정부가 임대료 지급 | AB89: IBK기업은행 | AC89: 해당없음 | AD89: 이다인 | AF89: 유재섭 | AG89: 정상 | AH89: 39128 | AI89: 기보유 | AJ89: 국내실물 | AK89: 인프라 | AL89: Debt | AM89: 인출 | AN89: 운영 | AO89: 0 | AP89: 9223000000 | AQ89: 0 | AR89: 0 | AS89: 0 | AT89: 0 | AU89: 0 | AV89: 0 | AW89: 9223000000 | AX89: 0 | AY89: 169773000 | AZ89: 8144498743 | BA89: 0 | BB89: -169773000 | BC89: 1078501257 | BD89: 0 | BE89: 13877735 | BF89: 818969604 | BG89: 0 | BH89: 13877735 | BI89: 0 | BJ89: 0 | BK89: 0 | BL89: 11750451 | BM89: 0 | BN89: 0 | BO89: 4039504 | BP89: 11784831 | BQ89: 4039504 | BR89: 11784831 | BS89: 0 | BT89: 0 | BU89: 0 | BV89: 4039504 | BW89: 11784831 | BX89: 0.37525066 | BY89: 1.018147 | BZ89: 0 | CA89: 1078717000 | CB89: 1078717000 | CC89: 1248490000 | CD89: 0 | CE89: 1078501257 | CF89: 1078501257 | CG89: 1248240302 | CH89: 1078501257 | CI89: 1078501257 | CJ89: 1248240302 | CK89: 33955 | CL89: 0 | CM89: 0.37193508 | CN89: 4.463221 | CO89: 4.463221 | CP89: 4.0113245e+08 | CQ89: 4.8135895e+09 | CR89: 4.8135895e+09 | CS89: 1.0887964 | CT89: 1.1742683e+09 | CU89: 4.41 | CV89: 0 | CW89: 0 | CX89: 0 | CY89: 4.41 | CZ89: 4.7561905e+09 | DA89: 0 | DB89: 0 | DC89: 0 | DD89: 748698930 | DE89: 1078501257 | DF89: 0 | DG89: 0 | DH89: 1 | DI89: 0 | DJ89: 1078501257 | DK89: 0 | DL89: 1248240302 | DM89: 0 | DN89: 0 | DO89: 0 | DP89: 169773000 | DQ89: 0 | DR89: 0 | DS89: 0 | DT89: 0 | DU89: 0 | DV89: 1.5932768e+09 | DW89: 0 | DX89: 0 | DY89: 0 | DZ89: 0 | EA89: 0 | EB89: 0 | EC89: 0 | ED89: 0 | EE89: 0 | EF89: 0 | EG89: 4039504 | EH89: 0 | EI89: 0 | EJ89: 0 | EK89: 0 | EL89: 11784831 | EM89: 0 | EN89: 0 | EO89: 0 | EP89: 4039504 | EQ89: 11784831 | ER89: 346 | EU89: ~2016 | EV89: 국내대출 | EW89: 0 | EX89: 4039504 | EY89: 0 | EZ89: 0 | FA89: 0 | FB89: 0 | FC89: 11784831 | FD89: 0 | FE89: 0 | FF89: 0 | FG89: 0 | FH89: 0 | FI89: 0 | FJ89: 0 | FK89: 0 | FL89: 0 | FM89: 0 | FN89: 0 | FO89: 0 | FP89: 0 | FQ89: TRUE | FR89: TRUE
